Workbook

Sheet Index
A1: event_value | B1: schema_title | C1: api_version | D1: borana_schema_id | E1: mugie_schema | F1: icon_id | G1: image_url | H1: n_fields | I1: n_enums | J1: event_name | K1: event_category_display | L1: event_category_id | M1: event_updated_at | N1: sheet_name | O1: Open
A2: fatality | B2: EventType Test Data | C2: v1 | D2: =VLOOKUP(A2, borana_schemas!A:D, 4, FALSE) -> https://borana.pamdas.org/api/v1.0/activity/events/schema/eventtype/fatality | E2: =VLOOKUP(A2, mugie_schemas!A:D, 4, FALSE) -> #N/A | F2: human_activities_observation_rep | H2: 16 | I2: 5 | J2: Fatality | K2: Accident & Emergency | L2: fb9ee509-1dac-42ca-b0ec-7428d6a83214 | N2: fatality | O2: =HYPERLINK("#'fatality'!A1","Open") -> Open
A3: medical_evacuation_report | B3: EventType Test Data | C3: v1 | D3: =VLOOKUP(A3, borana_schemas!A:D, 4, FALSE) -> https://borana.pamdas.org/api/v1.0/activity/events/schema/eventtype/medical_evacuation_report | E3: =VLOOKUP(A3, mugie_schemas!A:D, 4, FALSE) -> #N/A | F3: medevac_rep | H3: 13 | I3: 3 | J3: Medical Evacuation | K3: Accident & Emergency | L3: fb9ee509-1dac-42ca-b0ec-7428d6a83214 | N3: medical_evacuation_report | O3: =HYPERLINK("#'medical_evacuation_report'!A1","Open") -> Open
A4: missing_persons | B4: EventType Test Data | C4: v1 | D4: =VLOOKUP(A4, borana_schemas!A:D, 4, FALSE) -> https://borana.pamdas.org/api/v1.0/activity/events/schema/eventtype/missing_persons | E4: =VLOOKUP(A4, mugie_schemas!A:D, 4, FALSE) -> #N/A | F4: missing_person_rep | H4: 19 | I4: 4 | J4: Missing Person(s) | K4: Accident & Emergency | L4: fb9ee509-1dac-42ca-b0ec-7428d6a83214 | N4: missing_persons | O4: =HYPERLINK("#'missing_persons'!A1","Open") -> Open
A5: mist_rep | B5: EventType Test Data | C5: v1 | D5: =VLOOKUP(A5, borana_schemas!A:D, 4, FALSE) -> https://borana.pamdas.org/api/v1.0/activity/events/schema/eventtype/mist_rep | E5: =VLOOKUP(A5, mugie_schemas!A:D, 4, FALSE) -> #N/A | F5: mist_rep | H5: 12 | I5: 3 | J5: ATMIST | K5: Accident & Emergency | L5: fb9ee509-1dac-42ca-b0ec-7428d6a83214 | N5: mist_rep | O5: =HYPERLINK("#'mist_rep'!A1","Open") -> Open
A6: vehicle_accident_rep | B6: EventType Test Data | C6: v1 | D6: =VLOOKUP(A6, borana_schemas!A:D, 4, FALSE) -> https://borana.pamdas.org/api/v1.0/activity/events/schema/eventtype/vehicle_accident_rep | E6: =VLOOKUP(A6, mugie_schemas!A:D, 4, FALSE) -> #N/A | F6: accident_rep | H6: 21 | I6: 5 | J6: Vehicle Accident | K6: Accident & Emergency | L6: fb9ee509-1dac-42ca-b0ec-7428d6a83214 | N6: vehicle_accident_rep | O6: =HYPERLINK("#'vehicle_accident_rep'!A1","Open") -> Open
A7: wild_fire | B7: Wild Fire Report | C7: v1 | D7: =VLOOKUP(A7, borana_schemas!A:D, 4, FALSE) -> https://borana.pamdas.org/api/v1.0/activity/events/schema/eventtype/wild_fire | E7: =VLOOKUP(A7, mugie_schemas!A:D, 4, FALSE) -> #N/A | F7: fire_rep | H7: 12 | I7: 6 | J7: Wild Fire | K7: Accident & Emergency | N7: wild_fire | O7: =HYPERLINK("#'wild_fire'!A1","Open") -> Open
A8: atmist_backup | B8: ATMIST | C8: v1 | D8: =VLOOKUP(A8, borana_schemas!A:D, 4, FALSE) -> https://borana.pamdas.org/api/v1.0/activity/events/schema/eventtype/atmist_backup | E8: =VLOOKUP(A8, mugie_schemas!A:D, 4, FALSE) -> #N/A | F8: mist_rep | H8: 13 | I8: 2 | J8: ATMIST | K8: Accident & Emergency OpsRoom | L8: 781bea94-4fdc-450d-8283-cbf77dfe3763 | N8: atmist_backup | O8: =HYPERLINK("#'atmist_backup'!A1","Open") -> Open
A9: fatality_backup | B9: EventType Test Data | C9: v1 | D9: =VLOOKUP(A9, borana_schemas!A:D, 4, FALSE) -> https://borana.pamdas.org/api/v1.0/activity/events/schema/eventtype/fatality_backup | E9: =VLOOKUP(A9, mugie_schemas!A:D, 4, FALSE) -> #N/A | F9: human_activities_observation_rep | H9: 17 | I9: 4 | J9: Fatality | K9: Accident & Emergency OpsRoom | L9: 781bea94-4fdc-450d-8283-cbf77dfe3763 | N9: fatality_backup | O9: =HYPERLINK("#'fatality_backup'!A1","Open") -> Open
A10: med_evac_backup | B10: EventType Test Data | C10: v1 | D10: =VLOOKUP(A10, borana_schemas!A:D, 4, FALSE) -> https://borana.pamdas.org/api/v1.0/activity/events/schema/eventtype/med_evac_backup | E10: =VLOOKUP(A10, mugie_schemas!A:D, 4, FALSE) -> #N/A | F10: medevac_request_rep | H10: 14 | I10: 2 | J10: Medical Evacuation | K10: Accident & Emergency OpsRoom | L10: 781bea94-4fdc-450d-8283-cbf77dfe3763 | N10: med_evac_backup | O10: =HYPERLINK("#'med_evac_backup'!A1","Open") -> Open
A11: missing_person_backup | B11: EventType Test Data | C11: v1 | D11: =VLOOKUP(A11, borana_schemas!A:D, 4, FALSE) -> https://borana.pamdas.org/api/v1.0/activity/events/schema/eventtype/missing_person_backup | E11: =VLOOKUP(A11, mugie_schemas!A:D, 4, FALSE) -> #N/A | F11: missing_person_rep | H11: 20 | I11: 3 | J11: Missing Person(s) | K11: Accident & Emergency OpsRoom | L11: 781bea94-4fdc-450d-8283-cbf77dfe3763 | N11: missing_person_backup | O11: =HYPERLINK("#'missing_person_backup'!A1","Open") -> Open
A12: veh_acc_backup | B12: EventType Test Data | C12: v1 | D12: =VLOOKUP(A12, borana_schemas!A:D, 4, FALSE) -> https://borana.pamdas.org/api/v1.0/activity/events/schema/eventtype/veh_acc_backup | E12: =VLOOKUP(A12, mugie_schemas!A:D, 4, FALSE) -> #N/A | F12: accident_rep | H12: 22 | I12: 4 | J12: Vehicle Accident | K12: Accident & Emergency OpsRoom | L12: 781bea94-4fdc-450d-8283-cbf77dfe3763 | N12: veh_acc_backup | O12: =HYPERLINK("#'veh_acc_backup'!A1","Open") -> Open
A13: wildfire_backup | B13: Wild Fire Report | C13: v1 | D13: =VLOOKUP(A13, borana_schemas!A:D, 4, FALSE) -> https://borana.pamdas.org/api/v1.0/activity/events/schema/eventtype/wildfire_backup | E13: =VLOOKUP(A13, mugie_schemas!A:D, 4, FALSE) -> #N/A | F13: fire_rep | H13: 13 | I13: 5 | J13: Wild Fire | K13: Accident & Emergency OpsRoom | N13: wildfire_backup | O13: =HYPERLINK("#'wildfire_backup'!A1","Open") -> Open
A14: air_ops_boma_sighting | B14: Boma Sighting | C14: v1 | D14: =VLOOKUP(A14, borana_schemas!A:D, 4, FALSE) -> https://borana.pamdas.org/api/v1.0/activity/events/schema/eventtype/air_ops_boma_sighting | E14: =VLOOKUP(A14, mugie_schemas!A:D, 4, FALSE) -> #N/A | F14: boma_rep | H14: 8 | I14: 2 | J14: Boma Sighting | K14: Air Ops | N14: air_ops_boma_sighting | O14: =HYPERLINK("#'air_ops_boma_sighting'!A1","Open") -> Open
A15: air_ops_camel_sighting | B15: Camel Sighting | C15: v1 | D15: =VLOOKUP(A15, borana_schemas!A:D, 4, FALSE) -> https://borana.pamdas.org/api/v1.0/activity/events/schema/eventtype/air_ops_camel_sighting | E15: =VLOOKUP(A15, mugie_schemas!A:D, 4, FALSE) -> #N/A | F15: air_ops_camel_sighting | H15: 3 | I15: 0 | J15: Camel Sighting | K15: Air Ops | N15: air_ops_camel_sighting | O15: =HYPERLINK("#'air_ops_camel_sighting'!A1","Open") -> Open
A16: air_ops_cattle_sighting | B16: Cattle Sighting | C16: v1 | D16: =VLOOKUP(A16, borana_schemas!A:D, 4, FALSE) -> https://borana.pamdas.org/api/v1.0/activity/events/schema/eventtype/air_ops_cattle_sighting | E16: =VLOOKUP(A16, mugie_schemas!A:D, 4, FALSE) -> #N/A | F16: bull_rep | H16: 3 | I16: 0 | J16: Cattle Sighting | K16: Air Ops | N16: air_ops_cattle_sighting | O16: =HYPERLINK("#'air_ops_cattle_sighting'!A1","Open") -> Open
A17: air_ops_elephant_carcass | B17: Elephant Carcass | C17: v1 | D17: =VLOOKUP(A17, borana_schemas!A:D, 4, FALSE) -> https://borana.pamdas.org/api/v1.0/activity/events/schema/eventtype/air_ops_elephant_carcass | E17: =VLOOKUP(A17, mugie_schemas!A:D, 4, FALSE) -> #N/A | F17: elephant_mortality_rep | H17: 4 | I17: 2 | J17: Elephant Carcass | K17: Air Ops | N17: air_ops_elephant_carcass | O17: =HYPERLINK("#'air_ops_elephant_carcass'!A1","Open") -> Open
A18: air_ops_logging | B18: Logging | C18: v1 | D18: =VLOOKUP(A18, borana_schemas!A:D, 4, FALSE) -> https://borana.pamdas.org/api/v1.0/activity/events/schema/eventtype/air_ops_logging | E18: =VLOOKUP(A18, mugie_schemas!A:D, 4, FALSE) -> #N/A | F18: deforestation_rep | H18: 6 | I18: 3 | J18: Logging | K18: Air Ops | N18: air_ops_logging | O18: =HYPERLINK("#'air_ops_logging'!A1","Open") -> Open
A19: air_ops_people_sighting | B19: People Sighting | C19: v1 | D19: =VLOOKUP(A19, borana_schemas!A:D, 4, FALSE) -> https://borana.pamdas.org/api/v1.0/activity/events/schema/eventtype/air_ops_people_sighting | E19: =VLOOKUP(A19, mugie_schemas!A:D, 4, FALSE) -> #N/A | F19: suspicious_person_rep | H19: 5 | I19: 2 | J19: People Sighting | K19: Air Ops | N19: air_ops_people_sighting | O19: =HYPERLINK("#'air_ops_people_sighting'!A1","Open") -> Open
A20: air_ops_shoat_sighting | B20: Shoats Sighting | C20: v1 | D20: =VLOOKUP(A20, borana_schemas!A:D, 4, FALSE) -> https://borana.pamdas.org/api/v1.0/activity/events/schema/eventtype/air_ops_shoat_sighting | E20: =VLOOKUP(A20, mugie_schemas!A:D, 4, FALSE) -> #N/A | F20: goat_rep | H20: 3 | I20: 0 | J20: Shoat Sighting | K20: Air Ops | N20: air_ops_shoat_sighting | O20: =HYPERLINK("#'air_ops_shoat_sighting'!A1","Open") -> Open
A21: air_ops_wildlife_carcass | B21: Wildlife Carcass | C21: v1 | D21: =VLOOKUP(A21, borana_schemas!A:D, 4, FALSE) -> https://borana.pamdas.org/api/v1.0/activity/events/schema/eventtype/air_ops_wildlife_carcass | E21: =VLOOKUP(A21, mugie_schemas!A:D, 4, FALSE) -> #N/A | F21: carcass_rep | H21: 5 | I21: 2 | J21: Wildlife Carcass | K21: Air Ops | N21: air_ops_wildlife_carcass | O21: =HYPERLINK("#'air_ops_wildlife_carcass'!A1","Open") -> Open
A22: air_ops_wildlife_sighting | B22: Other Wildlife Sighting | C22: v1 | D22: =VLOOKUP(A22, borana_schemas!A:D, 4, FALSE) -> https://borana.pamdas.org/api/v1.0/activity/events/schema/eventtype/air_ops_wildlife_sighting | E22: =VLOOKUP(A22, mugie_schemas!A:D, 4, FALSE) -> #N/A | F22: other_wildlife_sightings_rep | H22: 2 | I22: 1 | J22: Wildlife Sighting | K22: Air Ops | N22: air_ops_wildlife_sighting | O22: =HYPERLINK("#'air_ops_wildlife_sighting'!A1","Open") -> Open
A23: charcoal_kiln | B23: Charcoal Kiln | C23: v1 | D23: =VLOOKUP(A23, borana_schemas!A:D, 4, FALSE) -> https://borana.pamdas.org/api/v1.0/activity/events/schema/eventtype/charcoal_kiln | E23: =VLOOKUP(A23, mugie_schemas!A:D, 4, FALSE) -> #N/A | F23: charcoal_kiln_rep | H23: 4 | I23: 1 | J23: Charcoal Kiln | K23: Air Ops | N23: charcoal_kiln | O23: =HYPERLINK("#'charcoal_kiln'!A1","Open") -> Open
A24: degraded_area | B24: Erosion Report Report | C24: v1 | D24: =VLOOKUP(A24, borana_schemas!A:D, 4, FALSE) -> https://borana.pamdas.org/api/v1.0/activity/events/schema/eventtype/degraded_area | E24: =VLOOKUP(A24, mugie_schemas!A:D, 4, FALSE) -> #N/A | F24: spur-trail_rep | H24: 10 | I24: 4 | J24: Degraded Area | K24: Air Ops | N24: degraded_area | O24: =HYPERLINK("#'degraded_area'!A1","Open") -> Open
A25: nesting_site | B25: EventType Test Data | C25: v1 | E25: =VLOOKUP(A25, mugie_schemas!A:D, 4, FALSE) -> https://mugie.pamdas.org/api/v1.0/activity/events/schema/eventtype/nesting_site | F25: nest_rep | G25: https://mugie.pamdas.org/static/sprite-src/nest_rep.svg | H25: 5 | I25: 1 | J25: Nesting Site | K25: Avian Events | L25: 87b9675f-312c-4985-a5bf-38ff4423146e | N25: nesting_site | O25: =HYPERLINK("#'nesting_site'!A1","Open") -> Open
A26: raptor_sighting | B26: EventType Test Data | C26: v1 | E26: =VLOOKUP(A26, mugie_schemas!A:D, 4, FALSE) -> https://mugie.pamdas.org/api/v1.0/activity/events/schema/eventtype/raptor_sighting | F26: hawk_rep | G26: https://mugie.pamdas.org/static/sprite-src/hawk_rep.svg | H26: 9 | I26: 4 | J26: Raptor Sighting | K26: Avian Events | L26: 87b9675f-312c-4985-a5bf-38ff4423146e | N26: raptor_sighting | O26: =HYPERLINK("#'raptor_sighting'!A1","Open") -> Open
A27: disease_rep | B27: Disease Monitoring Report | C27: v1 | D27: =VLOOKUP(A27, borana_schemas!A:D, 4, FALSE) -> https://borana.pamdas.org/api/v1.0/activity/events/schema/eventtype/disease_rep | E27: =VLOOKUP(A27, mugie_schemas!A:D, 4, FALSE) -> #N/A | F27: disease_rep | H27: 13 | I27: 9 | J27: Disease Monitoring | K27: Bio And Eco Monitoring | N27: disease_rep | O27: =HYPERLINK("#'disease_rep'!A1","Open") -> Open
A28: elephant_incident_vrf | B28: Rangelands Report (rangelands_rep) | C28: v1 | D28: =VLOOKUP(A28, borana_schemas!A:D, 4, FALSE) -> https://borana.pamdas.org/api/v1.0/activity/events/schema/eventtype/elephant_incident_vrf | E28: =VLOOKUP(A28, mugie_schemas!A:D, 4, FALSE) -> #N/A | F28: animalfence_rep | H28: 12 | I28: 6 | J28: Elephant Incident Verification | K28: Bio And Eco Monitoring | N28: elephant_incident_vrf | O28: =HYPERLINK("#'elephant_incident_vrf'!A1","Open") -> Open
A29: elephant_mortality | B29: Elephant Mortality | C29: v1 | D29: =VLOOKUP(A29, borana_schemas!A:D, 4, FALSE) -> https://borana.pamdas.org/api/v1.0/activity/events/schema/eventtype/elephant_mortality | E29: =VLOOKUP(A29, mugie_schemas!A:D, 4, FALSE) -> #N/A | F29: elephant_mortality | H29: 28 | I29: 15 | J29: Elephant Mortality | K29: Bio And Eco Monitoring | L29: 03cc816c-724a-4365-8eb7-3a09843ff196 | N29: elephant_mortality | O29: =HYPERLINK("#'elephant_mortality'!A1","Open") -> Open
A30: eov_monitoring | B30: EOV Monitoring | C30: v1 | D30: =VLOOKUP(A30, borana_schemas!A:D, 4, FALSE) -> https://borana.pamdas.org/api/v1.0/activity/events/schema/eventtype/eov_monitoring | E30: =VLOOKUP(A30, mugie_schemas!A:D, 4, FALSE) -> #N/A | F30: corridor_clearance_rep | H30: 24 | I30: 19 | J30: EOV | K30: Bio And Eco Monitoring | L30: 03cc816c-724a-4365-8eb7-3a09843ff196 | N30: eov_monitoring | O30: =HYPERLINK("#'eov_monitoring'!A1","Open") -> Open
A31: injured_abandoned_rep | B31: Injured Abandoned Animal Report | C31: v1 | D31: =VLOOKUP(A31, borana_schemas!A:D, 4, FALSE) -> https://borana.pamdas.org/api/v1.0/activity/events/schema/eventtype/injured_abandoned_rep | E31: =VLOOKUP(A31, mugie_schemas!A:D, 4, FALSE) -> #N/A | F31: mist_rep | H31: 13 | I31: 6 | J31: Injured/Abandoned Animal | K31: Bio And Eco Monitoring | N31: injured_abandoned_rep | O31: =HYPERLINK("#'injured_abandoned_rep'!A1","Open") -> Open
A32: invasive_rep | B32: Invasive Alien Plants Report | C32: v1 | D32: =VLOOKUP(A32, borana_schemas!A:D, 4, FALSE) -> https://borana.pamdas.org/api/v1.0/activity/events/schema/eventtype/invasive_rep | E32: https://mugie.pamdas.org/api/v1.0/activity/events/schema/eventtype/invasive_species_rep | F32: invasive_species_rep | H32: 17 | I32: 10 | J32: Invasive Alien Plant Species | K32: Bio And Eco Monitoring | N32: invasive_rep | O32: =HYPERLINK("#'invasive_rep'!A1","Open") -> Open
A33: lewa_postmortem_rep | B33: Post Mortem Report | C33: v1 | D33: =VLOOKUP(A33, borana_schemas!A:D, 4, FALSE) -> https://borana.pamdas.org/api/v1.0/activity/events/schema/eventtype/lewa_postmortem_rep | E33: =VLOOKUP(A33, mugie_schemas!A:D, 4, FALSE) -> #N/A | F33: lewa_postmortem_rep | H33: 13 | I33: 4 | J33: Post Mortem | K33: Bio And Eco Monitoring | N33: lewa_postmortem_rep | O33: =HYPERLINK("#'lewa_postmortem_rep'!A1","Open") -> Open
A34: lion_sighting | B34: EventType Test Data | C34: v1 | D34: =VLOOKUP(A34, borana_schemas!A:D, 4, FALSE) -> https://borana.pamdas.org/api/v1.0/activity/events/schema/eventtype/lion_sighting | E34: =VLOOKUP(A34, mugie_schemas!A:D, 4, FALSE) -> https://mugie.pamdas.org/api/v1.0/activity/events/schema/eventtype/lion_sighting | F34: lion_sighting_rep | H34: 21 | I34: 15 | J34: Lion Sighting | K34: Bio And Eco Monitoring | L34: 03cc816c-724a-4365-8eb7-3a09843ff196 | N34: lion_sighting | O34: =HYPERLINK("#'lion_sighting'!A1","Open") -> Open
A35: mgt_burn_rep | B35: Controlled Burn Report | C35: v1 | D35: =VLOOKUP(A35, borana_schemas!A:D, 4, FALSE) -> https://borana.pamdas.org/api/v1.0/activity/events/schema/eventtype/mgt_burn_rep | E35: =VLOOKUP(A35, mugie_schemas!A:D, 4, FALSE) -> #N/A | F35: burn_rep | H35: 15 | I35: 7 | J35: Controlled Burn | K35: Bio And Eco Monitoring | N35: mgt_burn_rep | O35: =HYPERLINK("#'mgt_burn_rep'!A1","Open") -> Open
A36: rainfall_rep | B36: Rainfall Report Report | C36: v1 | D36: =VLOOKUP(A36, borana_schemas!A:D, 4, FALSE) -> https://borana.pamdas.org/api/v1.0/activity/events/schema/eventtype/rainfall_rep | E36: =VLOOKUP(A36, mugie_schemas!A:D, 4, FALSE) -> #N/A | F36: rainfall_rep | H36: 4 | I36: 2 | J36: Rainfall Report | K36: Bio And Eco Monitoring | N36: rainfall_rep | O36: =HYPERLINK("#'rainfall_rep'!A1","Open") -> Open
A37: resource_use | B37: Resource Use Report | C37: v1 | D37: =VLOOKUP(A37, borana_schemas!A:D, 4, FALSE) -> https://borana.pamdas.org/api/v1.0/activity/events/schema/eventtype/resource_use | E37: =VLOOKUP(A37, mugie_schemas!A:D, 4, FALSE) -> #N/A | F37: resource_use | H37: 7 | I37: 5 | J37: Resource Use | K37: Bio And Eco Monitoring | N37: resource_use | O37: =HYPERLINK("#'resource_use'!A1","Open") -> Open
A38: soil_mentor_basic | B38: Soil Mentor Report | C38: v1 | D38: =VLOOKUP(A38, borana_schemas!A:D, 4, FALSE) -> https://borana.pamdas.org/api/v1.0/activity/events/schema/eventtype/soil_mentor_basic | E38: =VLOOKUP(A38, mugie_schemas!A:D, 4, FALSE) -> #N/A | F38: vulva_inspection_rep | H38: 37 | I38: 11 | J38: Soil Mentor Basic | K38: Bio And Eco Monitoring | N38: soil_mentor_basic | O38: =HYPERLINK("#'soil_mentor_basic'!A1","Open") -> Open
A39: soil_qual_test | B39: Soil Quality Test | C39: v1 | D39: =VLOOKUP(A39, borana_schemas!A:D, 4, FALSE) -> https://borana.pamdas.org/api/v1.0/activity/events/schema/eventtype/soil_qual_test | E39: =VLOOKUP(A39, mugie_schemas!A:D, 4, FALSE) -> #N/A | F39: generic_rep | H39: 16 | I39: 3 | J39: Soil Quality Test | K39: Bio And Eco Monitoring | N39: soil_qual_test | O39: =HYPERLINK("#'soil_qual_test'!A1","Open") -> Open
A40: wildlife_mortality | B40: EventType Test Data | C40: v1 | D40: =VLOOKUP(A40, borana_schemas!A:D, 4, FALSE) -> https://borana.pamdas.org/api/v1.0/activity/events/schema/eventtype/wildlife_mortality | E40: =VLOOKUP(A40, mugie_schemas!A:D, 4, FALSE) -> #N/A | F40: carcass_rep | H40: 13 | I40: 6 | J40: Wildlife Mortality | K40: Bio And Eco Monitoring | L40: 03cc816c-724a-4365-8eb7-3a09843ff196 | N40: wildlife_mortality | O40: =HYPERLINK("#'wildlife_mortality'!A1","Open") -> Open
A41: wildlife_sighting_rep | B41: Wildlife Sighting Report | C41: v1 | D41: =VLOOKUP(A41, borana_schemas!A:D, 4, FALSE) -> https://borana.pamdas.org/api/v1.0/activity/events/schema/eventtype/wildlife_sighting_rep | E41: =VLOOKUP(A41, mugie_schemas!A:D, 4, FALSE) -> #N/A | F41: mammals_observation | H41: 10 | I41: 4 | J41: Wildlife Sighting | K41: Bio And Eco Monitoring | N41: wildlife_sighting_rep | O41: =HYPERLINK("#'wildlife_sighting_rep'!A1","Open") -> Open
A42: community_activity_report | B42: Community Activity Log | C42: v1 | D42: =VLOOKUP(A42, borana_schemas!A:D, 4, FALSE) -> https://borana.pamdas.org/api/v1.0/activity/events/schema/eventtype/community_activity_report | E42: =VLOOKUP(A42, mugie_schemas!A:D, 4, FALSE) -> #N/A | F42: operation_rep | H42: 20 | I42: 4 | J42: Community Activity Report | K42: Community Engagement | N42: community_activity_report | O42: =HYPERLINK("#'community_activity_report'!A1","Open") -> Open
A43: community_request | B43: Community Request | C43: v1 | D43: =VLOOKUP(A43, borana_schemas!A:D, 4, FALSE) -> https://borana.pamdas.org/api/v1.0/activity/events/schema/eventtype/community_request | E43: =VLOOKUP(A43, mugie_schemas!A:D, 4, FALSE) -> #N/A | F43: radio_rep | H43: 5 | I43: 1 | J43: Community Request | K43: Community Engagement | N43: community_request | O43: =HYPERLINK("#'community_request'!A1","Open") -> Open
A44: monthly_community_activity_summary | B44: Monthly Community Activity Summary | C44: v1 | D44: =VLOOKUP(A44, borana_schemas!A:D, 4, FALSE) -> https://borana.pamdas.org/api/v1.0/activity/events/schema/eventtype/monthly_community_activity_summary | E44: =VLOOKUP(A44, mugie_schemas!A:D, 4, FALSE) -> #N/A | F44: all_posts_rep | H44: 19 | I44: 1 | J44: Monthly Community Activity Summary | K44: Community Engagement | N44: monthly_community_activity_summ | O44: =HYPERLINK("#'monthly_community_activity_summ'!A1","Open") -> Open
A45: water_dispensation | B45: Water Dispensation | C45: v1 | D45: =VLOOKUP(A45, borana_schemas!A:D, 4, FALSE) -> https://borana.pamdas.org/api/v1.0/activity/events/schema/eventtype/water_dispensation | E45: =VLOOKUP(A45, mugie_schemas!A:D, 4, FALSE) -> #N/A | F45: water_rep | H45: 5 | I45: 1 | J45: Water Dispensation | K45: Community Engagement | N45: water_dispensation | O45: =HYPERLINK("#'water_dispensation'!A1","Open") -> Open
A46: sandalwood | B46: Placeholder schema | C46: v1 | E46: =VLOOKUP(A46, mugie_schemas!A:D, 4, FALSE) -> https://mugie.pamdas.org/api/v1.0/activity/events/schema/eventtype/sandalwood | F46: natural_feature_rep | G46: https://mugie.pamdas.org/static/sprite-src/natural_feature_rep.svg | H46: 2 | I46: 0 | J46: Sandalwood | K46: Bio And Eco Monitoring | L46: 748f7f8a-1a22-4300-9229-b7e15e7ec142 | N46: sandalwood | O46: =HYPERLINK("#'sandalwood'!A1","Open") -> Open
A47: illegal_grazing | B47: Illegal grazing Report | C47: v1 | E47: https://mugie.pamdas.org/api/v1.0/activity/events/schema/eventtype/illegal_grazing | F47: activity_rep | G47: https://mugie.pamdas.org/static/sprite-src/activity_rep.svg | H47: 7 | I47: 3 | J47: Illegal Grazing | K47: Law Enforcement | L47: 748f7f8a-1a22-4300-9229-b7e15e7ec142 | N47: illegal_grazing | O47: =HYPERLINK("#'illegal_grazing'!A1","Open") -> Open
A48: on_transit | B48: Livestock On transit | C48: v1 | E48: https://mugie.pamdas.org/api/v1.0/activity/events/schema/eventtype/on_transit | F48: livestock_movement_rep | G48: https://mugie.pamdas.org/static/sprite-src/livestock_movement_rep.svg | H48: 6 | I48: 1 | J48: Livestock On Transit | K48: Law Enforcement | L48: 748f7f8a-1a22-4300-9229-b7e15e7ec142 | M48: TRUE | N48: on_transit | O48: =HYPERLINK("#'on_transit'!A1","Open") -> Open
A49: recoveriestrophies | B49: EventType Recoveries - Trophies (confiscationtrophies_rep) | C49: v1 | E49: https://mugie.pamdas.org/api/v1.0/activity/events/schema/eventtype/recoveriestrophies | F49: recoveriestrophies | G49: https://mugie.pamdas.org/static/generic-black.svg | H49: 30 | I49: 0 | J49: Recoveries - Trophies | K49: Law Enforcement | L49: 748f7f8a-1a22-4300-9229-b7e15e7ec142 | M49: TRUE | N49: recoveriestrophies | O49: =HYPERLINK("#'recoveriestrophies'!A1","Open") -> Open
A50: trespassing | B50: Trespassing Report | C50: v1 | E50: https://mugie.pamdas.org/api/v1.0/activity/events/schema/eventtype/trespassing | F50: crossing_rep | G50: https://mugie.pamdas.org/static/sprite-src/crossing_rep.svg | H50: 5 | I50: 2 | J50: Trespassing | K50: Law Enforcement | L50: 748f7f8a-1a22-4300-9229-b7e15e7ec142 | M50: TRUE | N50: trespassing | O50: =HYPERLINK("#'trespassing'!A1","Open") -> Open
A51: baton_rep | B51: Baton Report | C51: v1 | D51: =VLOOKUP(A51, borana_schemas!A:D, 4, FALSE) -> https://borana.pamdas.org/api/v1.0/activity/events/schema/eventtype/baton_rep | E51: =VLOOKUP(A51, mugie_schemas!A:D, 4, FALSE) -> https://mugie.pamdas.org/api/v1.0/activity/events/schema/eventtype/baton_rep | F51: ranger_shot_rep | H51: 10 | I51: 5 | J51: Baton Report | K51: HWC | L51: 97172f47-979e-40ff-ad0a-8e4103b3ea7c | N51: baton_rep | O51: =HYPERLINK("#'baton_rep'!A1","Open") -> Open
A52: hwc_crop_verification | B52: EventType Test Data | C52: v1 | D52: =VLOOKUP(A52, borana_schemas!A:D, 4, FALSE) -> https://borana.pamdas.org/api/v1.0/activity/events/schema/eventtype/hwc_crop_verification | E52: =VLOOKUP(A52, mugie_schemas!A:D, 4, FALSE) -> #N/A | F52: all_posts_rep | H52: 34 | I52: 13 | J52: HWC Crop Damage Verification | K52: HWC | L52: 97172f47-979e-40ff-ad0a-8e4103b3ea7c | N52: hwc_crop_verification | O52: =HYPERLINK("#'hwc_crop_verification'!A1","Open") -> Open
A53: hwc_crops | B53: EventType Test Data | C53: v1 | D53: =VLOOKUP(A53, borana_schemas!A:D, 4, FALSE) -> https://borana.pamdas.org/api/v1.0/activity/events/schema/eventtype/hwc_crops | E53: =VLOOKUP(A53, mugie_schemas!A:D, 4, FALSE) -> https://mugie.pamdas.org/api/v1.0/activity/events/schema/eventtype/hwc_crops | F53: hwc_alert_rep | H53: 24 | I53: 7 | J53: HWC Crop Damage | K53: HWC | L53: 97172f47-979e-40ff-ad0a-8e4103b3ea7c | N53: hwc_crops | O53: =HYPERLINK("#'hwc_crops'!A1","Open") -> Open
A54: hwc_human_death | B54: EventType Test Data | C54: v1 | D54: =VLOOKUP(A54, borana_schemas!A:D, 4, FALSE) -> https://borana.pamdas.org/api/v1.0/activity/events/schema/eventtype/hwc_human_death | E54: =VLOOKUP(A54, mugie_schemas!A:D, 4, FALSE) -> https://mugie.pamdas.org/api/v1.0/activity/events/schema/eventtype/hwc_human_death | F54: hwc_alert_rep | H54: 20 | I54: 9 | J54: HWC Human Death | K54: HWC | L54: 97172f47-979e-40ff-ad0a-8e4103b3ea7c | N54: hwc_human_death | O54: =HYPERLINK("#'hwc_human_death'!A1","Open") -> Open
A55: hwc_human_death_verification | B55: EventType Test Data | C55: v1 | D55: =VLOOKUP(A55, borana_schemas!A:D, 4, FALSE) -> https://borana.pamdas.org/api/v1.0/activity/events/schema/eventtype/hwc_human_death_verification | E55: =VLOOKUP(A55, mugie_schemas!A:D, 4, FALSE) -> #N/A | F55: all_posts_rep | H55: 36 | I55: 11 | J55: HWC Human Death Verification | K55: HWC | L55: 97172f47-979e-40ff-ad0a-8e4103b3ea7c | N55: hwc_human_death_verification | O55: =HYPERLINK("#'hwc_human_death_verification'!A1","Open") -> Open
A56: hwc_human_injury | B56: EventType Test Data | C56: v1 | D56: =VLOOKUP(A56, borana_schemas!A:D, 4, FALSE) -> https://borana.pamdas.org/api/v1.0/activity/events/schema/eventtype/hwc_human_injury | E56: =VLOOKUP(A56, mugie_schemas!A:D, 4, FALSE) -> https://mugie.pamdas.org/api/v1.0/activity/events/schema/eventtype/hwc_human_injury | F56: hwc_alert_rep | H56: 20 | I56: 10 | J56: HWC Human Injury | K56: HWC | L56: 97172f47-979e-40ff-ad0a-8e4103b3ea7c | N56: hwc_human_injury | O56: =HYPERLINK("#'hwc_human_injury'!A1","Open") -> Open
A57: hwc_human_injury_verification | B57: EventType Test Data | C57: v1 | D57: =VLOOKUP(A57, borana_schemas!A:D, 4, FALSE) -> https://borana.pamdas.org/api/v1.0/activity/events/schema/eventtype/hwc_human_injury_verification | E57: =VLOOKUP(A57, mugie_schemas!A:D, 4, FALSE) -> #N/A | F57: all_posts_rep | H57: 37 | I57: 12 | J57: HWC Human Injury Verification | K57: HWC | L57: 97172f47-979e-40ff-ad0a-8e4103b3ea7c | N57: hwc_human_injury_verification | O57: =HYPERLINK("#'hwc_human_injury_verification'!A1","Open") -> Open
A58: hwc_livestock | B58: EventType Test Data | C58: v1 | D58: =VLOOKUP(A58, borana_schemas!A:D, 4, FALSE) -> https://borana.pamdas.org/api/v1.0/activity/events/schema/eventtype/hwc_livestock | E58: =VLOOKUP(A58, mugie_schemas!A:D, 4, FALSE) -> #N/A | F58: lion_carcass_rep | H58: 22 | I58: 7 | J58: HWC Livestock Predation | K58: HWC | L58: 97172f47-979e-40ff-ad0a-8e4103b3ea7c | N58: hwc_livestock | O58: =HYPERLINK("#'hwc_livestock'!A1","Open") -> Open
A59: hwc_livestock_verification | B59: EventType Test Data | C59: v1 | D59: =VLOOKUP(A59, borana_schemas!A:D, 4, FALSE) -> https://borana.pamdas.org/api/v1.0/activity/events/schema/eventtype/hwc_livestock_verification | E59: =VLOOKUP(A59, mugie_schemas!A:D, 4, FALSE) -> #N/A | F59: all_posts_rep | H59: 68 | I59: 37 | J59: HWC Livestock Predation Verification | K59: HWC | L59: 97172f47-979e-40ff-ad0a-8e4103b3ea7c | N59: hwc_livestock_verification | O59: =HYPERLINK("#'hwc_livestock_verification'!A1","Open") -> Open
A60: hwc_mitigation_response | B60: EventType Test Data | C60: v1 | D60: =VLOOKUP(A60, borana_schemas!A:D, 4, FALSE) -> https://borana.pamdas.org/api/v1.0/activity/events/schema/eventtype/hwc_mitigation_response | E60: =VLOOKUP(A60, mugie_schemas!A:D, 4, FALSE) -> https://mugie.pamdas.org/api/v1.0/activity/events/schema/eventtype/hwc_mitigation_response | F60: hwc_rep | H60: 15 | I60: 3 | J60: HWC Mitigation Response | K60: HWC | L60: 97172f47-979e-40ff-ad0a-8e4103b3ea7c | N60: hwc_mitigation_response | O60: =HYPERLINK("#'hwc_mitigation_response'!A1","Open") -> Open
A61: hwc_peoperty_dam_verification | B61: EventType Test Data | C61: v1 | D61: =VLOOKUP(A61, borana_schemas!A:D, 4, FALSE) -> https://borana.pamdas.org/api/v1.0/activity/events/schema/eventtype/hwc_peoperty_dam_verification | E61: =VLOOKUP(A61, mugie_schemas!A:D, 4, FALSE) -> #N/A | F61: all_posts_rep | H61: 53 | I61: 19 | J61: HWC Property Damage Verification | K61: HWC | L61: 97172f47-979e-40ff-ad0a-8e4103b3ea7c | N61: hwc_peoperty_dam_verification | O61: =HYPERLINK("#'hwc_peoperty_dam_verification'!A1","Open") -> Open
A62: hwc_property | B62: EventType Test Data | C62: v1 | D62: =VLOOKUP(A62, borana_schemas!A:D, 4, FALSE) -> https://borana.pamdas.org/api/v1.0/activity/events/schema/eventtype/hwc_property | E62: =VLOOKUP(A62, mugie_schemas!A:D, 4, FALSE) -> https://mugie.pamdas.org/api/v1.0/activity/events/schema/eventtype/hwc_property | F62: hwc_alert_rep | H62: 21 | I62: 6 | J62: HWC Property Damage | K62: HWC | L62: 97172f47-979e-40ff-ad0a-8e4103b3ea7c | N62: hwc_property | O62: =HYPERLINK("#'hwc_property'!A1","Open") -> Open
A63: hwc_retaliation | B63: EventType Test Data | C63: v1 | D63: =VLOOKUP(A63, borana_schemas!A:D, 4, FALSE) -> https://borana.pamdas.org/api/v1.0/activity/events/schema/eventtype/hwc_retaliation | E63: =VLOOKUP(A63, mugie_schemas!A:D, 4, FALSE) -> https://mugie.pamdas.org/api/v1.0/activity/events/schema/eventtype/hwc_retaliation | F63: human_wildlife_conflict_rep | H63: 18 | I63: 3 | J63: HWC Retaliation | K63: HWC | L63: 97172f47-979e-40ff-ad0a-8e4103b3ea7c | N63: hwc_retaliation | O63: =HYPERLINK("#'hwc_retaliation'!A1","Open") -> Open
A64: hwc_threat | B64: HWC - Threat Report | C64: v1 | D64: =VLOOKUP(A64, borana_schemas!A:D, 4, FALSE) -> https://borana.pamdas.org/api/v1.0/activity/events/schema/eventtype/hwc_threat | E64: =VLOOKUP(A64, mugie_schemas!A:D, 4, FALSE) -> https://mugie.pamdas.org/api/v1.0/activity/events/schema/eventtype/hwc_threat | F64: hwc_alert_rep | H64: 16 | I64: 6 | J64: HWC Threat | K64: HWC | N64: hwc_threat | O64: =HYPERLINK("#'hwc_threat'!A1","Open") -> Open
A65: arrest_report | B65: Arrest Report | C65: v1 | D65: =VLOOKUP(A65, borana_schemas!A:D, 4, FALSE) -> https://borana.pamdas.org/api/v1.0/activity/events/schema/eventtype/arrest_report | E65: =VLOOKUP(A65, mugie_schemas!A:D, 4, FALSE) -> #N/A | F65: arrest_rep | H65: 25 | I65: 4 | J65: Arrest | K65: Law Enforcement | L65: 5ae25fb3-33b0-4dca-a3f7-47d42e4f876b | N65: arrest_report | O65: =HYPERLINK("#'arrest_report'!A1","Open") -> Open
A66: cameratrap_rep | B66: Auto-generated schema, from incoming data. | C66: v1 | D66: =VLOOKUP(A66, borana_schemas!A:D, 4, FALSE) -> https://borana.pamdas.org/api/v1.0/activity/events/schema/eventtype/cameratrap_rep | E66: =VLOOKUP(A66, mugie_schemas!A:D, 4, FALSE) -> #N/A | F66: cameratrap_rep | H66: 13 | I66: 2 | J66: Camera Trap | K66: Law Enforcement | N66: cameratrap_rep | O66: =HYPERLINK("#'cameratrap_rep'!A1","Open") -> Open
A67: contact_report | B67: Contact Report | C67: v1 | D67: =VLOOKUP(A67, borana_schemas!A:D, 4, FALSE) -> https://borana.pamdas.org/api/v1.0/activity/events/schema/eventtype/contact_report | E67: =VLOOKUP(A67, mugie_schemas!A:D, 4, FALSE) -> #N/A | F67: contact_rep | H67: 29 | I67: 2 | J67: Contact | K67: Law Enforcement | L67: 5ae25fb3-33b0-4dca-a3f7-47d42e4f876b | N67: contact_report | O67: =HYPERLINK("#'contact_report'!A1","Open") -> Open
A68: illegal_activity_rep | B68: EventType Test Data | C68: v1 | D68: =VLOOKUP(A68, borana_schemas!A:D, 4, FALSE) -> https://borana.pamdas.org/api/v1.0/activity/events/schema/eventtype/illegal_activity_rep | E68: https://mugie.pamdas.org/api/v1.0/activity/events/schema/eventtype/illegal_activity | F68: activity_rep | H68: 13 | I68: 2 | J68: Illegal Activity | K68: Law Enforcement | L68: 5ae25fb3-33b0-4dca-a3f7-47d42e4f876b | N68: illegal_activity_rep | O68: =HYPERLINK("#'illegal_activity_rep'!A1","Open") -> Open
A69: incident_collection | B69: Incident Collection | C69: v1 | D69: =VLOOKUP(A69, borana_schemas!A:D, 4, FALSE) -> https://borana.pamdas.org/api/v1.0/activity/events/schema/eventtype/incident_collection | E69: =VLOOKUP(A69, mugie_schemas!A:D, 4, FALSE) -> https://mugie.pamdas.org/api/v1.0/activity/events/schema/eventtype/incident_collection | F69: incident_collection_rep | H69: 3 | I69: 2 | J69: Incident Collection | K69: Law Enforcement | N69: incident_collection | O69: =HYPERLINK("#'incident_collection'!A1","Open") -> Open
A70: known_suspects | B70: EventType Test Data | C70: v1 | D70: =VLOOKUP(A70, borana_schemas!A:D, 4, FALSE) -> https://borana.pamdas.org/api/v1.0/activity/events/schema/eventtype/known_suspects | E70: =VLOOKUP(A70, mugie_schemas!A:D, 4, FALSE) -> #N/A | F70: human_activities_observation_rep | H70: 23 | I70: 7 | J70: Known Suspect(s) | K70: Law Enforcement | L70: 5ae25fb3-33b0-4dca-a3f7-47d42e4f876b | N70: known_suspects | O70: =HYPERLINK("#'known_suspects'!A1","Open") -> Open
A71: livestock_theft | B71: EventType Test Data | C71: v1 | D71: =VLOOKUP(A71, borana_schemas!A:D, 4, FALSE) -> https://borana.pamdas.org/api/v1.0/activity/events/schema/eventtype/livestock_theft | E71: =VLOOKUP(A71, mugie_schemas!A:D, 4, FALSE) -> #N/A | F71: stock_theft_rep | H71: 17 | I71: 3 | J71: Livestock Theft | K71: Law Enforcement | L71: 5ae25fb3-33b0-4dca-a3f7-47d42e4f876b | N71: livestock_theft | O71: =HYPERLINK("#'livestock_theft'!A1","Open") -> Open
A72: poacher_camp | B72: EventType Test Data | C72: v1 | D72: =VLOOKUP(A72, borana_schemas!A:D, 4, FALSE) -> https://borana.pamdas.org/api/v1.0/activity/events/schema/eventtype/poacher_camp | E72: =VLOOKUP(A72, mugie_schemas!A:D, 4, FALSE) -> #N/A | F72: poacher_camp_rep | H72: 18 | I72: 5 | J72: Poacher's Camp | K72: Law Enforcement | L72: 5ae25fb3-33b0-4dca-a3f7-47d42e4f876b | N72: poacher_camp | O72: =HYPERLINK("#'poacher_camp'!A1","Open") -> Open
A73: shot_report | B73: EventType Test Data | C73: v1 | D73: =VLOOKUP(A73, borana_schemas!A:D, 4, FALSE) -> https://borana.pamdas.org/api/v1.0/activity/events/schema/eventtype/shot_report | E73: https://mugie.pamdas.org/api/v1.0/activity/events/schema/eventtype/gunshot | F73: shot_rep | H73: 17 | I73: 5 | J73: Shot | K73: Law Enforcement | L73: 5ae25fb3-33b0-4dca-a3f7-47d42e4f876b | N73: shot_report | O73: =HYPERLINK("#'shot_report'!A1","Open") -> Open
A74: sighting_rep | B74: EventType Test Data | C74: v1 | D74: =VLOOKUP(A74, borana_schemas!A:D, 4, FALSE) -> https://borana.pamdas.org/api/v1.0/activity/events/schema/eventtype/sighting_rep | E74: =VLOOKUP(A74, mugie_schemas!A:D, 4, FALSE) -> #N/A | F74: sighting_rep | H74: 44 | I74: 20 | J74: Sighting | K74: Law Enforcement | L74: 5ae25fb3-33b0-4dca-a3f7-47d42e4f876b | N74: sighting_rep | O74: =HYPERLINK("#'sighting_rep'!A1","Open") -> Open
A75: snares_traps | B75: EventType Test Data | C75: v1 | D75: =VLOOKUP(A75, borana_schemas!A:D, 4, FALSE) -> https://borana.pamdas.org/api/v1.0/activity/events/schema/eventtype/snares_traps | E75: =VLOOKUP(A75, mugie_schemas!A:D, 4, FALSE) -> #N/A | F75: snare_rep | H75: 17 | I75: 3 | J75: Snares & Traps | K75: Law Enforcement | L75: 5ae25fb3-33b0-4dca-a3f7-47d42e4f876b | N75: snares_traps | O75: =HYPERLINK("#'snares_traps'!A1","Open") -> Open
A76: spoor_rep | B76: EventType Test Data | C76: v1 | D76: =VLOOKUP(A76, borana_schemas!A:D, 4, FALSE) -> https://borana.pamdas.org/api/v1.0/activity/events/schema/eventtype/spoor_rep | E76: =VLOOKUP(A76, mugie_schemas!A:D, 4, FALSE) -> #N/A | F76: spoor_rep | H76: 29 | I76: 14 | J76: Spoor | K76: Law Enforcement | L76: 5ae25fb3-33b0-4dca-a3f7-47d42e4f876b | N76: spoor_rep | O76: =HYPERLINK("#'spoor_rep'!A1","Open") -> Open
A77: theft_robbery | B77: EventType Test Data | C77: v1 | D77: =VLOOKUP(A77, borana_schemas!A:D, 4, FALSE) -> https://borana.pamdas.org/api/v1.0/activity/events/schema/eventtype/theft_robbery | E77: =VLOOKUP(A77, mugie_schemas!A:D, 4, FALSE) -> #N/A | F77: robbery_theft_rep | H77: 59 | I77: 24 | J77: Theft | K77: Law Enforcement | L77: 5ae25fb3-33b0-4dca-a3f7-47d42e4f876b | N77: theft_robbery | O77: =HYPERLINK("#'theft_robbery'!A1","Open") -> Open
A78: authority_to_deploy | B78: Authority to Deploy | C78: v1 | D78: =VLOOKUP(A78, borana_schemas!A:D, 4, FALSE) -> https://borana.pamdas.org/api/v1.0/activity/events/schema/eventtype/authority_to_deploy | E78: =VLOOKUP(A78, mugie_schemas!A:D, 4, FALSE) -> #N/A | F78: sit_rep | H78: 6 | I78: 3 | J78: Authority to Deploy | K78: Legal | L78: 36879dad-1388-4627-8a00-b6765fafa413 | N78: authority_to_deploy | O78: =HYPERLINK("#'authority_to_deploy'!A1","Open") -> Open
A79: caution_report | B79: Caution Report | C79: v1 | D79: =VLOOKUP(A79, borana_schemas!A:D, 4, FALSE) -> https://borana.pamdas.org/api/v1.0/activity/events/schema/eventtype/caution_report | E79: =VLOOKUP(A79, mugie_schemas!A:D, 4, FALSE) -> #N/A | F79: all_posts_rep | H79: 8 | I79: 3 | J79: Caution Report | K79: Legal | L79: 36879dad-1388-4627-8a00-b6765fafa413 | N79: caution_report | O79: =HYPERLINK("#'caution_report'!A1","Open") -> Open
A80: court_case_report | B80: Court Case Report | C80: v1 | D80: =VLOOKUP(A80, borana_schemas!A:D, 4, FALSE) -> https://borana.pamdas.org/api/v1.0/activity/events/schema/eventtype/court_case_report | E80: =VLOOKUP(A80, mugie_schemas!A:D, 4, FALSE) -> #N/A | F80: all_posts_rep | H80: 15 | I80: 5 | J80: Court Case Report | K80: Legal | L80: 36879dad-1388-4627-8a00-b6765fafa413 | N80: court_case_report | O80: =HYPERLINK("#'court_case_report'!A1","Open") -> Open
A81: evidence_crime_scene | B81: EventType Test Data | C81: v1 | D81: =VLOOKUP(A81, borana_schemas!A:D, 4, FALSE) -> https://borana.pamdas.org/api/v1.0/activity/events/schema/eventtype/evidence_crime_scene | E81: =VLOOKUP(A81, mugie_schemas!A:D, 4, FALSE) -> #N/A | F81: all_posts_rep | H81: 45 | I81: 17 | J81: Evidence - Crime Scene | K81: Legal | L81: 36879dad-1388-4627-8a00-b6765fafa413 | N81: evidence_crime_scene | O81: =HYPERLINK("#'evidence_crime_scene'!A1","Open") -> Open
A82: evidence_suspect_property | B82: EventType Test Data | C82: v1 | D82: =VLOOKUP(A82, borana_schemas!A:D, 4, FALSE) -> https://borana.pamdas.org/api/v1.0/activity/events/schema/eventtype/evidence_suspect_property | E82: =VLOOKUP(A82, mugie_schemas!A:D, 4, FALSE) -> #N/A | F82: all_posts_rep | H82: 27 | I82: 9 | J82: Evidence - Suspect's Property | K82: Legal | L82: 36879dad-1388-4627-8a00-b6765fafa413 | N82: evidence_suspect_property | O82: =HYPERLINK("#'evidence_suspect_property'!A1","Open") -> Open
A83: evidence_weapons_ammo | B83: EventType Test Data | C83: v1 | D83: =VLOOKUP(A83, borana_schemas!A:D, 4, FALSE) -> https://borana.pamdas.org/api/v1.0/activity/events/schema/eventtype/evidence_weapons_ammo | E83: =VLOOKUP(A83, mugie_schemas!A:D, 4, FALSE) -> #N/A | F83: all_posts_rep | H83: 24 | I83: 8 | J83: Evidence - Suspect's Weapons & Ammo | K83: Legal | L83: 36879dad-1388-4627-8a00-b6765fafa413 | N83: evidence_weapons_ammo | O83: =HYPERLINK("#'evidence_weapons_ammo'!A1","Open") -> Open
A84: use_of_force_justification | B84: EventType Test Data | C84: v1 | D84: =VLOOKUP(A84, borana_schemas!A:D, 4, FALSE) -> https://borana.pamdas.org/api/v1.0/activity/events/schema/eventtype/use_of_force_justification | E84: =VLOOKUP(A84, mugie_schemas!A:D, 4, FALSE) -> #N/A | F84: sit_rep | H84: 14 | I84: 5 | J84: Use of Force | K84: Legal | L84: 36879dad-1388-4627-8a00-b6765fafa413 | N84: use_of_force_justification | O84: =HYPERLINK("#'use_of_force_justification'!A1","Open") -> Open
A85: grazing_location | B85: Rainfall Report Report | C85: v1 | D85: =VLOOKUP(A85, borana_schemas!A:D, 4, FALSE) -> https://borana.pamdas.org/api/v1.0/activity/events/schema/eventtype/grazing_location | E85: =VLOOKUP(A85, mugie_schemas!A:D, 4, FALSE) -> #N/A | F85: bull_rep | H85: 1 | I85: 0 | J85: Grazing location | K85: Livestock Report | N85: grazing_location | O85: =HYPERLINK("#'grazing_location'!A1","Open") -> Open
A86: fence_002 | B86: EventType Test Data | C86: v1 | D86: =VLOOKUP(A86, borana_schemas!A:D, 4, FALSE) -> https://borana.pamdas.org/api/v1.0/activity/events/schema/eventtype/fence_002 | E86: https://mugie.pamdas.org/api/v1.0/activity/events/schema/eventtype/fence_rp | F86: fence_rep | H86: 19 | I86: 9 | J86: Fence | K86: Logistics | L86: 0ed2d7f3-4448-4dbb-ac8b-10e7bce53dd4 | N86: fence_002 | O86: =HYPERLINK("#'fence_002'!A1","Open") -> Open
A87: gate_entry_test | B87: Gate Activity Test - NG | C87: v1 | D87: =VLOOKUP(A87, borana_schemas!A:D, 4, FALSE) -> https://borana.pamdas.org/api/v1.0/activity/events/schema/eventtype/gate_entry_test | E87: =VLOOKUP(A87, mugie_schemas!A:D, 4, FALSE) -> #N/A | F87: wayfinding_rep | H87: 13 | I87: 4 | J87: Gate Activity | K87: Logistics | N87: gate_entry_test | O87: =HYPERLINK("#'gate_entry_test'!A1","Open") -> Open
A88: grazing_rep | B88: Rotational Grazing Report Report | C88: v1 | D88: =VLOOKUP(A88, borana_schemas!A:D, 4, FALSE) -> https://borana.pamdas.org/api/v1.0/activity/events/schema/eventtype/grazing_rep | E88: =VLOOKUP(A88, mugie_schemas!A:D, 4, FALSE) -> #N/A | F88: livestock_movement_rep | H88: 10 | I88: 5 | J88: Rotational Grazing | K88: Logistics | N88: grazing_rep | O88: =HYPERLINK("#'grazing_rep'!A1","Open") -> Open
A89: lwc_erosion_rep | B89: Erosion Report Report | C89: v1 | D89: =VLOOKUP(A89, borana_schemas!A:D, 4, FALSE) -> https://borana.pamdas.org/api/v1.0/activity/events/schema/eventtype/lwc_erosion_rep | E89: =VLOOKUP(A89, mugie_schemas!A:D, 4, FALSE) -> #N/A | F89: lwc_erosion_rep | H89: 10 | I89: 4 | J89: Erosion Report | K89: Logistics | N89: lwc_erosion_rep | O89: =HYPERLINK("#'lwc_erosion_rep'!A1","Open") -> Open
A90: lwc_road_maintenance_rep | B90: Road Maintenance Report | C90: v1 | D90: =VLOOKUP(A90, borana_schemas!A:D, 4, FALSE) -> https://borana.pamdas.org/api/v1.0/activity/events/schema/eventtype/lwc_road_maintenance_rep | E90: =VLOOKUP(A90, mugie_schemas!A:D, 4, FALSE) -> #N/A | F90: lwc_road_maintenance_rep | H90: 7 | I90: 5 | J90: Road Maintenance | K90: Logistics | N90: lwc_road_maintenance_rep | O90: =HYPERLINK("#'lwc_road_maintenance_rep'!A1","Open") -> Open
A91: post_rep | B91: EventType Test Data | C91: v1 | D91: =VLOOKUP(A91, borana_schemas!A:D, 4, FALSE) -> https://borana.pamdas.org/api/v1.0/activity/events/schema/eventtype/post_rep | E91: =VLOOKUP(A91, mugie_schemas!A:D, 4, FALSE) -> #N/A | F91: all_posts_rep | H91: 16 | I91: 6 | J91: Post Report | K91: Logistics | L91: 0ed2d7f3-4448-4dbb-ac8b-10e7bce53dd4 | N91: post_rep | O91: =HYPERLINK("#'post_rep'!A1","Open") -> Open
A92: shift_change_rep | B92: End of Shift Report | C92: v1 | D92: =VLOOKUP(A92, borana_schemas!A:D, 4, FALSE) -> https://borana.pamdas.org/api/v1.0/activity/events/schema/eventtype/shift_change_rep | E92: =VLOOKUP(A92, mugie_schemas!A:D, 4, FALSE) -> #N/A | F92: radio_rep | H92: 11 | I92: 8 | J92: Ops Room End Of Shift | K92: Logistics | N92: shift_change_rep | O92: =HYPERLINK("#'shift_change_rep'!A1","Open") -> Open
A93: black_rhino_fight_request_2025 | B93: Black Rhino Fight | C93: v1 | D93: =VLOOKUP(A93, borana_schemas!A:D, 4, FALSE) -> https://borana.pamdas.org/api/v1.0/activity/events/schema/eventtype/black_rhino_fight_request_2025 | E93: =VLOOKUP(A93, mugie_schemas!A:D, 4, FALSE) -> #N/A | F93: rhino_fighting_rep | H93: 9 | I93: 4 | J93: Black Rhino Fight Summary | K93: Rhino Management | L93: 874e243d-16d8-4ac9-89b3-24aaa163eb1f | N93: black_rhino_fight_request_2025 | O93: =HYPERLINK("#'black_rhino_fight_request_2025'!A1","Open") -> Open
A94: black_rhino_home_range | B94: Black Rhino HomeRange | C94: v1 | D94: =VLOOKUP(A94, borana_schemas!A:D, 4, FALSE) -> https://borana.pamdas.org/api/v1.0/activity/events/schema/eventtype/black_rhino_home_range | E94: =VLOOKUP(A94, mugie_schemas!A:D, 4, FALSE) -> #N/A | F94: geofence_break_rep | H94: 16 | I94: 9 | J94: Black Rhino Home Range | K94: Rhino Management | L94: 874e243d-16d8-4ac9-89b3-24aaa163eb1f | N94: black_rhino_home_range | O94: =HYPERLINK("#'black_rhino_home_range'!A1","Open") -> Open
A95: black_rhino_mating_2025 | B95: Black Rhino Mating | C95: v1 | D95: =VLOOKUP(A95, borana_schemas!A:D, 4, FALSE) -> https://borana.pamdas.org/api/v1.0/activity/events/schema/eventtype/black_rhino_mating_2025 | E95: =VLOOKUP(A95, mugie_schemas!A:D, 4, FALSE) -> #N/A | F95: rhino_mounting_rep | H95: 8 | I95: 3 | J95: Black Rhino Mating | K95: Rhino Management | N95: black_rhino_mating_2025 | O95: =HYPERLINK("#'black_rhino_mating_2025'!A1","Open") -> Open
A96: black_rhino_sighting_rv002 | B96: Black Rhino Sighting | C96: v1 | D96: =VLOOKUP(A96, borana_schemas!A:D, 4, FALSE) -> https://borana.pamdas.org/api/v1.0/activity/events/schema/eventtype/black_rhino_sighting_rv002 | E96: =VLOOKUP(A96, mugie_schemas!A:D, 4, FALSE) -> #N/A | F96: rhino_sighting_rep | H96: 29 | I96: 20 | J96: Black Rhino Sighting | K96: Rhino Management | L96: 874e243d-16d8-4ac9-89b3-24aaa163eb1f | N96: black_rhino_sighting_rv002 | O96: =HYPERLINK("#'black_rhino_sighting_rv002'!A1","Open") -> Open
A97: br_birth | B97: Black Rhino Birth | C97: v1 | D97: =VLOOKUP(A97, borana_schemas!A:D, 4, FALSE) -> https://borana.pamdas.org/api/v1.0/activity/events/schema/eventtype/br_birth | E97: =VLOOKUP(A97, mugie_schemas!A:D, 4, FALSE) -> #N/A | F97: rhino_birth_rep | H97: 15 | I97: 6 | J97: Black Rhino Birth | K97: Rhino Management | L97: 874e243d-16d8-4ac9-89b3-24aaa163eb1f | N97: br_birth | O97: =HYPERLINK("#'br_birth'!A1","Open") -> Open
A98: br_capture_record | B98: Black Rhino Capture Record | C98: v1 | D98: =VLOOKUP(A98, borana_schemas!A:D, 4, FALSE) -> https://borana.pamdas.org/api/v1.0/activity/events/schema/eventtype/br_capture_record | E98: =VLOOKUP(A98, mugie_schemas!A:D, 4, FALSE) -> #N/A | F98: all_posts_rep | H98: 37 | I98: 5 | J98: Black Rhino Capture Record | K98: Rhino Management | L98: 874e243d-16d8-4ac9-89b3-24aaa163eb1f | N98: br_capture_record | O98: =HYPERLINK("#'br_capture_record'!A1","Open") -> Open
A99: br_introduction | B99: Black Rhino Introduction | C99: v1 | D99: =VLOOKUP(A99, borana_schemas!A:D, 4, FALSE) -> https://borana.pamdas.org/api/v1.0/activity/events/schema/eventtype/br_introduction | E99: =VLOOKUP(A99, mugie_schemas!A:D, 4, FALSE) -> #N/A | F99: rhino_territorial_movement_rep | H99: 11 | I99: 4 | J99: Black Rhino Introduction | K99: Rhino Management | L99: 874e243d-16d8-4ac9-89b3-24aaa163eb1f | N99: br_introduction | O99: =HYPERLINK("#'br_introduction'!A1","Open") -> Open
A100: br_mortality | B100: Black Rhino Mortality | C100: v1 | D100: =VLOOKUP(A100, borana_schemas!A:D, 4, FALSE) -> https://borana.pamdas.org/api/v1.0/activity/events/schema/eventtype/br_mortality | E100: =VLOOKUP(A100, mugie_schemas!A:D, 4, FALSE) -> #N/A | F100: rhinonatural_rep | H100: 33 | I100: 16 | J100: Black Rhino Mortality | K100: Rhino Management | N100: br_mortality | O100: =HYPERLINK("#'br_mortality'!A1","Open") -> Open
...

Sheet borana_schemas
A1: event_value | B1: schema_title | C1: api_version | D1: schema_id | E1: icon_id | F1: image_url
A2: aip_polygon | B2: Invasive Alien Plants Report | C2: v1 | D2: https://borana.pamdas.org/api/v1.0/activity/events/schema/eventtype/aip_polygon | E2: invasive_species_rep | F2: https://borana.pamdas.org/static/invasive_species-black.svg
A3: aip_tourism | B3: Invasive Alien Plants Report | C3: v1 | D3: https://borana.pamdas.org/api/v1.0/activity/events/schema/eventtype/aip_tourism | E3: invasive_species_rep | F3: https://borana.pamdas.org/static/invasive_species-black.svg
A4: air_ops_boma_sighting | B4: Boma Sighting | C4: v1 | D4: https://borana.pamdas.org/api/v1.0/activity/events/schema/eventtype/air_ops_boma_sighting | E4: boma_rep | F4: https://borana.pamdas.org/static/sprite-src/boma_rep.svg
A5: air_ops_camel_sighting | B5: Camel Sighting | C5: v1 | D5: https://borana.pamdas.org/api/v1.0/activity/events/schema/eventtype/air_ops_camel_sighting | E5: air_ops_camel_sighting | F5: https://borana.pamdas.org/static/generic-black.svg
A6: air_ops_cattle_sighting | B6: Cattle Sighting | C6: v1 | D6: https://borana.pamdas.org/api/v1.0/activity/events/schema/eventtype/air_ops_cattle_sighting | E6: bull_rep | F6: https://borana.pamdas.org/static/sprite-src/bull_rep.svg
A7: air_ops_elephant_carcass | B7: Elephant Carcass | C7: v1 | D7: https://borana.pamdas.org/api/v1.0/activity/events/schema/eventtype/air_ops_elephant_carcass | E7: elephant_mortality_rep | F7: https://borana.pamdas.org/static/elephant_mortality-black.svg
A8: air_ops_logging | B8: Logging | C8: v1 | D8: https://borana.pamdas.org/api/v1.0/activity/events/schema/eventtype/air_ops_logging | E8: deforestation_rep | F8: https://borana.pamdas.org/static/sprite-src/deforestation_rep.svg
A9: air_ops_people_sighting | B9: People Sighting | C9: v1 | D9: https://borana.pamdas.org/api/v1.0/activity/events/schema/eventtype/air_ops_people_sighting | E9: suspicious_person_rep | F9: https://borana.pamdas.org/static/suspicious_person_rep-black.svg
A10: air_ops_shoat_sighting | B10: Shoats Sighting | C10: v1 | D10: https://borana.pamdas.org/api/v1.0/activity/events/schema/eventtype/air_ops_shoat_sighting | E10: goat_rep | F10: https://borana.pamdas.org/static/sprite-src/goat_rep.svg
A11: air_ops_wildlife_carcass | B11: Wildlife Carcass | C11: v1 | D11: https://borana.pamdas.org/api/v1.0/activity/events/schema/eventtype/air_ops_wildlife_carcass | E11: carcass_rep | F11: https://borana.pamdas.org/static/carcass-black.svg
A12: air_ops_wildlife_sighting | B12: Other Wildlife Sighting | C12: v1 | D12: https://borana.pamdas.org/api/v1.0/activity/events/schema/eventtype/air_ops_wildlife_sighting | E12: other_wildlife_sightings_rep | F12: https://borana.pamdas.org/static/other_wildlife_sightings-black.svg
... A132: wr_removal | B132: EventType Test Data | C132: v1 | D132: https://borana.pamdas.org/api/v1.0/activity/events/schema/eventtype/wr_removal | E132: rhino_territorial_movement_rep | F132: https://borana.pamdas.org/static/rhino_territorial_movement-black.svg

Sheet mugie_schemas
A1: event_value | B1: schema_title | C1: api_version | D1: schema_id | E1: icon_id | F1: image_url | G1: n_fields | H1: n_enums | I1: event_name | J1: event_category_display | K1: event_category_id | L1: event_is_active | M1: event_updated_at | N1: sheet_name | O1: Open
A2: acoustic_detection | B2: Acoustic Detection (acoustic_detection) | C2: v1 | D2: https://mugie.pamdas.org/api/v1.0/activity/events/schema/eventtype/acoustic_detection | E2: radar_rep | F2: https://mugie.pamdas.org/static/sprite-src/radar_rep.svg | G2: 3 | H2: 0 | I2: Acoustic Detection | J2: Analyzer Event | K2: ef230385-5afc-40d1-ad07-c811f6da2b3c | L2: TRUE | N2: acoustic_detection | O2: =HYPERLINK("#'acoustic_detection'!A1","Open") -> Open
A3: firms_rep | B3: FIRMS Fire Report Schema | C3: v1 | D3: https://mugie.pamdas.org/api/v1.0/activity/events/schema/eventtype/firms_rep | E3: firms_rep | F3: https://mugie.pamdas.org/static/firms_rep-black.svg | G3: 6 | H3: 0 | I3: FIRMS Report | J3: Analyzer Event | K3: ef230385-5afc-40d1-ad07-c811f6da2b3c | L3: TRUE | N3: firms_rep | O3: =HYPERLINK("#'firms_rep'!A1","Open") -> Open
A4: gfw_activefire_alert | B4: Event Type Global Forest Watch Active Fire Alert | C4: v1 | D4: https://mugie.pamdas.org/api/v1.0/activity/events/schema/eventtype/gfw_activefire_alert | E4: fire_rep | F4: https://mugie.pamdas.org/static/fire-black.svg | G4: 9 | H4: 0 | I4: Active Fire Alert (GFW) | J4: Analyzer Event | K4: ef230385-5afc-40d1-ad07-c811f6da2b3c | L4: TRUE | N4: gfw_activefire_alert | O4: =HYPERLINK("#'gfw_activefire_alert'!A1","Open") -> Open
A5: gfw_glad_alert | B5: Event Type Global Forest Watch Tree Loss Alert | C5: v1 | D5: https://mugie.pamdas.org/api/v1.0/activity/events/schema/eventtype/gfw_glad_alert | E5: deforestation_rep | F5: https://mugie.pamdas.org/static/sprite-src/deforestation_rep.svg | G5: 4 | H5: 0 | I5: GLAD Tree-Loss Alert (GFW) | J5: Analyzer Event | K5: ef230385-5afc-40d1-ad07-c811f6da2b3c | L5: TRUE | N5: gfw_glad_alert | O5: =HYPERLINK("#'gfw_glad_alert'!A1","Open") -> Open
A6: immobility | B6: EventType Immobility | C6: v1 | D6: https://mugie.pamdas.org/api/v1.0/activity/events/schema/eventtype/immobility | E6: immobility | F6: https://mugie.pamdas.org/static/immobility-black.svg | G6: 7 | H6: 0 | I6: Immobility | J6: Analyzer Event | K6: ef230385-5afc-40d1-ad07-c811f6da2b3c | L6: TRUE | N6: immobility | O6: =HYPERLINK("#'immobility'!A1","Open") -> Open
A7: immobility_all_clear | B7: EventType Immobility | C7: v1 | D7: https://mugie.pamdas.org/api/v1.0/activity/events/schema/eventtype/immobility_all_clear | E7: immobility_all_clear | F7: https://mugie.pamdas.org/static/immobility_all_clear-black.svg | G7: 7 | H7: 0 | I7: Immobility All Clear | J7: Analyzer Event | K7: ef230385-5afc-40d1-ad07-c811f6da2b3c | L7: TRUE | N7: immobility_all_clear | O7: =HYPERLINK("#'immobility_all_clear'!A1","Open") -> Open
A8: low_speed_percentile | B8: EventType Low Speed Percentile | C8: v1 | D8: https://mugie.pamdas.org/api/v1.0/activity/events/schema/eventtype/low_speed_percentile | E8: low_speed_percentile | F8: https://mugie.pamdas.org/static/low_speed_percentile-black.svg | G8: 6 | H8: 0 | I8: Low Speed (Percentile) | J8: Analyzer Event | K8: ef230385-5afc-40d1-ad07-c811f6da2b3c | L8: TRUE | N8: low_speed_percentile | O8: =HYPERLINK("#'low_speed_percentile'!A1","Open") -> Open
A9: low_speed_wilcoxon | B9: EventType Low Speed Wilcox | C9: v1 | D9: https://mugie.pamdas.org/api/v1.0/activity/events/schema/eventtype/low_speed_wilcoxon | E9: low_speed_wilcoxon | F9: https://mugie.pamdas.org/static/low_speed_wilcoxon-black.svg | G9: 4 | H9: 0 | I9: Low Speed (Wilcoxon) | J9: Analyzer Event | K9: ef230385-5afc-40d1-ad07-c811f6da2b3c | L9: TRUE | N9: low_speed_wilcoxon | O9: =HYPERLINK("#'low_speed_wilcoxon'!A1","Open") -> Open
A10: low_speed_wilcoxon_all_clear | B10: EventType Low Speed Wilcox All Clear | C10: v1 | D10: https://mugie.pamdas.org/api/v1.0/activity/events/schema/eventtype/low_speed_wilcoxon_all_clear | E10: low_speed_wilcoxon_all_clear | F10: https://mugie.pamdas.org/static/generic-black.svg | G10: 5 | H10: 0 | I10: Low Speed (Wilcoxon) All Clear | J10: Analyzer Event | K10: ef230385-5afc-40d1-ad07-c811f6da2b3c | L10: TRUE | N10: low_speed_wilcoxon_all_clear | O10: =HYPERLINK("#'low_speed_wilcoxon_all_clear'!A1","Open") -> Open
A11: proximity | B11: EventType Proximity | C11: v1 | D11: https://mugie.pamdas.org/api/v1.0/activity/events/schema/eventtype/proximity | E11: proximity | F11: https://mugie.pamdas.org/static/sprite-src/proximity.svg | G11: 7 | H11: 0 | I11: Proximity | J11: Analyzer Event | K11: ef230385-5afc-40d1-ad07-c811f6da2b3c | L11: TRUE | N11: proximity | O11: =HYPERLINK("#'proximity'!A1","Open") -> Open
A12: silence_source_provider_rep | B12: Entry Alert | C12: v1 | D12: https://mugie.pamdas.org/api/v1.0/activity/events/schema/eventtype/silence_source_provider_rep | E12: silence_source_provider_rep | F12: https://mugie.pamdas.org/static/sprite-src/silence_source_provider_rep.svg | G12: 3 | H12: 0 | I12: Silent Source Provider | J12: Analyzer Event | K12: ef230385-5afc-40d1-ad07-c811f6da2b3c | L12: TRUE | N12: silence_source_provider_rep | O12: =HYPERLINK("#'silence_source_provider_rep'!A1","Open") -> Open
A13: silence_source_rep | B13: Entry Alert | C13: v1 | D13: https://mugie.pamdas.org/api/v1.0/activity/events/schema/eventtype/silence_source_rep | E13: silence_source_rep | F13: https://mugie.pamdas.org/static/sprite-src/silence_source_rep.svg | G13: 7 | H13: 0 | I13: Silent Source | J13: Analyzer Event | K13: ef230385-5afc-40d1-ad07-c811f6da2b3c | L13: TRUE | N13: silence_source_rep | O13: =HYPERLINK("#'silence_source_rep'!A1","Open") -> Open
A14: subject_proximity | B14: Subject Proximity Schema | C14: v1 | D14: https://mugie.pamdas.org/api/v1.0/activity/events/schema/eventtype/subject_proximity | E14: subject_proximity | F14: https://mugie.pamdas.org/static/sprite-src/subject_proximity.svg | G14: 10 | H14: 0 | I14: Subject Proximity | J14: Analyzer Event | K14: ef230385-5afc-40d1-ad07-c811f6da2b3c | L14: TRUE | N14: subject_proximity | O14: =HYPERLINK("#'subject_proximity'!A1","Open") -> Open
A15: nesting_site | B15: EventType Test Data | C15: v1 | D15: https://mugie.pamdas.org/api/v1.0/activity/events/schema/eventtype/nesting_site | E15: nest_rep | F15: https://mugie.pamdas.org/static/sprite-src/nest_rep.svg | G15: 5 | H15: 1 | I15: Nesting Site | J15: Avian Events | K15: 87b9675f-312c-4985-a5bf-38ff4423146e | L15: TRUE | N15: nesting_site | O15: =HYPERLINK("#'nesting_site'!A1","Open") -> Open
A16: raptor_sighting | B16: EventType Test Data | C16: v1 | D16: https://mugie.pamdas.org/api/v1.0/activity/events/schema/eventtype/raptor_sighting | E16: hawk_rep | F16: https://mugie.pamdas.org/static/sprite-src/hawk_rep.svg | G16: 9 | H16: 4 | I16: Raptor Sighting | J16: Avian Events | K16: 87b9675f-312c-4985-a5bf-38ff4423146e | L16: TRUE | N16: raptor_sighting | O16: =HYPERLINK("#'raptor_sighting'!A1","Open") -> Open
A17: invasive_species_rep | B17: Invasive Species (invasive_species_rep) | C17: v1 | D17: https://mugie.pamdas.org/api/v1.0/activity/events/schema/eventtype/invasive_species_rep | E17: invasive_species_rep | F17: https://mugie.pamdas.org/static/invasive_species-black.svg | G17: 3 | H17: 3 | I17: Invasive Species | J17: HIDDEN | K17: 50acb72c-5038-4f7f-9cb6-d432026f5032 | L17: TRUE | N17: invasive_species_rep | O17: =HYPERLINK("#'invasive_species_rep'!A1","Open") -> Open
A18: airplane | B18: Trespassing Report | C18: v1 | D18: https://mugie.pamdas.org/api/v1.0/activity/events/schema/eventtype/airplane | E18: plane-patrol-icon | F18: https://mugie.pamdas.org/static/sprite-src/plane-patrol-icon.svg | G18: 5 | H18: 2 | I18: Airplane | J18: Human Activities | K18: 748f7f8a-1a22-4300-9229-b7e15e7ec142 | L18: TRUE | N18: airplane | O18: =HYPERLINK("#'airplane'!A1","Open") -> Open
A19: armed_people | B19: Gunshot Report | C19: v1 | D19: https://mugie.pamdas.org/api/v1.0/activity/events/schema/eventtype/armed_people | E19: bushmeat_poacher_rep | F19: https://mugie.pamdas.org/static/sprite-src/bushmeat_poacher_rep.svg | G19: 3 | H19: 0 | I19: Armed people | J19: Human Activities | K19: 748f7f8a-1a22-4300-9229-b7e15e7ec142 | L19: TRUE | N19: armed_people | O19: =HYPERLINK("#'armed_people'!A1","Open") -> Open
A20: bushmeattrading | B20: Bushmeat & Trading Report | C20: v1 | D20: https://mugie.pamdas.org/api/v1.0/activity/events/schema/eventtype/bushmeattrading | E20: bushmeat_poacher_rep | F20: https://mugie.pamdas.org/static/sprite-src/bushmeat_poacher_rep.svg | G20: 8 | H20: 3 | I20: Bushmeat & Trophy | J20: Human Activities | K20: 748f7f8a-1a22-4300-9229-b7e15e7ec142 | L20: TRUE | N20: bushmeattrading | O20: =HYPERLINK("#'bushmeattrading'!A1","Open") -> Open
A21: fence_rp | B21: EventType fence Data | C21: v1 | D21: https://mugie.pamdas.org/api/v1.0/activity/events/schema/eventtype/fence_rp | E21: fence_voltage_rep | F21: https://mugie.pamdas.org/static/sprite-src/fence_voltage_rep.svg | G21: 21 | H21: 3 | I21: Fence | J21: Human Activities | K21: 748f7f8a-1a22-4300-9229-b7e15e7ec142 | L21: TRUE | N21: fence_rp | O21: =HYPERLINK("#'fence_rp'!A1","Open") -> Open
A22: gunshot | B22: Gunshot Report | C22: v1 | D22: https://mugie.pamdas.org/api/v1.0/activity/events/schema/eventtype/gunshot | E22: AK_47_rep | F22: https://mugie.pamdas.org/static/sprite-src/AK_47_rep.svg | G22: 4 | H22: 0 | I22: Gunshot | J22: Human Activities | K22: 748f7f8a-1a22-4300-9229-b7e15e7ec142 | L22: TRUE | N22: gunshot | O22: =HYPERLINK("#'gunshot'!A1","Open") -> Open
A23: illegal_activity | B23: EventType Test Data | C23: v1 | D23: https://mugie.pamdas.org/api/v1.0/activity/events/schema/eventtype/illegal_activity | E23: illegal_activity_rep | F23: https://mugie.pamdas.org/static/illegal_activity-black.svg | G23: 8 | H23: 1 | I23: Illegal Activity | J23: Human Activities | K23: 748f7f8a-1a22-4300-9229-b7e15e7ec142 | L23: TRUE | N23: illegal_activity | O23: =HYPERLINK("#'illegal_activity'!A1","Open") -> Open
A24: illegal_grazing | B24: Illegal grazing Report | C24: v1 | D24: https://mugie.pamdas.org/api/v1.0/activity/events/schema/eventtype/illegal_grazing | E24: activity_rep | F24: https://mugie.pamdas.org/static/sprite-src/activity_rep.svg | G24: 7 | H24: 3 | I24: Illegal Grazing | J24: Human Activities | K24: 748f7f8a-1a22-4300-9229-b7e15e7ec142 | L24: TRUE | N24: illegal_grazing | O24: =HYPERLINK("#'illegal_grazing'!A1","Open") -> Open
A25: incident_collection | B25: Incident Collection | C25: v1 | D25: https://mugie.pamdas.org/api/v1.0/activity/events/schema/eventtype/incident_collection | E25: incident_collection | F25: https://mugie.pamdas.org/static/incident_collection-black.svg | G25: 3 | H25: 2 | I25: Incident Collection | J25: Human Activities | K25: 748f7f8a-1a22-4300-9229-b7e15e7ec142 | L25: TRUE | N25: incident_collection | O25: =HYPERLINK("#'incident_collection'!A1","Open") -> Open
A26: invasiveplantrep | B26: Alien Plant Control Report | C26: v1 | D26: https://mugie.pamdas.org/api/v1.0/activity/events/schema/eventtype/invasiveplantrep | E26: invasive_species_rep | F26: https://mugie.pamdas.org/static/invasive_species-black.svg | G26: 2 | H26: 1 | I26: Invasive Plant Control | J26: Human Activities | K26: 748f7f8a-1a22-4300-9229-b7e15e7ec142 | L26: TRUE | N26: invasiveplantrep | O26: =HYPERLINK("#'invasiveplantrep'!A1","Open") -> Open
A27: natural_production | B27: Natural production Report | C27: v1 | D27: https://mugie.pamdas.org/api/v1.0/activity/events/schema/eventtype/natural_production | E27: invasive_species_rep | F27: https://mugie.pamdas.org/static/invasive_species-black.svg | G27: 6 | H27: 3 | I27: Natural Products | J27: Human Activities | K27: 748f7f8a-1a22-4300-9229-b7e15e7ec142 | L27: TRUE | N27: natural_production | O27: =HYPERLINK("#'natural_production'!A1","Open") -> Open
A28: on_transit | B28: Livestock On transit | C28: v1 | D28: https://mugie.pamdas.org/api/v1.0/activity/events/schema/eventtype/on_transit | E28: livestock_movement_rep | F28: https://mugie.pamdas.org/static/sprite-src/livestock_movement_rep.svg | G28: 6 | H28: 1 | I28: Livestock On Transit | J28: Human Activities | K28: 748f7f8a-1a22-4300-9229-b7e15e7ec142 | L28: TRUE | N28: on_transit | O28: =HYPERLINK("#'on_transit'!A1","Open") -> Open
A29: recoveriestrophies | B29: EventType Recoveries - Trophies (confiscationtrophies_rep) | C29: v1 | D29: https://mugie.pamdas.org/api/v1.0/activity/events/schema/eventtype/recoveriestrophies | E29: recoveriestrophies | F29: https://mugie.pamdas.org/static/generic-black.svg | G29: 30 | H29: 0 | I29: Recoveries - Trophies | J29: Human Activities | K29: 748f7f8a-1a22-4300-9229-b7e15e7ec142 | L29: TRUE | N29: recoveriestrophies | O29: =HYPERLINK("#'recoveriestrophies'!A1","Open") -> Open
A30: sandalwood | B30: Placeholder schema | C30: v1 | D30: https://mugie.pamdas.org/api/v1.0/activity/events/schema/eventtype/sandalwood | E30: natural_feature_rep | F30: https://mugie.pamdas.org/static/sprite-src/natural_feature_rep.svg | G30: 2 | H30: 0 | I30: Sandalwood | J30: Human Activities | K30: 748f7f8a-1a22-4300-9229-b7e15e7ec142 | L30: TRUE | N30: sandalwood | O30: =HYPERLINK("#'sandalwood'!A1","Open") -> Open
A31: sandalwood_poly | B31: Placeholder schema | C31: v1 | D31: https://mugie.pamdas.org/api/v1.0/activity/events/schema/eventtype/sandalwood_poly | E31: natural_feature_rep | F31: https://mugie.pamdas.org/static/sprite-src/natural_feature_rep.svg | G31: 2 | H31: 0 | I31: Sandalwood Polygon | J31: Human Activities | K31: 748f7f8a-1a22-4300-9229-b7e15e7ec142 | L31: TRUE | N31: sandalwood_poly | O31: =HYPERLINK("#'sandalwood_poly'!A1","Open") -> Open
A32: snares | B32: Snares Report | C32: v1 | D32: https://mugie.pamdas.org/api/v1.0/activity/events/schema/eventtype/snares | E32: snare_rep | F32: https://mugie.pamdas.org/static/snare-black.svg | G32: 7 | H32: 3 | I32: Snares | J32: Human Activities | K32: 748f7f8a-1a22-4300-9229-b7e15e7ec142 | L32: TRUE | N32: snares | O32: =HYPERLINK("#'snares'!A1","Open") -> Open
A33: spoor | B33: Human Spoor | C33: v1 | D33: https://mugie.pamdas.org/api/v1.0/activity/events/schema/eventtype/spoor | E33: spoor_rep | F33: https://mugie.pamdas.org/static/spoor-black.svg | G33: 4 | H33: 4 | I33: Spoor | J33: Human Activities | K33: 748f7f8a-1a22-4300-9229-b7e15e7ec142 | L33: TRUE | N33: spoor | O33: =HYPERLINK("#'spoor'!A1","Open") -> Open
A34: trespassing | B34: Trespassing Report | C34: v1 | D34: https://mugie.pamdas.org/api/v1.0/activity/events/schema/eventtype/trespassing | E34: crossing_rep | F34: https://mugie.pamdas.org/static/sprite-src/crossing_rep.svg | G34: 5 | H34: 2 | I34: Trespassing | J34: Human Activities | K34: 748f7f8a-1a22-4300-9229-b7e15e7ec142 | L34: TRUE | N34: trespassing | O34: =HYPERLINK("#'trespassing'!A1","Open") -> Open
A35: wood_collecting | B35: Wood collecting Report | C35: v1 | D35: https://mugie.pamdas.org/api/v1.0/activity/events/schema/eventtype/wood_collecting | E35: timber-observation_rep | F35: https://mugie.pamdas.org/static/sprite-src/timber-observation_rep.svg | G35: 9 | H35: 4 | I35: Wood Collection | J35: Human Activities | K35: 748f7f8a-1a22-4300-9229-b7e15e7ec142 | L35: TRUE | N35: wood_collecting | O35: =HYPERLINK("#'wood_collecting'!A1","Open") -> Open
A36: baton_rep | B36: EventType Test Data | C36: v1 | D36: https://mugie.pamdas.org/api/v1.0/activity/events/schema/eventtype/baton_rep | E36: ranger_shot_rep | F36: https://mugie.pamdas.org/static/ranger_shot_rep-black.svg | G36: 10 | H36: 1 | I36: Baton Report | J36: Human Wildlife Conflict | K36: e28e5162-3409-48ce-8d01-8bade1d5b4d6 | L36: TRUE | N36: baton_rep | O36: =HYPERLINK("#'baton_rep'!A1","Open") -> Open
A37: hwc_crops | B37: EventType Test Data | C37: v1 | D37: https://mugie.pamdas.org/api/v1.0/activity/events/schema/eventtype/hwc_crops | E37: human_wildlife_conflict_rep | F37: https://mugie.pamdas.org/static/human_wildlife_conflict-black.svg | G37: 24 | H37: 1 | I37: HWC Crop Damage | J37: Human Wildlife Conflict | K37: e28e5162-3409-48ce-8d01-8bade1d5b4d6 | L37: TRUE | N37: hwc_crops | O37: =HYPERLINK("#'hwc_crops'!A1","Open") -> Open
A38: hwc_human_death | B38: EventType Test Data | C38: v1 | D38: https://mugie.pamdas.org/api/v1.0/activity/events/schema/eventtype/hwc_human_death | E38: hwc_human_death_rep | F38: https://mugie.pamdas.org/static/sprite-src/hwc_human_death_rep.svg | G38: 20 | H38: 1 | I38: HWC Human Death | J38: Human Wildlife Conflict | K38: e28e5162-3409-48ce-8d01-8bade1d5b4d6 | L38: TRUE | N38: hwc_human_death | O38: =HYPERLINK("#'hwc_human_death'!A1","Open") -> Open
A39: hwc_human_injury | B39: EventType Test Data | C39: v1 | D39: https://mugie.pamdas.org/api/v1.0/activity/events/schema/eventtype/hwc_human_injury | E39: hwc_alert_rep | F39: https://mugie.pamdas.org/static/sprite-src/hwc_alert_rep.svg | G39: 20 | H39: 1 | I39: HWC Human Injury | J39: Human Wildlife Conflict | K39: e28e5162-3409-48ce-8d01-8bade1d5b4d6 | L39: TRUE | N39: hwc_human_injury | O39: =HYPERLINK("#'hwc_human_injury'!A1","Open") -> Open
A40: hwc_livestock_pred_rv00 | B40: EventType Test Data | C40: v1 | D40: https://mugie.pamdas.org/api/v1.0/activity/events/schema/eventtype/hwc_livestock_pred_rv00 | E40: livestock-death_rep | F40: https://mugie.pamdas.org/static/sprite-src/livestock-death_rep.svg | G40: 22 | H40: 4 | I40: HWC Livestock Predation | J40: Human Wildlife Conflict | K40: e28e5162-3409-48ce-8d01-8bade1d5b4d6 | L40: TRUE | N40: hwc_livestock_pred_rv00 | O40: =HYPERLINK("#'hwc_livestock_pred_rv00'!A1","Open") -> Open
A41: hwc_mitigation_response | B41: EventType Test Data | C41: v1 | D41: https://mugie.pamdas.org/api/v1.0/activity/events/schema/eventtype/hwc_mitigation_response | E41: hwc_mitigation_response_rep | F41: https://mugie.pamdas.org/static/sprite-src/hwc_mitigation_response_rep.svg | G41: 15 | H41: 1 | I41: HWC Mitigation Response | J41: Human Wildlife Conflict | K41: e28e5162-3409-48ce-8d01-8bade1d5b4d6 | L41: TRUE | N41: hwc_mitigation_response | O41: =HYPERLINK("#'hwc_mitigation_response'!A1","Open") -> Open
A42: hwc_property | B42: EventType Test Data | C42: v1 | D42: https://mugie.pamdas.org/api/v1.0/activity/events/schema/eventtype/hwc_property | E42: hwc_alert_rep | F42: https://mugie.pamdas.org/static/sprite-src/hwc_alert_rep.svg | G42: 21 | H42: 1 | I42: HWC Property Damage | J42: Human Wildlife Conflict | K42: e28e5162-3409-48ce-8d01-8bade1d5b4d6 | L42: TRUE | N42: hwc_property | O42: =HYPERLINK("#'hwc_property'!A1","Open") -> Open
A43: hwc_retaliation | B43: EventType Test Data | C43: v1 | D43: https://mugie.pamdas.org/api/v1.0/activity/events/schema/eventtype/hwc_retaliation | E43: hwc_alert_rep | F43: https://mugie.pamdas.org/static/sprite-src/hwc_alert_rep.svg | G43: 18 | H43: 1 | I43: HWC Retaliation | J43: Human Wildlife Conflict | K43: e28e5162-3409-48ce-8d01-8bade1d5b4d6 | L43: TRUE | N43: hwc_retaliation | O43: =HYPERLINK("#'hwc_retaliation'!A1","Open") -> Open
A44: hwc_threat | B44: HWC - Threat Report | C44: v1 | D44: https://mugie.pamdas.org/api/v1.0/activity/events/schema/eventtype/hwc_threat | E44: hwc_threat_rep | F44: https://mugie.pamdas.org/static/sprite-src/hwc_threat_rep.svg | G44: 16 | H44: 1 | I44: HWC Threat | J44: Human Wildlife Conflict | K44: e28e5162-3409-48ce-8d01-8bade1d5b4d6 | L44: TRUE | N44: hwc_threat | O44: =HYPERLINK("#'hwc_threat'!A1","Open") -> Open
A45: crop_damage | B45: Crop Damage Report | C45: v1 | D45: https://mugie.pamdas.org/api/v1.0/activity/events/schema/eventtype/crop_damage | E45: land_clearance_rep | F45: https://mugie.pamdas.org/static/sprite-src/land_clearance_rep.svg | G45: 10 | H45: 6 | I45: Crop Damage | J45: Human Wildlife Interaction | K45: fcb31f92-b151-4be2-9518-3800aabcd97c | L45: TRUE | N45: crop_damage | O45: =HYPERLINK("#'crop_damage'!A1","Open") -> Open
A46: elephant_out_of_geofence | B46: Elephants Out of Geofence | C46: v1 | D46: https://mugie.pamdas.org/api/v1.0/activity/events/schema/eventtype/elephant_out_of_geofence | E46: hwc_alert_rep | F46: https://mugie.pamdas.org/static/sprite-src/hwc_alert_rep.svg | G46: 3 | H46: 0 | I46: Elephant out of Geofence | J46: Human Wildlife Interaction | K46: fcb31f92-b151-4be2-9518-3800aabcd97c | L46: TRUE | N46: elephant_out_of_geofence | O46: =HYPERLINK("#'elephant_out_of_geofence'!A1","Open") -> Open
A47: human_death | B47: Human death Report | C47: v1 | D47: https://mugie.pamdas.org/api/v1.0/activity/events/schema/eventtype/human_death | E47: loss_of_human_life_rep | F47: https://mugie.pamdas.org/static/loss_of_human_life-black.svg | G47: 8 | H47: 4 | I47: Human Death | J47: Human Wildlife Interaction | K47: fcb31f92-b151-4be2-9518-3800aabcd97c | L47: TRUE | N47: human_death | O47: =HYPERLINK("#'human_death'!A1","Open") -> Open
A48: human_injury | B48: Human Injury Report | C48: v1 | D48: https://mugie.pamdas.org/api/v1.0/activity/events/schema/eventtype/human_injury | E48: medevac_rep | F48: https://mugie.pamdas.org/static/medevac_rep-black.svg | G48: 8 | H48: 4 | I48: Human Injury | J48: Human Wildlife Interaction | K48: fcb31f92-b151-4be2-9518-3800aabcd97c | L48: TRUE | N48: human_injury | O48: =HYPERLINK("#'human_injury'!A1","Open") -> Open
A49: human_threats | B49: Human threats Report | C49: v1 | D49: https://mugie.pamdas.org/api/v1.0/activity/events/schema/eventtype/human_threats | E49: poaching_route_rep | F49: https://mugie.pamdas.org/static/sprite-src/poaching_route_rep.svg | G49: 7 | H49: 4 | I49: Human Threats | J49: Human Wildlife Interaction | K49: fcb31f92-b151-4be2-9518-3800aabcd97c | L49: TRUE | N49: human_threats | O49: =HYPERLINK("#'human_threats'!A1","Open") -> Open
A50: lion_sighting | B50: EventType Test Data | C50: v1 | D50: https://mugie.pamdas.org/api/v1.0/activity/events/schema/eventtype/lion_sighting | E50: lion_sighting_rep | F50: https://mugie.pamdas.org/static/lion_sighting-black.svg | G50: 23 | H50: 16 | I50: Lion Sighting | J50: Human Wildlife Interaction | K50: fcb31f92-b151-4be2-9518-3800aabcd97c | L50: TRUE | N50: lion_sighting | O50: =HYPERLINK("#'lion_sighting'!A1","Open") -> Open
A51: predation_at_boma | B51: Predation at Boma Report | C51: v1 | D51: https://mugie.pamdas.org/api/v1.0/activity/events/schema/eventtype/predation_at_boma | E51: open_gate_rep | F51: https://mugie.pamdas.org/static/sprite-src/open_gate_rep.svg | G51: 14 | H51: 8 | I51: Predation at Boma | J51: Human Wildlife Interaction | K51: fcb31f92-b151-4be2-9518-3800aabcd97c | L51: TRUE | N51: predation_at_boma | O51: =HYPERLINK("#'predation_at_boma'!A1","Open") -> Open
A52: predation_while_grazing | B52: Predation while grazing Report | C52: v1 | D52: https://mugie.pamdas.org/api/v1.0/activity/events/schema/eventtype/predation_while_grazing | E52: feeding_rep | F52: https://mugie.pamdas.org/static/sprite-src/feeding_rep.svg | G52: 13 | H52: 7 | I52: Predation While Grazing | J52: Human Wildlife Interaction | K52: fcb31f92-b151-4be2-9518-3800aabcd97c | L52: TRUE | N52: predation_while_grazing | O52: =HYPERLINK("#'predation_while_grazing'!A1","Open") -> Open
A53: road_kill | B53: Road Kill | C53: v1 | D53: https://mugie.pamdas.org/api/v1.0/activity/events/schema/eventtype/road_kill | E53: accident_rep | F53: https://mugie.pamdas.org/static/accident-black.svg | G53: 6 | H53: 5 | I53: Road Kill | J53: Human Wildlife Interaction | K53: fcb31f92-b151-4be2-9518-3800aabcd97c | L53: TRUE | N53: road_kill | O53: =HYPERLINK("#'road_kill'!A1","Open") -> Open
A54: wfd | B54: WFD Report | C54: v1 | D54: https://mugie.pamdas.org/api/v1.0/activity/events/schema/eventtype/wfd | E54: animalfence_rep | F54: https://mugie.pamdas.org/static/sprite-src/animalfence_rep.svg | G54: 5 | H54: 1 | I54: Wildlife Fence Damage | J54: Human Wildlife Interaction | K54: fcb31f92-b151-4be2-9518-3800aabcd97c | L54: TRUE | N54: wfd | O54: =HYPERLINK("#'wfd'!A1","Open") -> Open
A55: rainfall_data | B55: Rainfall Report | C55: v1 | D55: https://mugie.pamdas.org/api/v1.0/activity/events/schema/eventtype/rainfall_data | E55: rainfall_rep | F55: https://mugie.pamdas.org/static/sprite-src/rainfall_rep.svg | G55: 3 | H55: 2 | I55: Rainfall | J55: Logistics | K55: 2f7ecd77-43db-4687-adba-58fcd42fac14 | L55: TRUE | N55: rainfall_data | O55: =HYPERLINK("#'rainfall_data'!A1","Open") -> Open
A56: water-required | B56: Water Required | C56: v1 | D56: https://mugie.pamdas.org/api/v1.0/activity/events/schema/eventtype/water-required | E56: water_level_rep | F56: https://mugie.pamdas.org/static/water_level-black.svg | G56: 2 | H56: 1 | I56: Water Required | J56: Logistics | K56: 2f7ecd77-43db-4687-adba-58fcd42fac14 | L56: TRUE | N56: water-required | O56: =HYPERLINK("#'water-required'!A1","Open") -> Open
A57: fence_dam_repair | B57: EventType Test Data | C57: v1 | D57: https://mugie.pamdas.org/api/v1.0/activity/events/schema/eventtype/fence_dam_repair | E57: fence_breakage_rep | F57: https://mugie.pamdas.org/static/fence_breakage-black.svg | G57: 8 | H57: 5 | I57: Fence Damage and Repair | J57: Mugie Mainteinance Reports | K57: 48b89d60-9ab5-4ce3-af18-615f3b5321c7 | L57: TRUE | N57: fence_dam_repair | O57: =HYPERLINK("#'fence_dam_repair'!A1","Open") -> Open
A58: smartinjuredanimals | B58: Placeholder schema | C58: v1 | D58: https://mugie.pamdas.org/api/v1.0/activity/events/schema/eventtype/smartinjuredanimals | E58: injured_animal_rep | F58: https://mugie.pamdas.org/static/injured_animal-black.svg | G58: 1 | H58: 0 | I58: Injuredanimals | J58: Mugie SMART | K58: 15f4b227-7cfa-43e7-9638-e366f9be62db | L58: TRUE | N58: smartinjuredanimals | O58: =HYPERLINK("#'smartinjuredanimals'!A1","Open") -> Open
A59: mugiesmart | B59: Placeholder schema | C59: v1 | D59: https://mugie.pamdas.org/api/v1.0/activity/events/schema/eventtype/mugiesmart | E59: mugiesmart | F59: https://mugie.pamdas.org/static/generic-black.svg | G59: 1 | H59: 0 | I59: Mugie SMART | J59: patrol coverage | K59: 0fbb0cf4-b241-482f-ad67-e70ee1f8f5bb | L59: TRUE | N59: mugiesmart | O59: =HYPERLINK("#'mugiesmart'!A1","Open") -> Open
A60: tpfa_nesting_site | B60: EventType Test Data | C60: v1 | D60: https://mugie.pamdas.org/api/v1.0/activity/events/schema/eventtype/tpfa_nesting_site | E60: bird-nest_rep | F60: https://mugie.pamdas.org/static/sprite-src/bird-nest_rep.svg | G60: 9 | H60: 1 | I60: TPFA-Nesting Site | J60: TPFA-The Peregrine Fund Events | K60: 2c27419c-e124-4daa-a351-a0f95e8aa4ea | L60: TRUE | N60: tpfa_nesting_site | O60: =HYPERLINK("#'tpfa_nesting_site'!A1","Open") -> Open
A61: dead_animal_rv001 | B61: EventType Test Data | C61: v1 | D61: https://mugie.pamdas.org/api/v1.0/activity/events/schema/eventtype/dead_animal_rv001 | E61: carcass_rep | F61: https://mugie.pamdas.org/static/carcass-black.svg | G61: 25 | H61: 12 | I61: Dead Animal | J61: VETERINARY | K61: 56af8fb2-b218-49c2-8105-04e7b85e5eb4 | L61: TRUE | N61: dead_animal_rv001 | O61: =HYPERLINK("#'dead_animal_rv001'!A1","Open") -> Open
A62: live_animal_rv001 | B62: EventType Test Data | C62: v1 | D62: https://mugie.pamdas.org/api/v1.0/activity/events/schema/eventtype/live_animal_rv001 | E62: injured_animal_rep | F62: https://mugie.pamdas.org/static/injured_animal-black.svg | G62: 42 | H62: 34 | I62: Live Animal | J62: VETERINARY | K62: 56af8fb2-b218-49c2-8105-04e7b85e5eb4 | L62: TRUE | N62: live_animal_rv001 | O62: =HYPERLINK("#'live_animal_rv001'!A1","Open") -> Open
A63: injured_animal | B63: Injured Animal Report | C63: v1 | D63: https://mugie.pamdas.org/api/v1.0/activity/events/schema/eventtype/injured_animal | E63: injured_animal_rep | F63: https://mugie.pamdas.org/static/injured_animal-black.svg | G63: 5 | H63: 2 | I63: Injured Animal | J63: Wildlife Health | K63: 8659ecac-d659-4aa6-857e-d75b33b41777 | L63: TRUE | N63: injured_animal | O63: =HYPERLINK("#'injured_animal'!A1","Open") -> Open
A64: wildlife_disease_dead_animal | B64: Wildlife disease (Dead animal) Report | C64: v1 | D64: https://mugie.pamdas.org/api/v1.0/activity/events/schema/eventtype/wildlife_disease_dead_animal | E64: white_rhino_carcass_natural_rep | F64: https://mugie.pamdas.org/static/sprite-src/white_rhino_carcass_natural_rep.svg | G64: 17 | H64: 13 | I64: Wildlife Disease (Dead Animal) | J64: Wildlife Health | K64: 8659ecac-d659-4aa6-857e-d75b33b41777 | L64: TRUE | N64: wildlife_disease_dead_animal | O64: =HYPERLINK("#'wildlife_disease_dead_animal'!A1","Open") -> Open
A65: wildlife_disease_live_animal | B65: Wildlife disease (Live animal) Report | C65: v1 | D65: https://mugie.pamdas.org/api/v1.0/activity/events/schema/eventtype/wildlife_disease_live_animal | E65: mist_rep | F65: https://mugie.pamdas.org/static/mist-black.svg | G65: 21 | H65: 17 | I65: Wildlife Disease (Live Animal) | J65: Wildlife Health | K65: 8659ecac-d659-4aa6-857e-d75b33b41777 | L65: TRUE | N65: wildlife_disease_live_animal | O65: =HYPERLINK("#'wildlife_disease_live_animal'!A1","Open") -> Open
A66: carcasses | B66: Carcasses Report | C66: v1 | D66: https://mugie.pamdas.org/api/v1.0/activity/events/schema/eventtype/carcasses | E66: carcass_rep | F66: https://mugie.pamdas.org/static/carcass-black.svg | G66: 8 | H66: 4 | I66: Carcasses | J66: Wildlife Sighting | K66: bcd1284e-7697-40c6-8cbf-254a0b4a294d | L66: TRUE | N66: carcasses | O66: =HYPERLINK("#'carcasses'!A1","Open") -> Open
A67: live_animals | B67: Live Animals Report | C67: v1 | D67: https://mugie.pamdas.org/api/v1.0/activity/events/schema/eventtype/live_animals | E67: other_wildlife_sightings_rep | F67: https://mugie.pamdas.org/static/other_wildlife_sightings-black.svg | G67: 2 | H67: 1 | I67: Live Animals | J67: Wildlife Sighting | K67: bcd1284e-7697-40c6-8cbf-254a0b4a294d | L67: TRUE | N67: live_animals | O67: =HYPERLINK("#'live_animals'!A1","Open") -> Open

Sheet suyian_schemas
A1: event_value | B1: schema_title | C1: api_version | D1: schema_id | E1: icon_id | F1: image_url | G1: n_fields | H1: n_enums | I1: event_name | J1: event_category_display | K1: event_category_id | L1: event_is_active | M1: event_updated_at | N1: sheet_name
A2: acoustic_detection | B2: Acoustic Detection (acoustic_detection) | C2: v1 | D2: https://suyian.pamdas.org/api/v1.0/activity/events/schema/eventtype/acoustic_detection | E2: radar_rep | F2: https://suyian.pamdas.org/static/sprite-src/radar_rep.svg | G2: 3 | H2: 0 | I2: Acoustic Detection | J2: Analyzer Event | K2: ef230385-5afc-40d1-ad07-c811f6da2b3c | L2: TRUE | N2: acoustic_detection
A3: baboon_rep | B3: Total Number of Animals Sighted | C3: v1 | D3: https://suyian.pamdas.org/api/v1.0/activity/events/schema/eventtype/baboon_rep | E3: baboon_rep | F3: https://suyian.pamdas.org/static/sprite-src/baboon_rep.svg | G3: 1 | H3: 0 | I3: Baboon | J3: Wildlife Monitoring. | K3: 7113fef7-7eaf-460d-82e0-1462171bcd57 | L3: TRUE | N3: baboon_rep
A4: blackbackedjackal | B4: Total Number of Animals Sighted | C4: v1 | D4: https://suyian.pamdas.org/api/v1.0/activity/events/schema/eventtype/blackbackedjackal | E4: jackal_rep | F4: https://suyian.pamdas.org/static/sprite-src/jackal_rep.svg | G4: 1 | H4: 0 | I4: Black-backed jackal | J4: Wildlife Monitoring. | K4: 7113fef7-7eaf-460d-82e0-1462171bcd57 | L4: TRUE | N4: blackbackedjackal
A5: buffalo_rep | B5: Total Number of Animals Sighted | C5: v1 | D5: https://suyian.pamdas.org/api/v1.0/activity/events/schema/eventtype/buffalo_rep | E5: buffalo_rep | F5: https://suyian.pamdas.org/static/sprite-src/buffalo_rep.svg | G5: 1 | H5: 0 | I5: Buffalo | J5: Wildlife Monitoring. | K5: 7113fef7-7eaf-460d-82e0-1462171bcd57 | L5: TRUE | N5: buffalo_rep
A6: cheetah_rep | B6: Total Number of Animals Sighted | C6: v1 | D6: https://suyian.pamdas.org/api/v1.0/activity/events/schema/eventtype/cheetah_rep | E6: cheetah_sighting_rep | F6: https://suyian.pamdas.org/static/sprite-src/cheetah_sighting_rep.svg | G6: 1 | H6: 0 | I6: Cheetah | J6: Wildlife Monitoring. | K6: 7113fef7-7eaf-460d-82e0-1462171bcd57 | L6: TRUE | N6: cheetah_rep
A7: dead_animal_revision_2 | B7: EventType Test Data | C7: v1 | D7: https://suyian.pamdas.org/api/v1.0/activity/events/schema/eventtype/dead_animal_revision_2 | E7: carcass_rep | F7: https://suyian.pamdas.org/static/carcass-black.svg | G7: 25 | H7: 12 | I7: Dead Animal | J7: VETERINARY | K7: 72142042-edc8-4770-b6a7-021cee90169a | L7: TRUE | N7: dead_animal_revision_2
A8: dikdik_rep | B8: Total Number of Animals Sighted | C8: v1 | D8: https://suyian.pamdas.org/api/v1.0/activity/events/schema/eventtype/dikdik_rep | E8: duiker_rep | F8: https://suyian.pamdas.org/static/sprite-src/duiker_rep.svg | G8: 1 | H8: 0 | I8: Dikdik | J8: Wildlife Monitoring. | K8: 7113fef7-7eaf-460d-82e0-1462171bcd57 | L8: TRUE | N8: dikdik_rep
A9: distancesampling_rep | B9: Distance Sampling Report | C9: v1 | D9: https://suyian.pamdas.org/api/v1.0/activity/events/schema/eventtype/distancesampling_rep | E9: sighting_rep | F9: https://suyian.pamdas.org/static/sprite-src/sighting_rep.svg | G9: 5 | H9: 2 | I9: Distance Sampling | J9: Wildlife Monitoring. | K9: 7113fef7-7eaf-460d-82e0-1462171bcd57 | L9: TRUE | N9: distancesampling_rep
A10: eland_rep | B10: Total Number of Animals Sighted | C10: v1 | D10: https://suyian.pamdas.org/api/v1.0/activity/events/schema/eventtype/eland_rep | E10: eland_rep | F10: https://suyian.pamdas.org/static/sprite-src/eland_rep.svg | G10: 1 | H10: 0 | I10: Eland | J10: Wildlife Monitoring. | K10: 7113fef7-7eaf-460d-82e0-1462171bcd57 | L10: TRUE | N10: eland_rep
A11: elephant_mortality_mike | B11: Elephant Mortality | C11: v1 | D11: https://suyian.pamdas.org/api/v1.0/activity/events/schema/eventtype/elephant_mortality_mike | E11: elephant_mortality_rep | F11: https://suyian.pamdas.org/static/elephant_mortality-black.svg | G11: 9 | H11: 7 | I11: Elephant Mortality | J11: Wildlife Monitoring. | K11: 7113fef7-7eaf-460d-82e0-1462171bcd57 | L11: TRUE | N11: elephant_mortality_mike
A12: elephant_rep | B12: Total Number of Animals Sighted | C12: v1 | D12: https://suyian.pamdas.org/api/v1.0/activity/events/schema/eventtype/elephant_rep | E12: elephant_signs-event | F12: https://suyian.pamdas.org/static/sprite-src/elephant_signs-event.svg | G12: 1 | H12: 0 | I12: Elephant | J12: Wildlife Monitoring. | K12: 7113fef7-7eaf-460d-82e0-1462171bcd57 | L12: TRUE | N12: elephant_rep
A13: firms_rep | B13: FIRMS Fire Report Schema | C13: v1 | D13: https://suyian.pamdas.org/api/v1.0/activity/events/schema/eventtype/firms_rep | E13: firms_rep | F13: https://suyian.pamdas.org/static/firms_rep-black.svg | G13: 6 | H13: 0 | I13: FIRMS Report | J13: Analyzer Event | K13: ef230385-5afc-40d1-ad07-c811f6da2b3c | L13: TRUE | N13: firms_rep
... A55: wilddog_rep | B55: Total Number of Animals Sighted | C55: v1 | D55: https://suyian.pamdas.org/api/v1.0/activity/events/schema/eventtype/wilddog_rep | E55: wild_dog_rep | F55: https://suyian.pamdas.org/static/sprite-src/wild_dog_rep.svg | G55: 1 | H55: 0 | I55: Wild dog | J55: Wildlife Monitoring. | K55: 7113fef7-7eaf-460d-82e0-1462171bcd57 | L55: TRUE | N55: wilddog_rep

Sheet sosian_schemas
A1: event_value | B1: schema_title | C1: api_version | D1: schema_id | E1: icon_id | F1: image_url | G1: n_fields | H1: n_enums | I1: event_name | J1: event_category_display | K1: event_category_id | L1: event_is_active | M1: event_updated_at | N1: sheet_name
A2: acoustic_detection | B2: Acoustic Detection (acoustic_detection) | C2: v1 | D2: https://sosian.pamdas.org/api/v1.0/activity/events/schema/eventtype/acoustic_detection | E2: radar_rep | F2: https://sosian.pamdas.org/static/sprite-src/radar_rep.svg | G2: 3 | H2: 0 | I2: Acoustic Detection | J2: Analyzer Event | K2: ef230385-5afc-40d1-ad07-c811f6da2b3c | L2: TRUE | N2: acoustic_detection
A3: area_polygon_tool | B3: Polygon Tool (polygon_sighting) | C3: v1 | D3: https://sosian.pamdas.org/api/v1.0/activity/events/schema/eventtype/area_polygon_tool | E3: geofence_break_rep | F3: https://sosian.pamdas.org/static/geofence_break-black.svg | G3: 3 | H3: 2 | I3: Area Measurement Tool | J3: Habitat Health | K3: a869348d-b8a8-426c-a938-c4627de48216 | L3: TRUE | N3: area_polygon_tool
A4: buffalo | B4: Buffalo Report | C4: v1 | D4: https://sosian.pamdas.org/api/v1.0/activity/events/schema/eventtype/buffalo | E4: buffalo_rep | F4: https://sosian.pamdas.org/static/sprite-src/buffalo_rep.svg | G4: 1 | H4: 0 | I4: Buffalo | J4: Wildlife Sighting | K4: e7860c5e-49f2-4393-b733-afba3e8b51eb | L4: TRUE | N4: buffalo
A5: bushmeattrading | B5: Bushmeat & Trading Report | C5: v1 | D5: https://sosian.pamdas.org/api/v1.0/activity/events/schema/eventtype/bushmeattrading | E5: bushmeat_poacher_rep | F5: https://sosian.pamdas.org/static/sprite-src/bushmeat_poacher_rep.svg | G5: 8 | H5: 3 | I5: Bushmeat & Trophy | J5: Human Activities | K5: 116904c3-87e9-4599-bf1f-530109c13cb7 | L5: TRUE | N5: bushmeattrading
A6: carcasses | B6: Carcasses Report | C6: v1 | D6: https://sosian.pamdas.org/api/v1.0/activity/events/schema/eventtype/carcasses | E6: carcass_rep | F6: https://sosian.pamdas.org/static/carcass-black.svg | G6: 8 | H6: 4 | I6: Carcasses | J6: Wildlife Sighting | K6: e7860c5e-49f2-4393-b733-afba3e8b51eb | L6: TRUE | N6: carcasses
A7: cheetah | B7: cheetah Report | C7: v1 | D7: https://sosian.pamdas.org/api/v1.0/activity/events/schema/eventtype/cheetah | E7: cheetah_sighting_rep | F7: https://sosian.pamdas.org/static/sprite-src/cheetah_sighting_rep.svg | G7: 1 | H7: 0 | I7: Cheetah | J7: Wildlife Sighting | K7: e7860c5e-49f2-4393-b733-afba3e8b51eb | L7: TRUE | N7: cheetah
A8: crop_damage | B8: Crop Damage Report | C8: v1 | D8: https://sosian.pamdas.org/api/v1.0/activity/events/schema/eventtype/crop_damage | E8: land_clearance_rep | F8: https://sosian.pamdas.org/static/sprite-src/land_clearance_rep.svg | G8: 10 | H8: 6 | I8: Crop Damage | J8: Human Wildlife Interaction | K8: d78ae70e-0aae-425b-9ca1-5b96a663f4c8 | L8: TRUE | N8: crop_damage
A9: cropdamage_polygon_tool | B9: Crop Damage polygon Report | C9: v1 | D9: https://sosian.pamdas.org/api/v1.0/activity/events/schema/eventtype/cropdamage_polygon_tool | E9: geofence_break_rep | F9: https://sosian.pamdas.org/static/geofence_break-black.svg | G9: 10 | H9: 6 | I9: Crop Damage (Polygon Tool) | J9: Human Wildlife Interaction | K9: d78ae70e-0aae-425b-9ca1-5b96a663f4c8 | L9: TRUE | N9: cropdamage_polygon_tool
A10: dead_animal | B10: EventType Test Data | C10: v1 | D10: https://sosian.pamdas.org/api/v1.0/activity/events/schema/eventtype/dead_animal | E10: wildlife_mortality_rep | F10: https://sosian.pamdas.org/static/sprite-src/wildlife_mortality_rep.svg | G10: 25 | H10: 12 | I10: Dead Animal | J10: VETERINARY | K10: 731d3546-eaf5-46c9-bbff-df0c948d8396 | L10: TRUE | N10: dead_animal
A11: eland | B11: Eland Report | C11: v1 | D11: https://sosian.pamdas.org/api/v1.0/activity/events/schema/eventtype/eland | E11: eland_rep | F11: https://sosian.pamdas.org/static/sprite-src/eland_rep.svg | G11: 1 | H11: 0 | I11: Eland | J11: Wildlife Sighting | K11: e7860c5e-49f2-4393-b733-afba3e8b51eb | L11: TRUE | N11: eland
A12: elephant_sighting | B12: Elephant Report | C12: v1 | D12: https://sosian.pamdas.org/api/v1.0/activity/events/schema/eventtype/elephant_sighting | E12: elephant_sighting_rep | F12: https://sosian.pamdas.org/static/elephant_sighting-black.svg | G12: 1 | H12: 0 | I12: Elephant | J12: Wildlife Sighting | K12: e7860c5e-49f2-4393-b733-afba3e8b51eb | L12: TRUE | N12: elephant_sighting
A13: fence_damage | B13: Fence damage Report | C13: v1 | D13: https://sosian.pamdas.org/api/v1.0/activity/events/schema/eventtype/fence_damage | E13: fence_breakage_rep | F13: https://sosian.pamdas.org/static/fence_breakage-black.svg | G13: 8 | H13: 3 | I13: Fence Damage | J13: Human Activities | K13: 116904c3-87e9-4599-bf1f-530109c13cb7 | L13: TRUE | N13: fence_damage
... A60: wood_collecting | B60: Wood collecting Report | C60: v1 | D60: https://sosian.pamdas.org/api/v1.0/activity/events/schema/eventtype/wood_collecting | E60: timber-observation_rep | F60: https://sosian.pamdas.org/static/sprite-src/timber-observation_rep.svg | G60: 9 | H60: 5 | I60: Wood Collection | J60: Human Activities | K60: 116904c3-87e9-4599-bf1f-530109c13cb7 | L60: TRUE | N60: wood_collecting

Sheet aip_polygon
A1: event_value | B1: event_name | C1: event_category_display | D1: event_category_id | E1: path | F1: json_key | G1: ui_title | H1: type | I1: format | J1: required | K1: is_array | L1: array_item_type | M1: enum_values | N1: enum_names | O1: inactive_enum | P1: enum_images | Q1: minimum | R1: maximum | S1: pattern | T1: default | U1: examples | V1: description | W1: key_ref | X1: notes
A2: aip_polygon | B2: Alien Invasive Plants Polygon | C2: Bio And Eco Monitoring | D2: 03cc816c-724a-4365-8eb7-3a09843ff196 | E2: invasivealienplants_alienplantspecies | F2: invasivealienplants_alienplantspecies | G2: Alien Plant Species | H2: string | J2: FALSE | K2: FALSE | M2: acaciamearnsiiblackwattle acaciamelanoxylonaustralianblackwood austrocylindropuntiasubalatadevilsrope bryophyllumdelagoensemotherofmillions bryophyllumfedtschenkoistonecrop catharanthusroseusrosyperiwinkle cereusjamaceruqueenofthenight chromoleanaodoratatriffidweed cuscutareflexagoldendodder daturastramoniumcommonthornapple eucalyptussppgumtrees euryopschrysanthemoidesgoldendaisy grevilliarobustasilkyoak kalanchoebeharensisvelvetelephantear lantanacamaraverbena opuntiaficusindicafigopuntia opuntiastrictapricklypear partheniumhysterophorusfamineweed solanummauritianumbugweed tithoniadiversifoliamexicansunflower agave_sisal argemone_poppy cirsium_thistle senna_arsenicbush xanthium_cocklebur | N2: {"acaciamearnsiiblackwattle":"Acacia Mearnsii - Black Wattle","acaciamelanoxylonaustralianblackwood":"Acacia Melanoxylon - Australian Blackwood","agave_sisal":"Agave sisalana - Sisal hemp","argemone_poppy":"Argemone mexicana - Mexican poppy","austrocylindropuntiasubalatadevilsrope":"Austrocylindropuntia Subalata - Devils Rope","bryophyllumdelagoensemotherofmillions":"Bryophyllum Delagoense - Mother of Millions","bryophyllumfedtschenkoistonecrop":"Bryophyllum Fedtschenkoi - Stonecrop","catharanthusroseusrosyperiwinkle":"Catharanthus Roseus - Rosy Periwinkle","cereusjamaceruqueenofthenight":"Cereus Jamaceru - Queen of the Night","chromoleanaodoratatriffidweed":"Chromoleana Odorata - Triffid Weed","cirsium_thistle":"Cirsium vulgare - Common thistle","cuscutareflexagoldendodder":"Cuscuta Reflexa - Golden Dodder","daturastramoniumcommonthornapple":"Datura Stramonium - Common Thorn Apple","eucalyptussppgumtrees":"Eucalyptus Spp. - Gum Trees","euryopschrysanthemoidesgoldendaisy":"Euryops Chrysanthemoides - Golden Daisy","grevilliarobustasilkyoak":"Grevillia Robusta - Silky Oak","kalanchoebeharensisvelvetelephantear":"Kalanchoe Beharensis - Velvet Elephant Ear","lantanacamaraverbena":"Lantana Camara - Verbena","opuntiaficusindicafigopuntia":"Opuntia Ficus Indica - Fig Opuntia","opuntiastrictapricklypear":"Opuntia Stricta - Prickly Pear","partheniumhysterophorusfamineweed":"Parthenium Hysterophorus - Famine Weed","senna_arsenicbush":"Senna occidentalis - Arsenic bush","solanummauritianumbugweed":"Solanum Mauritianum - Bug Weed","tithoniadiversifoliamexicansunflower":"Tithonia Diversifolia - Mexican Sunflower","xanthium_cocklebur":"Xanthium strumarium - Cocklebur"} | P2: {"acaciamearnsiiblackwattle":"string","acaciamelanoxylonaustralianblackwood":"string","austrocylindropuntiasubalatadevilsrope":"string","bryophyllumdelagoensemotherofmillions":"string","bryophyllumfedtschenkoistonecrop":"string","catharanthusroseusrosyperiwinkle":"string","cereusjamaceruqueenofthenight":"string","chromoleanaodoratatriffidweed":"string","cuscutareflexagoldendodder":"string","daturastramoniumcommonthornapple":"string","eucalyptussppgumtrees":"string","euryopschrysanthemoidesgoldendaisy":"string","grevilliarobustasilkyoak":"string","kalanchoebeharensisvelvetelephantear":"string","lantanacamaraverbena":"string","opuntiaficusindicafigopuntia":"string","opuntiastrictapricklypear":"string","partheniumhysterophorusfamineweed":"string","solanummauritianumbugweed":"string","tithoniadiversifoliamexicansunflower":"string"}
A3: aip_polygon | B3: Alien Invasive Plants Polygon | C3: Bio And Eco Monitoring | D3: 03cc816c-724a-4365-8eb7-3a09843ff196 | E3: invasivealienplants_phenologicalstate | F3: invasivealienplants_phenologicalstate | J3: FALSE | K3: FALSE | W3: invasivealienplants_phenologicalstate
A4: aip_polygon | B4: Alien Invasive Plants Polygon | C4: Bio And Eco Monitoring | D4: 03cc816c-724a-4365-8eb7-3a09843ff196 | E4: invasivealienplants_iapdensity | F4: invasivealienplants_iapdensity | G4: IAP Density | H4: string | J4: FALSE | K4: FALSE | M4: 1 2 3 4 5 | N4: {"1":"1","2":"2","3":"3","4":"4","5":"5"} | P4: {"1":"string","2":"string","3":"string","4":"string","5":"string"}
A5: aip_polygon | B5: Alien Invasive Plants Polygon | C5: Bio And Eco Monitoring | D5: 03cc816c-724a-4365-8eb7-3a09843ff196 | E5: invasivealienplants_biocontroldensity | F5: invasivealienplants_biocontroldensity | G5: Bio-control Density | H5: string | J5: FALSE | K5: FALSE | M5: 0 1 2 3 | N5: {"0":"0","1":"1","2":"2","3":"3"} | P5: {"0":"string","1":"string","2":"string","3":"string"}
A6: aip_polygon | B6: Alien Invasive Plants Polygon | C6: Bio And Eco Monitoring | D6: 03cc816c-724a-4365-8eb7-3a09843ff196 | E6: invasivealienplants_controlregimedetails | F6: invasivealienplants_controlregimedetails | G6: Control Regime Details | H6: string | J6: FALSE | K6: FALSE | M6: primarytreatment firstyearfollowup secondyearfollowup thirdyearfollowup | N6: {"firstyearfollowup":"First Year Follow-up","primarytreatment":"Primary Treatment","secondyearfollowup":"Second Year Follow-up","thirdyearfollowup":"Third Year Follow-up"} | P6: {"firstyearfollowup":"string","primarytreatment":"string","secondyearfollowup":"string","thirdyearfollowup":"string"}
A7: aip_polygon | B7: Alien Invasive Plants Polygon | C7: Bio And Eco Monitoring | D7: 03cc816c-724a-4365-8eb7-3a09843ff196 | E7: invasivealienplants_controlmethod | F7: invasivealienplants_controlmethod | G7: Control Method | H7: string | J7: FALSE | K7: FALSE | M7: biological chemical mechanical burning | N7: {"biological":"Biological","burning":"Burning","chemical":"Chemical","mechanical":"Mechanical"} | P7: {"biological":"string","burning":"string","chemical":"string","mechanical":"string"}
A8: aip_polygon | B8: Alien Invasive Plants Polygon | C8: Bio And Eco Monitoring | D8: 03cc816c-724a-4365-8eb7-3a09843ff196 | E8: invasivealienplants_controlapplication | F8: invasivealienplants_controlapplication | G8: Control Application | H8: string | J8: FALSE | K8: FALSE | M8: bioagentrelease cutstumptreatment foliarspray frilling ringbarking uprooting | N8: {"bioagentrelease":"Bio-agent Release","cutstumptreatment":"Cut Stump Treatment","foliarspray":"Foliar Spray","frilling":"Frilling","ringbarking":"Ring Barking","uprooting":"Up-Rooting"} | P8: {"bioagentrelease":"string","cutstumptreatment":"string","foliarspray":"string","frilling":"string","ringbarking":"string","uprooting":"string"}
A9: aip_polygon | B9: Alien Invasive Plants Polygon | C9: Bio And Eco Monitoring | D9: 03cc816c-724a-4365-8eb7-3a09843ff196 | E9: invasivealienplants_herbicideused | F9: invasivealienplants_herbicideused | G9: Herbicide Used | H9: string | J9: FALSE | K9: FALSE
A10: aip_polygon | B10: Alien Invasive Plants Polygon | C10: Bio And Eco Monitoring | D10: 03cc816c-724a-4365-8eb7-3a09843ff196 | E10: invasivealienplants_herbicideconcentration | F10: invasivealienplants_herbicideconcentration | G10: Herbicide Concentration % | H10: number | J10: FALSE | K10: FALSE | Q10: 0
A11: aip_polygon | B11: Alien Invasive Plants Polygon | C11: Bio And Eco Monitoring | D11: 03cc816c-724a-4365-8eb7-3a09843ff196 | E11: invasivealienplants_biologicalcontrolapplied | F11: invasivealienplants_biologicalcontrolapplied | G11: Biological Control Applied | H11: string | J11: FALSE | K11: FALSE | M11: cochineal none | N11: {"cochineal":"Cochineal","none":"None"}
A12: aip_polygon | B12: Alien Invasive Plants Polygon | C12: Bio And Eco Monitoring | D12: 03cc816c-724a-4365-8eb7-3a09843ff196 | E12: invasivealienplants_distributionaream | F12: invasivealienplants_distributionaream | G12: Distribution Area (m) | H12: number | J12: FALSE | K12: FALSE | Q12: 0
A13: aip_polygon | B13: Alien Invasive Plants Polygon | C13: Bio And Eco Monitoring | D13: 03cc816c-724a-4365-8eb7-3a09843ff196 | E13: invasivealienplants_weatherconditions | F13: invasivealienplants_weatherconditions | J13: FALSE | K13: FALSE | W13: invasivealienplants_weatherconditions
A14: aip_polygon | B14: Alien Invasive Plants Polygon | C14: Bio And Eco Monitoring | D14: 03cc816c-724a-4365-8eb7-3a09843ff196 | E14: invasivealienplants_watchkeepervalidation | F14: invasivealienplants_watchkeepervalidation | G14: Watch Keeper Validation | H14: string | J14: FALSE | K14: FALSE
A15: aip_polygon | B15: Alien Invasive Plants Polygon | C15: Bio And Eco Monitoring | D15: 03cc816c-724a-4365-8eb7-3a09843ff196 | E15: invasivealienplants_actionschecklist | F15: invasivealienplants_actionschecklist | J15: FALSE | K15: FALSE | W15: invasivealienplants_actionschecklist
A16: aip_polygon | B16: Alien Invasive Plants Polygon | C16: Bio And Eco Monitoring | D16: 03cc816c-724a-4365-8eb7-3a09843ff196 | E16: invasivealienplants_commandervalidation | F16: invasivealienplants_commandervalidation | G16: Commander Validation | H16: string | J16: FALSE | K16: FALSE
A17: aip_polygon | B17: Alien Invasive Plants Polygon | C17: Bio And Eco Monitoring | D17: 03cc816c-724a-4365-8eb7-3a09843ff196 | E17: invasivealienplants_treatmentefficacyatonemonth | F17: invasivealienplants_treatmentefficacyatonemonth | G17: Treatment Efficacy at One Month (%) | H17: number | J17: FALSE | K17: FALSE | Q17: 0
A18: aip_polygon | B18: Alien Invasive Plants Polygon | C18: Bio And Eco Monitoring | D18: 03cc816c-724a-4365-8eb7-3a09843ff196 | E18: invasivealienplants_conclusion | F18: invasivealienplants_conclusion | G18: Conclusion | H18: string | J18: FALSE | K18: FALSE

Sheet aip_tourism
A1: event_value | B1: event_name | C1: event_category_display | D1: event_category_id | E1: path | F1: json_key | G1: ui_title | H1: type | I1: format | J1: required | K1: is_array | L1: array_item_type | M1: enum_values | N1: enum_names | O1: inactive_enum | P1: enum_images | Q1: minimum | R1: maximum | S1: pattern | T1: default | U1: examples | V1: description | W1: key_ref | X1: notes
A2: aip_tourism | B2: Alien Invasive Plants | C2: Tourism | D2: 234f8623-6a68-4e2f-84a0-e28526b7d0d2 | E2: invasivealienplants_alienplantspecies | F2: invasivealienplants_alienplantspecies | G2: Alien Plant Species | H2: string | J2: FALSE | K2: FALSE | M2: acaciamearnsiiblackwattle acaciamelanoxylonaustralianblackwood austrocylindropuntiasubalatadevilsrope bryophyllumdelagoensemotherofmillions bryophyllumfedtschenkoistonecrop catharanthusroseusrosyperiwinkle cereusjamaceruqueenofthenight chromoleanaodoratatriffidweed cuscutareflexagoldendodder daturastramoniumcommonthornapple eucalyptussppgumtrees euryopschrysanthemoidesgoldendaisy grevilliarobustasilkyoak kalanchoebeharensisvelvetelephantear lantanacamaraverbena opuntiaficusindicafigopuntia opuntiastrictapricklypear partheniumhysterophorusfamineweed solanummauritianumbugweed tithoniadiversifoliamexicansunflower agave_sisal argemone_poppy cirsium_thistle senna_arsenicbush xanthium_cocklebur | N2: {"acaciamearnsiiblackwattle":"Acacia Mearnsii - Black Wattle","acaciamelanoxylonaustralianblackwood":"Acacia Melanoxylon - Australian Blackwood","agave_sisal":"Agave sisalana - Sisal hemp","argemone_poppy":"Argemone mexicana - Mexican poppy","austrocylindropuntiasubalatadevilsrope":"Austrocylindropuntia Subalata - Devils Rope","bryophyllumdelagoensemotherofmillions":"Bryophyllum Delagoense - Mother of Millions","bryophyllumfedtschenkoistonecrop":"Bryophyllum Fedtschenkoi - Stonecrop","catharanthusroseusrosyperiwinkle":"Catharanthus Roseus - Rosy Periwinkle","cereusjamaceruqueenofthenight":"Cereus Jamaceru - Queen of the Night","chromoleanaodoratatriffidweed":"Chromoleana Odorata - Triffid Weed","cirsium_thistle":"Cirsium vulgare - Common thistle","cuscutareflexagoldendodder":"Cuscuta Reflexa - Golden Dodder","daturastramoniumcommonthornapple":"Datura Stramonium - Common Thorn Apple","eucalyptussppgumtrees":"Eucalyptus Spp. - Gum Trees","euryopschrysanthemoidesgoldendaisy":"Euryops Chrysanthemoides - Golden Daisy","grevilliarobustasilkyoak":"Grevillia Robusta - Silky Oak","kalanchoebeharensisvelvetelephantear":"Kalanchoe Beharensis - Velvet Elephant Ear","lantanacamaraverbena":"Lantana Camara - Verbena","opuntiaficusindicafigopuntia":"Opuntia Ficus Indica - Fig Opuntia","opuntiastrictapricklypear":"Opuntia Stricta - Prickly Pear","partheniumhysterophorusfamineweed":"Parthenium Hysterophorus - Famine Weed","senna_arsenicbush":"Senna occidentalis - Arsenic bush","solanummauritianumbugweed":"Solanum Mauritianum - Bug Weed","tithoniadiversifoliamexicansunflower":"Tithonia Diversifolia - Mexican Sunflower","xanthium_cocklebur":"Xanthium strumarium - Cocklebur"} | P2: {"acaciamearnsiiblackwattle":"string","acaciamelanoxylonaustralianblackwood":"string","austrocylindropuntiasubalatadevilsrope":"string","bryophyllumdelagoensemotherofmillions":"string","bryophyllumfedtschenkoistonecrop":"string","catharanthusroseusrosyperiwinkle":"string","cereusjamaceruqueenofthenight":"string","chromoleanaodoratatriffidweed":"string","cuscutareflexagoldendodder":"string","daturastramoniumcommonthornapple":"string","eucalyptussppgumtrees":"string","euryopschrysanthemoidesgoldendaisy":"string","grevilliarobustasilkyoak":"string","kalanchoebeharensisvelvetelephantear":"string","lantanacamaraverbena":"string","opuntiaficusindicafigopuntia":"string","opuntiastrictapricklypear":"string","partheniumhysterophorusfamineweed":"string","solanummauritianumbugweed":"string","tithoniadiversifoliamexicansunflower":"string"}
A3: aip_tourism | B3: Alien Invasive Plants | C3: Tourism | D3: 234f8623-6a68-4e2f-84a0-e28526b7d0d2 | E3: invasivealienplants_phenologicalstate | F3: invasivealienplants_phenologicalstate | J3: FALSE | K3: FALSE | W3: invasivealienplants_phenologicalstate
A4: aip_tourism | B4: Alien Invasive Plants | C4: Tourism | D4: 234f8623-6a68-4e2f-84a0-e28526b7d0d2 | E4: invasivealienplants_iapdensity | F4: invasivealienplants_iapdensity | G4: IAP Density | H4: string | J4: FALSE | K4: FALSE | M4: 1 2 3 4 5 | N4: {"1":"1","2":"2","3":"3","4":"4","5":"5"} | P4: {"1":"string","2":"string","3":"string","4":"string","5":"string"}
A5: aip_tourism | B5: Alien Invasive Plants | C5: Tourism | D5: 234f8623-6a68-4e2f-84a0-e28526b7d0d2 | E5: invasivealienplants_biocontroldensity | F5: invasivealienplants_biocontroldensity | G5: Bio-control Density | H5: string | J5: FALSE | K5: FALSE | M5: 0 1 2 3 | N5: {"0":"0","1":"1","2":"2","3":"3"} | P5: {"0":"string","1":"string","2":"string","3":"string"}
A6: aip_tourism | B6: Alien Invasive Plants | C6: Tourism | D6: 234f8623-6a68-4e2f-84a0-e28526b7d0d2 | E6: invasivealienplants_watchkeepervalidation | F6: invasivealienplants_watchkeepervalidation | G6: Watch Keeper Validation | H6: string | J6: FALSE | K6: FALSE

Sheet air_ops_boma_sighting
A1: event_value | B1: event_name | C1: event_category_display | D1: event_category_id | E1: path | F1: json_key | G1: ui_title | H1: type | I1: format | J1: required | K1: is_array | L1: array_item_type | M1: enum_values | N1: enum_names | O1: inactive_enum | P1: enum_images | Q1: minimum | R1: maximum | S1: pattern | T1: default | U1: examples | V1: description | W1: key_ref | X1: notes
A2: air_ops_boma_sighting | B2: Boma Sighting | C2: Air Ops | D2: 2d9863c1-5d10-49ce-b95b-f453a2ddf663 | E2: numberanimals | F2: numberanimals | G2: Count | H2: number | J2: FALSE | K2: FALSE | Q2: 0
A3: air_ops_boma_sighting | B3: Boma Sighting | C3: Air Ops | D3: 2d9863c1-5d10-49ce-b95b-f453a2ddf663 | E3: bomasighting_status | F3: bomasighting_status | G3: Boma Status | H3: string | J3: FALSE | K3: FALSE | M3: active inactive | N3: {"active":"Active","inactive":"Inactive"}
A4: air_ops_boma_sighting | B4: Boma Sighting | C4: Air Ops | D4: 2d9863c1-5d10-49ce-b95b-f453a2ddf663 | E4: livestock_array | F4: livestock_array | G4: Livestock | H4: array | J4: FALSE | K4: TRUE | L4: object
A5: air_ops_boma_sighting | B5: Boma Sighting | C5: Air Ops | D5: 2d9863c1-5d10-49ce-b95b-f453a2ddf663 | E5: livestock_array[]..Animal Name | F5: Animal Name | G5: Type of Livestock | H5: string | J5: FALSE | K5: FALSE | M5: camels cattle donkey goats horse pigs poultry sheep | N5: {"camels":"Camel(s)","cattle":"Cattle","donkey":"Donkey(s)","goats":"Goat(s)","horse":"Horse(s)","pigs":"Pig(s)","poultry":"Poultry","sheep":"Sheep"}
A6: air_ops_boma_sighting | B6: Boma Sighting | C6: Air Ops | D6: 2d9863c1-5d10-49ce-b95b-f453a2ddf663 | E6: livestock_array[]..Number | F6: Number | G6: No. of Animals | H6: number | J6: FALSE | K6: FALSE | Q6: 1
A7: air_ops_boma_sighting | B7: Boma Sighting | C7: Air Ops | D7: 2d9863c1-5d10-49ce-b95b-f453a2ddf663 | E7: numberherders | F7: numberherders | G7: Number of Herders | H7: number | J7: FALSE | K7: FALSE | Q7: 0
A8: air_ops_boma_sighting | B8: Boma Sighting | C8: Air Ops | D8: 2d9863c1-5d10-49ce-b95b-f453a2ddf663 | E8: boma_sighting_action | F8: boma_sighting_action | J8: FALSE | K8: FALSE | W8: deployed_assets
A9: air_ops_boma_sighting | B9: Boma Sighting | C9: Air Ops | D9: 2d9863c1-5d10-49ce-b95b-f453a2ddf663 | E9: sighting_action | F9: sighting_action | J9: FALSE | K9: FALSE | W9: sighting_action

Sheet air_ops_camel_sighting
A1: event_value | B1: event_name | C1: event_category_display | D1: event_category_id | E1: path | F1: json_key | G1: ui_title | H1: type | I1: format | J1: required | K1: is_array | L1: array_item_type | M1: enum_values | N1: enum_names | O1: inactive_enum | P1: enum_images | Q1: minimum | R1: maximum | S1: pattern | T1: default | U1: examples | V1: description | W1: key_ref | X1: notes
A2: air_ops_camel_sighting | B2: Camel Sighting | C2: Air Ops | D2: 2d9863c1-5d10-49ce-b95b-f453a2ddf663 | E2: numberanimals | F2: numberanimals | G2: Count | H2: number | J2: FALSE | K2: FALSE | Q2: 0
A3: air_ops_camel_sighting | B3: Camel Sighting | C3: Air Ops | D3: 2d9863c1-5d10-49ce-b95b-f453a2ddf663 | E3: livestock_action | F3: livestock_action | J3: FALSE | K3: FALSE | W3: deployed_assets
A4: air_ops_camel_sighting | B4: Camel Sighting | C4: Air Ops | D4: 2d9863c1-5d10-49ce-b95b-f453a2ddf663 | E4: livestock_action_outcome | F4: livestock_action_outcome | J4: FALSE | K4: FALSE | W4: sighting_action

Sheet air_ops_cattle_sighting
A1: event_value | B1: event_name | C1: event_category_display | D1: event_category_id | E1: path | F1: json_key | G1: ui_title | H1: type | I1: format | J1: required | K1: is_array | L1: array_item_type | M1: enum_values | N1: enum_names | O1: inactive_enum | P1: enum_images | Q1: minimum | R1: maximum | S1: pattern | T1: default | U1: examples | V1: description | W1: key_ref | X1: notes
A2: air_ops_cattle_sighting | B2: Cattle Sighting | C2: Air Ops | D2: 2d9863c1-5d10-49ce-b95b-f453a2ddf663 | E2: numberanimals | F2: numberanimals | G2: Count | H2: number | J2: FALSE | K2: FALSE | Q2: 0
A3: air_ops_cattle_sighting | B3: Cattle Sighting | C3: Air Ops | D3: 2d9863c1-5d10-49ce-b95b-f453a2ddf663 | E3: livestock_action | F3: livestock_action | J3: FALSE | K3: FALSE | W3: deployed_assets
A4: air_ops_cattle_sighting | B4: Cattle Sighting | C4: Air Ops | D4: 2d9863c1-5d10-49ce-b95b-f453a2ddf663 | E4: livestock_action_outcome | F4: livestock_action_outcome | J4: FALSE | K4: FALSE | W4: sighting_action

Sheet air_ops_elephant_carcass
A1: event_value | B1: event_name | C1: event_category_display | D1: event_category_id | E1: path | F1: json_key | G1: ui_title | H1: type | I1: format | J1: required | K1: is_array | L1: array_item_type | M1: enum_values | N1: enum_names | O1: inactive_enum | P1: enum_images | Q1: minimum | R1: maximum | S1: pattern | T1: default | U1: examples | V1: description | W1: key_ref | X1: notes
A2: air_ops_elephant_carcass | B2: Elephant Carcass | C2: Air Ops | D2: 2d9863c1-5d10-49ce-b95b-f453a2ddf663 | E2: carcass_age | F2: carcass_age | G2: Age of Carcass | H2: string | J2: FALSE | K2: FALSE | M2: 1 2 week_month 3 4 5 unknown | N2: {"1":"Fresh – 1 day or Less","2":"Less than 1 Week","3":"1 Month - 3 Months","4":"6 Months - 1 Year","5":"> 1 Year","unknown":"Unknown","week_month":"1 Week - 1 Month"}
A3: air_ops_elephant_carcass | B3: Elephant Carcass | C3: Air Ops | D3: 2d9863c1-5d10-49ce-b95b-f453a2ddf663 | E3: tusk_status | F3: tusk_status | G3: Tusk Status | H3: string | J3: FALSE | K3: FALSE | M3: intact naturally_absent tusks_not_yet_developed right_tusk_missing left_tusk_missing both_tusks_removed_illegally | N3: {"both_tusks_removed_illegally":"Both Tusks Removed Illegally","intact":"Intact","left_tusk_missing":"Left Tusk Missing","naturally_absent":"Naturally Absent","right_tusk_missing":"Right Tusk Missing","tusks_not_yet_developed":"Tusks Not Yet Developed"}
A4: air_ops_elephant_carcass | B4: Elephant Carcass | C4: Air Ops | D4: 2d9863c1-5d10-49ce-b95b-f453a2ddf663 | E4: elephantcarcass_action | F4: elephantcarcass_action | J4: FALSE | K4: FALSE | W4: deployed_assets
A5: air_ops_elephant_carcass | B5: Elephant Carcass | C5: Air Ops | D5: 2d9863c1-5d10-49ce-b95b-f453a2ddf663 | E5: sighting_action | F5: sighting_action | J5: FALSE | K5: FALSE | W5: sighting_action

Sheet air_ops_logging
A1: event_value | B1: event_name | C1: event_category_display | D1: event_category_id | E1: path | F1: json_key | G1: ui_title | H1: type | I1: format | J1: required | K1: is_array | L1: array_item_type | M1: enum_values | N1: enum_names | O1: inactive_enum | P1: enum_images | Q1: minimum | R1: maximum | S1: pattern | T1: default | U1: examples | V1: description | W1: key_ref | X1: notes
A2: air_ops_logging | B2: Logging | C2: Air Ops | D2: 2d9863c1-5d10-49ce-b95b-f453a2ddf663 | E2: airops_logging_scale | F2: airops_logging_scale | G2: Scale | H2: string | J2: FALSE | K2: FALSE | M2: small medium large | N2: {"large":"Large >1 acre","medium":"Medium >0.5 acre","small":"Small <0.5 acre"}
A3: air_ops_logging | B3: Logging | C3: Air Ops | D3: 2d9863c1-5d10-49ce-b95b-f453a2ddf663 | E3: airops_logging_age | F3: airops_logging_age | G3: Age | H3: string | J3: FALSE | K3: FALSE | M3: active fresh_1wk recent_2wks old | N3: {"active":"Active","fresh_1wk":"Fresh <1 week","old":"Old >2 weeks","recent_2wks":"Recent <2 Weeks"}
A4: air_ops_logging | B4: Logging | C4: Air Ops | D4: 2d9863c1-5d10-49ce-b95b-f453a2ddf663 | E4: airops_logging_species | F4: airops_logging_species | G4: Species | H4: string | J4: FALSE | K4: FALSE | M4: acacia cedar commiphora sandalwood olive | N4: {"acacia":"Acacia spp.","cedar":"Cedar","commiphora":"Commiphora spp.","olive":"Wild Olive","sandalwood":"Sandalwood"}
A5: air_ops_logging | B5: Logging | C5: Air Ops | D5: 2d9863c1-5d10-49ce-b95b-f453a2ddf663 | E5: airops_logging_type | F5: airops_logging_type | G5: Type | H5: string | J5: FALSE | K5: FALSE | N5: {}
A6: air_ops_logging | B6: Logging | C6: Air Ops | D6: 2d9863c1-5d10-49ce-b95b-f453a2ddf663 | E6: logging_sighting_action | F6: logging_sighting_action | J6: FALSE | K6: FALSE | W6: deployed_assets
A7: air_ops_logging | B7: Logging | C7: Air Ops | D7: 2d9863c1-5d10-49ce-b95b-f453a2ddf663 | E7: sighting_action | F7: sighting_action | J7: FALSE | K7: FALSE | W7: sighting_action

Sheet air_ops_people_sighting
A1: event_value | B1: event_name | C1: event_category_display | D1: event_category_id | E1: path | F1: json_key | G1: ui_title | H1: type | I1: format | J1: required | K1: is_array | L1: array_item_type | M1: enum_values | N1: enum_names | O1: inactive_enum | P1: enum_images | Q1: minimum | R1: maximum | S1: pattern | T1: default | U1: examples | V1: description | W1: key_ref | X1: notes
A2: air_ops_people_sighting | B2: People Sighting | C2: Air Ops | D2: 2d9863c1-5d10-49ce-b95b-f453a2ddf663 | E2: numberanimals | F2: numberanimals | G2: Count | H2: number | J2: FALSE | K2: FALSE | Q2: 0
A3: air_ops_people_sighting | B3: People Sighting | C3: Air Ops | D3: 2d9863c1-5d10-49ce-b95b-f453a2ddf663 | E3: peoplesighting_direction | F3: peoplesighting_direction | G3: Direction of Travel | H3: string | J3: FALSE | K3: FALSE | M3: east north ne nw south se sw west | N3: {"east":"East","ne":"North East","north":"North","nw":"North West","se":"South East","south":"South","sw":"South West","west":"West"}
A4: air_ops_people_sighting | B4: People Sighting | C4: Air Ops | D4: 2d9863c1-5d10-49ce-b95b-f453a2ddf663 | E4: assessed_activity | F4: assessed_activity | G4: Assessed Activity | H4: string | J4: FALSE | K4: FALSE | M4: illegal internal tourism unknown | N4: {"illegal":"Illegal","internal":"Internal","tourism":"Tourism","unknown":"Unknown"}
A5: air_ops_people_sighting | B5: People Sighting | C5: Air Ops | D5: 2d9863c1-5d10-49ce-b95b-f453a2ddf663 | E5: people_sighting_action | F5: people_sighting_action | J5: FALSE | K5: FALSE | W5: deployed_assets
A6: air_ops_people_sighting | B6: People Sighting | C6: Air Ops | D6: 2d9863c1-5d10-49ce-b95b-f453a2ddf663 | E6: sighting_action | F6: sighting_action | J6: FALSE | K6: FALSE | W6: sighting_action

Sheet air_ops_shoat_sighting
A1: event_value | B1: event_name | C1: event_category_display | D1: event_category_id | E1: path | F1: json_key | G1: ui_title | H1: type | I1: format | J1: required | K1: is_array | L1: array_item_type | M1: enum_values | N1: enum_names | O1: inactive_enum | P1: enum_images | Q1: minimum | R1: maximum | S1: pattern | T1: default | U1: examples | V1: description | W1: key_ref | X1: notes
A2: air_ops_shoat_sighting | B2: Shoat Sighting | C2: Air Ops | D2: 2d9863c1-5d10-49ce-b95b-f453a2ddf663 | E2: numberanimals | F2: numberanimals | G2: Count | H2: number | J2: FALSE | K2: FALSE | Q2: 0
A3: air_ops_shoat_sighting | B3: Shoat Sighting | C3: Air Ops | D3: 2d9863c1-5d10-49ce-b95b-f453a2ddf663 | E3: livestock_action | F3: livestock_action | J3: FALSE | K3: FALSE | W3: deployed_assets
A4: air_ops_shoat_sighting | B4: Shoat Sighting | C4: Air Ops | D4: 2d9863c1-5d10-49ce-b95b-f453a2ddf663 | E4: livestock_action_outcome | F4: livestock_action_outcome | J4: FALSE | K4: FALSE | W4: sighting_action

Sheet air_ops_wildlife_carcass
A1: event_value | B1: event_name | C1: event_category_display | D1: event_category_id | E1: path | F1: json_key | G1: ui_title | H1: type | I1: format | J1: required | K1: is_array | L1: array_item_type | M1: enum_values | N1: enum_names | O1: inactive_enum | P1: enum_images | Q1: minimum | R1: maximum | S1: pattern | T1: default | U1: examples | V1: description | W1: key_ref | X1: notes
A2: air_ops_wildlife_carcass | B2: Wildlife Carcass | C2: Air Ops | D2: 2d9863c1-5d10-49ce-b95b-f453a2ddf663 | E2: carcass_species | F2: carcass_species | G2: Species | H2: string | J2: FALSE | K2: FALSE | M2: cheetah elephant leopard lion wilddog zebragrevys pangolin aardvark aardwolf africanwildcat baboon batearedfox beisaoryx blackbackedjackal bohorreedbuck buffalo bushbuck bushpig caracal civet jacksonshartebeest commonwaterbuck crocodile defassawaterbuck dikdik eland gazellegrants gazellethompsons gerenuk giantforesthog greyduiker groundhornbill hippo honeybadger hyenaspotted hyenastriped impala klipspringer kudugreater kudulesser oribi ostrich porcupine python reticulatedgiraffe scrubhare serval steenbuck vervetmonkey vulturelappetfaced vultureruppels vulturewhitebacked vulturewhiteheaded warthog whitetailedmongoose wildebeest zebraburchells bird black_rhino chameleon lizard snakes tortoise white_rhino | N2: {"aardvark":"Aardvark / Mhanga","aardwolf":"Aardwolf / Fisi ya Nkole","africanwildcat":"African Wild Cat / Paka Shume","baboon":"Baboon / Nugu","batearedfox":"Bat-eared Fox / Mbweha Masikio","beisaoryx":"Beisa Oryx / Choroa","bird":"Bird / Ndege","black_rhino":"Black Rhino","blackbackedjackal":"Black-backed Jackal / Mbweha Mweusi","bohorreedbuck":"Bohor Reedbuck","buffalo":"Buffalo / Nyathi","bushbuck":"Bushbuck","bushpig":"Bushpig","caracal":"Caracal / Simbamangu","chameleon":"Chameleon","cheetah":"Cheetah / Duma","civet":"Civet","commonwaterbuck":"Common Waterbuck","crocodile":"Crocodile / Mamba","defassawaterbuck":"Defassa Waterbuck / Mende","dikdik":"Dikdik / Elimu","eland":"Eland / Nchi","elephant":"Elephant / Ndovu","gazellegrants":"Grants Gazelle / Swara Granti","gazellethompsons":"Thompsons Gazelle / Swara Tomi","gerenuk":"Gerenuk / Twiga Swara","giantforesthog":"Giant Forest Hog","greyduiker":"Grey Duiker","groundhornbill":"Ground Hornbill","hippo":"Hippo / Kiboko","honeybadger":"Honey Badger / Mbichi ya Asali","hyenaspotted":"Spotted Hyena / Fisi","hyenastriped":"Striped Hyena / Fisi Mwenye Mistari","impala":"Impala / Swara","jacksonshartebeest":"Jacksons Hartebeest","klipspringer":"Klipspringer / Mbuzi Mawe","kudugreater":"Greater Kudu / Tandala Mkubwa","kudulesser":"Lesser Kudu / Tandala Mdogo","leopard":"Leopard / Chui","lion":"Lion / Simba","lizard":"Lizard","oribi":"Oribi","ostrich":"Ostrich / Mbuni","pangolin":"Pangolin","porcupine":"Porcupine / Nungu","python":"Python / Nyoka Mkubwa","reticulatedgiraffe":"Reticulated Giraffe / Twiga","scrubhare":"Scrub Hare","serval":"Serval","snakes":"Snake","steenbuck":"Steenbuck","tortoise":"Tortoise / Mzee Kobe","vervetmonkey":"Vervet Monkey / Tumbiri","vulturelappetfaced":"Lappet Faced Vulture","vultureruppels":"Ruppels Griffon","vulturewhitebacked":"White Backed Vulture","vulturewhiteheaded":"White Headed Vulture","warthog":"Warthog / Ngiri","white_rhino":"White Rhino","whitetailedmongoose":"White-tailed Mongoose / Nguchiro Mkia Mweupe","wilddog":"Wild Dog / Mbwa Mwitu","wildebeest":"Wildebeest / Nyumbu","zebraburchells":"Burchells Zebra / Punda Milia","zebragrevys":"Grevy's Zebra / Punda Milia Mkubwa"} | P2: {"aardvark":"string","aardwolf":"string","africanwildcat":"string","baboon":"string","batearedfox":"string","beisaoryx":"string","blackbackedjackal":"string","bohorreedbuck":"string","buffalo":"string","bushbuck":"string","bushpig":"string","caracal":"string","cheetah":"string","civet":"string","commonwaterbuck":"string","crocodile":"string","defassawaterbuck":"string","dikdik":"string","eland":"string","elephant":"string","gazellegrants":"string","gazellethompsons":"string","gerenuk":"string","giantforesthog":"string","greyduiker":"string","groundhornbill":"string","hippo":"string","honeybadger":"string","hyenaspotted":"string","hyenastriped":"string","impala":"string","jacksonshartebeest":"string","klipspringer":"string","kudugreater":"string","kudulesser":"string","leopard":"string","lion":"string","oribi":"string","ostrich":"string","pangolin":"string","porcupine":"string","python":"string","reticulatedgiraffe":"string","scrubhare":"string","serval":"string","steenbuck":"string","vervetmonkey":"string","vulturelappetfaced":"string","vultureruppels":"string","vulturewhitebacked":"string","vulturewhiteheaded":"string","warthog":"string","whitetailedmongoose":"string","wilddog":"string","wildebeest":"string","zebraburchells":"string","zebragrevys":"string"}
A3: air_ops_wildlife_carcass | B3: Wildlife Carcass | C3: Air Ops | D3: 2d9863c1-5d10-49ce-b95b-f453a2ddf663 | E3: carcass_count | F3: carcass_count | G3: Count | H3: number | J3: FALSE | K3: FALSE | Q3: 0
A4: air_ops_wildlife_carcass | B4: Wildlife Carcass | C4: Air Ops | D4: 2d9863c1-5d10-49ce-b95b-f453a2ddf663 | E4: carcass_age | F4: carcass_age | G4: Age of Carcass | H4: string | J4: FALSE | K4: FALSE | M4: 1 2 week_month 3 4 5 unknown | N4: {"1":"Fresh – 1 day or Less","2":"Less than 1 Week","3":"1 Month - 3 Months","4":"6 Months - 1 Year","5":"> 1 Year","unknown":"Unknown","week_month":"1 Week - 1 Month"}
A5: air_ops_wildlife_carcass | B5: Wildlife Carcass | C5: Air Ops | D5: 2d9863c1-5d10-49ce-b95b-f453a2ddf663 | E5: wildlifecarcass_action | F5: wildlifecarcass_action | J5: FALSE | K5: FALSE | W5: deployed_assets
A6: air_ops_wildlife_carcass | B6: Wildlife Carcass | C6: Air Ops | D6: 2d9863c1-5d10-49ce-b95b-f453a2ddf663 | E6: wildlife_carcass_animal_action | F6: wildlife_carcass_animal_action | J6: FALSE | K6: FALSE | W6: wildlife_caracass_sighting_action

Sheet air_ops_wildlife_sighting
A1: event_value | B1: event_name | C1: event_category_display | D1: event_category_id | E1: path | F1: json_key | G1: ui_title | H1: type | I1: format | J1: required | K1: is_array | L1: array_item_type | M1: enum_values | N1: enum_names | O1: inactive_enum | P1: enum_images | Q1: minimum | R1: maximum | S1: pattern | T1: default | U1: examples | V1: description | W1: key_ref | X1: notes
A2: air_ops_wildlife_sighting | B2: Wildlife Sighting | C2: Air Ops | D2: 2d9863c1-5d10-49ce-b95b-f453a2ddf663 | E2: airops_other_wildlife_sighting_species | F2: airops_other_wildlife_sighting_species | G2: Species | H2: string | J2: FALSE | K2: FALSE | M2: cheetah elephant leopard lion wilddog zebragrevys pangolin aardvark aardwolf africanwildcat baboon batearedfox beisaoryx blackbackedjackal bohorreedbuck buffalo bushbuck bushpig caracal civet jacksonshartebeest commonwaterbuck crocodile defassawaterbuck dikdik eland gazellegrants gazellethompsons gerenuk giantforesthog greyduiker groundhornbill hippo honeybadger hyenaspotted hyenastriped impala klipspringer kudugreater kudulesser oribi ostrich porcupine python reticulatedgiraffe scrubhare serval steenbuck vervetmonkey vulturelappetfaced vultureruppels vulturewhitebacked vulturewhiteheaded warthog whitetailedmongoose wildebeest zebraburchells bird black_rhino chameleon lizard snakes tortoise white_rhino | N2: {"aardvark":"Aardvark / Mhanga","aardwolf":"Aardwolf / Fisi ya Nkole","africanwildcat":"African Wild Cat / Paka Shume","baboon":"Baboon / Nugu","batearedfox":"Bat-eared Fox / Mbweha Masikio","beisaoryx":"Beisa Oryx / Choroa","bird":"Bird / Ndege","black_rhino":"Black Rhino","blackbackedjackal":"Black-backed Jackal / Mbweha Mweusi","bohorreedbuck":"Bohor Reedbuck","buffalo":"Buffalo / Nyathi","bushbuck":"Bushbuck","bushpig":"Bushpig","caracal":"Caracal / Simbamangu","chameleon":"Chameleon","cheetah":"Cheetah / Duma","civet":"Civet","commonwaterbuck":"Common Waterbuck","crocodile":"Crocodile / Mamba","defassawaterbuck":"Defassa Waterbuck / Mende","dikdik":"Dikdik / Elimu","eland":"Eland / Nchi","elephant":"Elephant / Ndovu","gazellegrants":"Grants Gazelle / Swara Granti","gazellethompsons":"Thompsons Gazelle / Swara Tomi","gerenuk":"Gerenuk / Twiga Swara","giantforesthog":"Giant Forest Hog","greyduiker":"Grey Duiker","groundhornbill":"Ground Hornbill","hippo":"Hippo / Kiboko","honeybadger":"Honey Badger / Mbichi ya Asali","hyenaspotted":"Spotted Hyena / Fisi","hyenastriped":"Striped Hyena / Fisi Mwenye Mistari","impala":"Impala / Swara","jacksonshartebeest":"Jacksons Hartebeest","klipspringer":"Klipspringer / Mbuzi Mawe","kudugreater":"Greater Kudu / Tandala Mkubwa","kudulesser":"Lesser Kudu / Tandala Mdogo","leopard":"Leopard / Chui","lion":"Lion / Simba","lizard":"Lizard","oribi":"Oribi","ostrich":"Ostrich / Mbuni","pangolin":"Pangolin","porcupine":"Porcupine / Nungu","python":"Python / Nyoka Mkubwa","reticulatedgiraffe":"Reticulated Giraffe / Twiga","scrubhare":"Scrub Hare","serval":"Serval","snakes":"Snake","steenbuck":"Steenbuck","tortoise":"Tortoise / Mzee Kobe","vervetmonkey":"Vervet Monkey / Tumbiri","vulturelappetfaced":"Lappet Faced Vulture","vultureruppels":"Ruppels Griffon","vulturewhitebacked":"White Backed Vulture","vulturewhiteheaded":"White Headed Vulture","warthog":"Warthog / Ngiri","white_rhino":"White Rhino","whitetailedmongoose":"White-tailed Mongoose / Nguchiro Mkia Mweupe","wilddog":"Wild Dog / Mbwa Mwitu","wildebeest":"Wildebeest / Nyumbu","zebraburchells":"Burchells Zebra / Punda Milia","zebragrevys":"Grevy's Zebra / Punda Milia Mkubwa"} | P2: {"aardvark":"string","aardwolf":"string","africanwildcat":"string","baboon":"string","batearedfox":"string","beisaoryx":"string","blackbackedjackal":"string","bohorreedbuck":"string","buffalo":"string","bushbuck":"string","bushpig":"string","caracal":"string","cheetah":"string","civet":"string","commonwaterbuck":"string","crocodile":"string","defassawaterbuck":"string","dikdik":"string","eland":"string","elephant":"string","gazellegrants":"string","gazellethompsons":"string","gerenuk":"string","giantforesthog":"string","greyduiker":"string","groundhornbill":"string","hippo":"string","honeybadger":"string","hyenaspotted":"string","hyenastriped":"string","impala":"string","jacksonshartebeest":"string","klipspringer":"string","kudugreater":"string","kudulesser":"string","leopard":"string","lion":"string","oribi":"string","ostrich":"string","pangolin":"string","porcupine":"string","python":"string","reticulatedgiraffe":"string","scrubhare":"string","serval":"string","steenbuck":"string","vervetmonkey":"string","vulturelappetfaced":"string","vultureruppels":"string","vulturewhitebacked":"string","vulturewhiteheaded":"string","warthog":"string","whitetailedmongoose":"string","wilddog":"string","wildebeest":"string","zebraburchells":"string","zebragrevys":"string"}
A3: air_ops_wildlife_sighting | B3: Wildlife Sighting | C3: Air Ops | D3: 2d9863c1-5d10-49ce-b95b-f453a2ddf663 | E3: numberanimals | F3: numberanimals | G3: Count | H3: number | J3: FALSE | K3: FALSE | Q3: 0

Sheet aircraft_accident
A1: event_value | B1: event_name | C1: event_category_display | D1: event_category_id | E1: path | F1: json_key | G1: ui_title | H1: type | I1: format | J1: required | K1: is_array | L1: array_item_type | M1: enum_values | N1: enum_names | O1: inactive_enum | P1: enum_images | Q1: minimum | R1: maximum | S1: pattern | T1: default | U1: examples | V1: description | W1: key_ref | X1: notes
A2: aircraft_accident | B2: Aircraft Accident | C2: Accident & Emergency | D2: fb9ee509-1dac-42ca-b0ec-7428d6a83214 | E2: event_time | F2: event_time | G2: Event Time | J2: FALSE | K2: FALSE | W2: Event Time
A3: aircraft_accident | B3: Aircraft Accident | C3: Accident & Emergency | D3: fb9ee509-1dac-42ca-b0ec-7428d6a83214 | E3: reportreportername | F3: reportreportername | G3: Reporter Name | H3: string | J3: FALSE | K3: FALSE
A4: aircraft_accident | B4: Aircraft Accident | C4: Accident & Emergency | D4: fb9ee509-1dac-42ca-b0ec-7428d6a83214 | E4: reportphonenumber | F4: reportphonenumber | G4: Telephone Number | H4: string | J4: FALSE | K4: FALSE
A5: aircraft_accident | B5: Aircraft Accident | C5: Accident & Emergency | D5: fb9ee509-1dac-42ca-b0ec-7428d6a83214 | E5: no_injured | F5: no_injured | G5: Number of Casualties | H5: number | J5: FALSE | K5: FALSE | Q5: 0
A6: aircraft_accident | B6: Aircraft Accident | C6: Accident & Emergency | D6: fb9ee509-1dac-42ca-b0ec-7428d6a83214 | E6: no_killed | F6: no_killed | G6: Number of Fatalities | H6: number | J6: FALSE | K6: FALSE | Q6: 0
A7: aircraft_accident | B7: Aircraft Accident | C7: Accident & Emergency | D7: fb9ee509-1dac-42ca-b0ec-7428d6a83214 | E7: pilots_details | F7: pilots_details | G7: Pilot's Details | H7: array | J7: FALSE | K7: TRUE | L7: object
A8: aircraft_accident | B8: Aircraft Accident | C8: Accident & Emergency | D8: fb9ee509-1dac-42ca-b0ec-7428d6a83214 | E8: pilots_details[]..pilots_name | F8: pilots_name | G8: Pilot's Name | H8: string | J8: FALSE | K8: FALSE
A9: aircraft_accident | B9: Aircraft Accident | C9: Accident & Emergency | D9: fb9ee509-1dac-42ca-b0ec-7428d6a83214 | E9: pilots_details[]..pilots_lic | F9: pilots_lic | G9: Pilot's Licence Number | H9: string | J9: FALSE | K9: FALSE
A10: aircraft_accident | B10: Aircraft Accident | C10: Accident & Emergency | D10: fb9ee509-1dac-42ca-b0ec-7428d6a83214 | E10: aircraft_details | F10: aircraft_details | G10: Aircraft Details | H10: array | J10: FALSE | K10: TRUE | L10: object
A11: aircraft_accident | B11: Aircraft Accident | C11: Accident & Emergency | D11: fb9ee509-1dac-42ca-b0ec-7428d6a83214 | E11: aircraft_details[]..aircraft_type | F11: aircraft_type | G11: Aircraft Type | H11: string | J11: FALSE | K11: FALSE | M11: fixed_wing helicopter | N11: {"fixed_wing":"Fixed Wing","helicopter":"Helicopter"}
A12: aircraft_accident | B12: Aircraft Accident | C12: Accident & Emergency | D12: fb9ee509-1dac-42ca-b0ec-7428d6a83214 | E12: aircraft_details[]..aircarft_capacity | F12: aircarft_capacity | G12: Aircraft Capacity | H12: string | J12: FALSE | K12: FALSE | M12: twelve_twentyfour one_two two_four four_six six_twelve | N12: {"four_six":"4-6 Pax","one_two":"1-2 Pax","six_twelve":"6-12 Pax","twelve_twentyfour":"12-24 Pax","two_four":"2-4 Pax"}
A13: aircraft_accident | B13: Aircraft Accident | C13: Accident & Emergency | D13: fb9ee509-1dac-42ca-b0ec-7428d6a83214 | E13: aircraft_details[]..aircraft_registration | F13: aircraft_registration | G13: Aircraft Registration | H13: string | J13: FALSE | K13: FALSE
A14: aircraft_accident | B14: Aircraft Accident | C14: Accident & Emergency | D14: fb9ee509-1dac-42ca-b0ec-7428d6a83214 | E14: aircraft_details[]..aircraft_operator | F14: aircraft_operator | G14: Operator | H14: string | J14: FALSE | K14: FALSE | M14: afrinav air_kenya boskys_aviation eaac governers_aviation rift_valley_aviation safarilink scenic sirai_aviation tropic_air wilderness_air yellow_wings zbac borana private lewa nrt kws nps military | N14: {"afrinav":"Afrinav","air_kenya":"Air Kenya","borana":"Borana","boskys_aviation":"Bosky's Aviation","eaac":"EAAC","governers_aviation":"Governers Aviation","kws":"KWS","lewa":"Lewa","military":"Military","nps":"National Police Service","nrt":"NRT","private":"Private","rift_valley_aviation":"Rift Valley Aviation","safarilink":"Safarilink","scenic":"Scenic Air","sirai_aviation":"Sirai Aviation","tropic_air":"Tropic Air","wilderness_air":"Wilderness Air","yellow_wings":"Yellow Wings","zbac":"ZBAC"} | O14: borana
A15: aircraft_accident | B15: Aircraft Accident | C15: Accident & Emergency | D15: fb9ee509-1dac-42ca-b0ec-7428d6a83214 | E15: witness_details | F15: witness_details | G15: Witness Details | H15: array | J15: FALSE | K15: TRUE | L15: object
A16: aircraft_accident | B16: Aircraft Accident | C16: Accident & Emergency | D16: fb9ee509-1dac-42ca-b0ec-7428d6a83214 | E16: witness_details[]..witness_name | F16: witness_name | G16: Witness Name | H16: string | J16: FALSE | K16: FALSE
A17: aircraft_accident | B17: Aircraft Accident | C17: Accident & Emergency | D17: fb9ee509-1dac-42ca-b0ec-7428d6a83214 | E17: witness_details[]..phone_no | F17: phone_no | G17: Phone Number | H17: number | J17: FALSE | K17: FALSE
A18: aircraft_accident | B18: Aircraft Accident | C18: Accident & Emergency | D18: fb9ee509-1dac-42ca-b0ec-7428d6a83214 | E18: weather_condition | F18: weather_condition | J18: FALSE | K18: FALSE | W18: Weather
A19: aircraft_accident | B19: Aircraft Accident | C19: Accident & Emergency | D19: fb9ee509-1dac-42ca-b0ec-7428d6a83214 | E19: watch_keeper_validation | F19: watch_keeper_validation | G19: Watch Keeper Validation | H19: string | J19: FALSE | K19: FALSE
A20: aircraft_accident | B20: Aircraft Accident | C20: Accident & Emergency | D20: fb9ee509-1dac-42ca-b0ec-7428d6a83214 | E20: watch_keeper_action | F20: watch_keeper_action | J20: FALSE | K20: FALSE | W20: Watch Keeper Action
A21: aircraft_accident | B21: Aircraft Accident | C21: Accident & Emergency | D21: fb9ee509-1dac-42ca-b0ec-7428d6a83214 | E21: commander_validation | F21: commander_validation | G21: Commander Validation | H21: string | J21: FALSE | K21: FALSE
A22: aircraft_accident | B22: Aircraft Accident | C22: Accident & Emergency | D22: fb9ee509-1dac-42ca-b0ec-7428d6a83214 | E22: comments | F22: comments | G22: Comments | H22: string | J22: FALSE | K22: FALSE

Sheet airstrip_arrivals
A1: event_value | B1: event_name | C1: event_category_display | D1: event_category_id | E1: path | F1: json_key | G1: ui_title | H1: type | I1: format | J1: required | K1: is_array | L1: array_item_type | M1: enum_values | N1: enum_names | O1: inactive_enum | P1: enum_images | Q1: minimum | R1: maximum | S1: pattern | T1: default | U1: examples | V1: description | W1: key_ref | X1: notes
A2: airstrip_arrivals | B2: Airstrip Arrivals | C2: Tourism | D2: 234f8623-6a68-4e2f-84a0-e28526b7d0d2 | E2: number_pass | F2: number_pass | G2: Number of Passengers | H2: number | J2: FALSE | K2: FALSE
A3: airstrip_arrivals | B3: Airstrip Arrivals | C3: Tourism | D3: 234f8623-6a68-4e2f-84a0-e28526b7d0d2 | E3: dest_from | F3: dest_from | G3: From | H3: string | J3: FALSE | K3: FALSE | M3: diani elk enasoit gilgil hkjw jkia kalama kilifi kokop lamu lewa loisaba loldaiga mara mpala mugie namunyak nanyuki olenaishu olj olmalo sasaab segera solio sosian soysambu tasvo watamu wilson other | N3: {"diani":"Diani","elk":"El Karama","enasoit":"Enasoit","gilgil":"Gilgil","hkjw":"HKJW","jkia":"JKIA","kalama":"Kalama","kilifi":"Kilifi","kokop":"Kokop","lamu":"Lamu","lewa":"Lewa","loisaba":"Loisaba","loldaiga":"Loldaiga","mara":"Mara","mpala":"Mpala","mugie":"Mugie","namunyak":"Namunyak / Reteti","nanyuki":"Nanyuki","olenaishu":"Ole Naishu","olj":"Ol Jogi","olmalo":"Ol Malo","other":"Other (specify in comments)","sasaab":"Sasaab","segera":"Segera","solio":"Solio","sosian":"Sosian","soysambu":"Soysambu","tasvo":"Tsavo","watamu":"Watamu","wilson":"Wilson"}
A4: airstrip_arrivals | B4: Airstrip Arrivals | C4: Tourism | D4: 234f8623-6a68-4e2f-84a0-e28526b7d0d2 | E4: aircraft | F4: aircraft | G4: Type of Aircraft | H4: string | J4: FALSE | K4: FALSE | M4: c180 c182 c206 c208 pc12 supercub helicopter | N4: {"c180":"C-180","c182":"C-182","c206":"C-206","c208":"C-208","helicopter":"Helicopter","pc12":"PC-12","supercub":"SuperCub"}
A5: airstrip_arrivals | B5: Airstrip Arrivals | C5: Tourism | D5: 234f8623-6a68-4e2f-84a0-e28526b7d0d2 | E5: reg | F5: reg | G5: Reg (capitals, no spaces) | H5: string | J5: FALSE | K5: FALSE
A6: airstrip_arrivals | B6: Airstrip Arrivals | C6: Tourism | D6: 234f8623-6a68-4e2f-84a0-e28526b7d0d2 | E6: purpose | F6: purpose | G6: Purpose | H6: string | J6: FALSE | K6: FALSE | M6: guest tourism luggage other | N6: {"guest":"Guest","luggage":"Luggage / Cargo","other":"Other (specify in comments)","tourism":"Tourism"}
A7: airstrip_arrivals | B7: Airstrip Arrivals | C7: Tourism | D7: 234f8623-6a68-4e2f-84a0-e28526b7d0d2 | E7: operator | F7: operator | G7: Operator Name | H7: string | J7: FALSE | K7: FALSE
A8: airstrip_arrivals | B8: Airstrip Arrivals | C8: Tourism | D8: 234f8623-6a68-4e2f-84a0-e28526b7d0d2 | E8: crew | F8: crew | G8: Crew Name | H8: string | J8: FALSE | K8: FALSE
A9: airstrip_arrivals | B9: Airstrip Arrivals | C9: Tourism | D9: 234f8623-6a68-4e2f-84a0-e28526b7d0d2 | E9: pax | F9: pax | G9: Number of Passengers | H9: number | J9: FALSE | K9: FALSE | Q9: 0
A10: airstrip_arrivals | B10: Airstrip Arrivals | C10: Tourism | D10: 234f8623-6a68-4e2f-84a0-e28526b7d0d2 | E10: cargo | F10: cargo | G10: Type of Cargo | H10: string | J10: FALSE | K10: FALSE | M10: personal other | N10: {"other":"Other Cargo (Specify in Comments)","personal":"Personal Luggage"}
A11: airstrip_arrivals | B11: Airstrip Arrivals | C11: Tourism | D11: 234f8623-6a68-4e2f-84a0-e28526b7d0d2 | E11: watch_validation | F11: watch_validation | G11: Ops Room Validation | H11: string | J11: FALSE | K11: FALSE
A12: airstrip_arrivals | B12: Airstrip Arrivals | C12: Tourism | D12: 234f8623-6a68-4e2f-84a0-e28526b7d0d2 | E12: comments | F12: comments | G12: Comments | H12: string | J12: FALSE | K12: FALSE

Sheet airstrip_dep
A1: event_value | B1: event_name | C1: event_category_display | D1: event_category_id | E1: path | F1: json_key | G1: ui_title | H1: type | I1: format | J1: required | K1: is_array | L1: array_item_type | M1: enum_values | N1: enum_names | O1: inactive_enum | P1: enum_images | Q1: minimum | R1: maximum | S1: pattern | T1: default | U1: examples | V1: description | W1: key_ref | X1: notes
A2: airstrip_dep | B2: Airstrip Departures | C2: Tourism | D2: 234f8623-6a68-4e2f-84a0-e28526b7d0d2 | E2: number_pass | F2: number_pass | G2: Number of Passengers | H2: number | J2: FALSE | K2: FALSE
A3: airstrip_dep | B3: Airstrip Departures | C3: Tourism | D3: 234f8623-6a68-4e2f-84a0-e28526b7d0d2 | E3: dest_from | F3: dest_from | G3: To | H3: string | J3: FALSE | K3: FALSE | M3: diani elk enasoit gilgil hkjw jkia kalama kilifi kokop lamu lewa loisaba loldaiga mara mpala mugie namunyak nanyuki olenaishu olj olmalo sasaab segera solio sosian soysambu tasvo watamu wilson other | N3: {"diani":"Diani","elk":"El Karama","enasoit":"Enasoit","gilgil":"Gilgil","hkjw":"HKJW","jkia":"JKIA","kalama":"Kalama","kilifi":"Kilifi","kokop":"Kokop","lamu":"Lamu","lewa":"Lewa","loisaba":"Loisaba","loldaiga":"Loldaiga","mara":"Mara","mpala":"Mpala","mugie":"Mugie","namunyak":"Namunyak / Reteti","nanyuki":"Nanyuki","olenaishu":"Ole Naishu","olj":"Ol Jogi","olmalo":"Ol Malo","other":"Other (specify in comments)","sasaab":"Sasaab","segera":"Segera","solio":"Solio","sosian":"Sosian","soysambu":"Soysambu","tasvo":"Tsavo","watamu":"Watamu","wilson":"Wilson"}
A4: airstrip_dep | B4: Airstrip Departures | C4: Tourism | D4: 234f8623-6a68-4e2f-84a0-e28526b7d0d2 | E4: aircraft | F4: aircraft | G4: Type of Aircraft | H4: string | J4: FALSE | K4: FALSE | M4: c180 c182 c206 c208 pc12 supercub helicopter | N4: {"c180":"C-180","c182":"C-182","c206":"C-206","c208":"C-208","helicopter":"Helicopter","pc12":"PC-12","supercub":"SuperCub"}
A5: airstrip_dep | B5: Airstrip Departures | C5: Tourism | D5: 234f8623-6a68-4e2f-84a0-e28526b7d0d2 | E5: reg | F5: reg | G5: Reg (capitals, no spaces) | H5: string | J5: FALSE | K5: FALSE
A6: airstrip_dep | B6: Airstrip Departures | C6: Tourism | D6: 234f8623-6a68-4e2f-84a0-e28526b7d0d2 | E6: purpose | F6: purpose | G6: Purpose | H6: string | J6: FALSE | K6: FALSE | M6: guest tourism luggage other | N6: {"guest":"Guest","luggage":"Luggage / Cargo","other":"Other (specify in comments)","tourism":"Tourism"}
A7: airstrip_dep | B7: Airstrip Departures | C7: Tourism | D7: 234f8623-6a68-4e2f-84a0-e28526b7d0d2 | E7: operator | F7: operator | G7: Operator Name | H7: string | J7: FALSE | K7: FALSE | M7: afrinav air_kenya boskys_aviation eaac governers_aviation rift_valley_aviation safarilink scenic sirai_aviation tropic_air wilderness_air yellow_wings zbac borana private lewa nrt kws nps military | N7: {"afrinav":"Afrinav","air_kenya":"Air Kenya","borana":"Borana","boskys_aviation":"Bosky's Aviation","eaac":"EAAC","governers_aviation":"Governers Aviation","kws":"KWS","lewa":"Lewa","military":"Military","nps":"National Police Service","nrt":"NRT","private":"Private","rift_valley_aviation":"Rift Valley Aviation","safarilink":"Safarilink","scenic":"Scenic Air","sirai_aviation":"Sirai Aviation","tropic_air":"Tropic Air","wilderness_air":"Wilderness Air","yellow_wings":"Yellow Wings","zbac":"ZBAC"} | O7: borana
A8: airstrip_dep | B8: Airstrip Departures | C8: Tourism | D8: 234f8623-6a68-4e2f-84a0-e28526b7d0d2 | E8: crew | F8: crew | G8: Crew Name | H8: string | J8: FALSE | K8: FALSE
A9: airstrip_dep | B9: Airstrip Departures | C9: Tourism | D9: 234f8623-6a68-4e2f-84a0-e28526b7d0d2 | E9: pax | F9: pax | G9: Number of Passengers | H9: number | J9: FALSE | K9: FALSE | Q9: 0
A10: airstrip_dep | B10: Airstrip Departures | C10: Tourism | D10: 234f8623-6a68-4e2f-84a0-e28526b7d0d2 | E10: cargo | F10: cargo | G10: Type of Cargo | H10: string | J10: FALSE | K10: FALSE | M10: personal other | N10: {"other":"Other Cargo (Specify in Comments)","personal":"Personal Luggage"}
A11: airstrip_dep | B11: Airstrip Departures | C11: Tourism | D11: 234f8623-6a68-4e2f-84a0-e28526b7d0d2 | E11: watch_validation | F11: watch_validation | G11: Ops Room Validation | H11: string | J11: FALSE | K11: FALSE
A12: airstrip_dep | B12: Airstrip Departures | C12: Tourism | D12: 234f8623-6a68-4e2f-84a0-e28526b7d0d2 | E12: comments | F12: comments | G12: Comments | H12: string | J12: FALSE | K12: FALSE

Sheet arrest_report
A1: event_value | B1: event_name | C1: event_category_display | D1: event_category_id | E1: path | F1: json_key | G1: ui_title | H1: type | I1: format | J1: required | K1: is_array | L1: array_item_type | M1: enum_values | N1: enum_names | O1: inactive_enum | P1: enum_images | Q1: minimum | R1: maximum | S1: pattern | T1: default | U1: examples | V1: description | W1: key_ref | X1: notes
A2: arrest_report | B2: Arrest | C2: Law Enforcement | D2: 5ae25fb3-33b0-4dca-a3f7-47d42e4f876b | E2: reportreportername | F2: reportreportername | G2: Reporter's Name | H2: string | J2: FALSE | K2: FALSE
A3: arrest_report | B3: Arrest | C3: Law Enforcement | D3: 5ae25fb3-33b0-4dca-a3f7-47d42e4f876b | E3: reportphonenumber | F3: reportphonenumber | G3: Telephone Number | H3: number | J3: FALSE | K3: FALSE
A4: arrest_report | B4: Arrest | C4: Law Enforcement | D4: 5ae25fb3-33b0-4dca-a3f7-47d42e4f876b | E4: deployed_assets | F4: deployed_assets | J4: FALSE | K4: FALSE | W4: Deployed Assets
A5: arrest_report | B5: Arrest | C5: Law Enforcement | D5: 5ae25fb3-33b0-4dca-a3f7-47d42e4f876b | E5: watch_keeper_checklist | F5: watch_keeper_checklist | J5: FALSE | K5: FALSE | W5: Watch Keeper Checklist
A6: arrest_report | B6: Arrest | C6: Law Enforcement | D6: 5ae25fb3-33b0-4dca-a3f7-47d42e4f876b | E6: event_time | F6: event_time | G6: Event Time | J6: FALSE | K6: FALSE | W6: Event Time
A7: arrest_report | B7: Arrest | C7: Law Enforcement | D7: 5ae25fb3-33b0-4dca-a3f7-47d42e4f876b | E7: suspect_details | F7: suspect_details | G7: Suspect(s) Details | H7: array | J7: FALSE | K7: TRUE | L7: object
A8: arrest_report | B8: Arrest | C8: Law Enforcement | D8: 5ae25fb3-33b0-4dca-a3f7-47d42e4f876b | E8: suspect_details[]..suspect_id | F8: suspect_id | G8: Suspect ID Code | H8: string | J8: FALSE | K8: FALSE
A9: arrest_report | B9: Arrest | C9: Law Enforcement | D9: 5ae25fb3-33b0-4dca-a3f7-47d42e4f876b | E9: suspect_details[]..suspect_name | F9: suspect_name | G9: Full Name(s) of Suspect | H9: string | J9: FALSE | K9: FALSE
A10: arrest_report | B10: Arrest | C10: Law Enforcement | D10: 5ae25fb3-33b0-4dca-a3f7-47d42e4f876b | E10: suspect_details[]..id_passport_no | F10: id_passport_no | G10: ID or Passport Number | H10: string | J10: FALSE | K10: FALSE
A11: arrest_report | B11: Arrest | C11: Law Enforcement | D11: 5ae25fb3-33b0-4dca-a3f7-47d42e4f876b | E11: suspect_details[]..dob | F11: dob | G11: Date of Birth | H11: string | J11: FALSE | K11: FALSE
A12: arrest_report | B12: Arrest | C12: Law Enforcement | D12: 5ae25fb3-33b0-4dca-a3f7-47d42e4f876b | E12: suspect_details[]..sex | F12: sex | G12: Sex | H12: string | J12: FALSE | K12: FALSE | M12: 2 1 | N12: {"1":"Male","2":"Female"}
A13: arrest_report | B13: Arrest | C13: Law Enforcement | D13: 5ae25fb3-33b0-4dca-a3f7-47d42e4f876b | E13: suspect_details[]..contact_no | F13: contact_no | G13: Telephone Number | H13: string | J13: FALSE | K13: FALSE
A14: arrest_report | B14: Arrest | C14: Law Enforcement | D14: 5ae25fb3-33b0-4dca-a3f7-47d42e4f876b | E14: suspect_details[]..address | F14: address | G14: Address | H14: string | J14: FALSE | K14: FALSE
A15: arrest_report | B15: Arrest | C15: Law Enforcement | D15: 5ae25fb3-33b0-4dca-a3f7-47d42e4f876b | E15: reason_for_arrest | F15: reason_for_arrest | J15: FALSE | K15: FALSE | W15: reason_for_arrest(s)
A16: arrest_report | B16: Arrest | C16: Law Enforcement | D16: 5ae25fb3-33b0-4dca-a3f7-47d42e4f876b | E16: arresting_ranger | F16: arresting_ranger | G16: Arresting Scout's Force Number | H16: string | J16: FALSE | K16: FALSE | M16: ndirangu_kiyaa manase_morijo John_pameri edward_nderitu silea_legei samson_moturi joseph_piroris meya_katoyie david_piroris andero_ngila nahashon_kayimba lokimathi_lochut lonyamal_leyiaso halkano_duba jacob_meriti kalaile_kaparo george_kamasia jailo_ngatia solomon_ngila ashian_ngila meka_kiperus franklin_kinyaga simon_kuyes maxwel_gikundi ephraim_mwanyumba joseph_katiori joseph_kisio david_mwongera nilan_kinyaga lokibet_mariko sentu_kisio silas_nkonge wilfred_legei | N16: {"John_pameri":"0.8549R","andero_ngila":"0.8557R","ashian_ngila":"0.8574R","david_mwongera":"1.2889","david_piroris":"0.8556R","edward_nderitu":"0.8550R","ephraim_mwanyumba":"1.2887","franklin_kinyaga":"1.2883","george_kamasia":"0.8570R","halkano_duba":"0.8564R","jacob_meriti":"0.8565R","jailo_ngatia":"0.8572R","joseph_katiori":"1.2888","joseph_kisio":"1.2888","joseph_piroris":"0.8554R","kalaile_kaparo":"0.8567R","lokibet_mariko":"Lokibet Mariko","lokimathi_lochut":"0.8560R","lonyamal_leyiaso":"0.8563R","manase_morijo":"0.8548R","maxwel_gikundi":"1.2886","meka_kiperus":"1.2882","meya_katoyie":"0.8555R","nahashon_kayimba":"0.8559R","ndirangu_kiyaa":"0.8546R","nilan_kinyaga":"1.289","samson_moturi":"0.8553R","sentu_kisio":"Sent Kisio","silas_nkonge":"Silas Nkonge","silea_legei":"0.8552R","simon_kuyes":"1.2885","solomon_ngila":"0.8573R","wilfred_legei":"Wilfred Legei"} | O16: lokibet_mariko silas_nkonge wilfred_legei
A17: arrest_report | B17: Arrest | C17: Law Enforcement | D17: 5ae25fb3-33b0-4dca-a3f7-47d42e4f876b | E17: arresting_officer | F17: arresting_officer | G17: NPS Arresting Officer's Force Number | H17: string | J17: FALSE | K17: FALSE
A18: arrest_report | B18: Arrest | C18: Law Enforcement | D18: 5ae25fb3-33b0-4dca-a3f7-47d42e4f876b | E18: occurrence_book_no | F18: occurrence_book_no | G18: Occurrence Book Number | H18: string | J18: FALSE | K18: FALSE
A19: arrest_report | B19: Arrest | C19: Law Enforcement | D19: 5ae25fb3-33b0-4dca-a3f7-47d42e4f876b | E19: Details | F19: Details | H19: string | J19: FALSE | K19: FALSE | W19: Details
A20: arrest_report | B20: Arrest | C20: Law Enforcement | D20: 5ae25fb3-33b0-4dca-a3f7-47d42e4f876b | E20: receiving_station | F20: receiving_station | G20: Receiving Police Station | H20: string | J20: FALSE | K20: FALSE | M20: doldol_station isiolo_central_station subuiga_station timau_station | N20: {"doldol_station":"Doldol","isiolo_central_station":"Isiolo Central","subuiga_station":"Subuiga","timau_station":"Timau"}
A21: arrest_report | B21: Arrest | C21: Law Enforcement | D21: 5ae25fb3-33b0-4dca-a3f7-47d42e4f876b | E21: handover_time | F21: handover_time | G21: Time of Handover | H21: string | J21: FALSE | K21: FALSE
A22: arrest_report | B22: Arrest | C22: Law Enforcement | D22: 5ae25fb3-33b0-4dca-a3f7-47d42e4f876b | E22: watch_keeper_validation | F22: watch_keeper_validation | G22: Watch Keeper Validation | H22: string | J22: FALSE | K22: FALSE
A23: arrest_report | B23: Arrest | C23: Law Enforcement | D23: 5ae25fb3-33b0-4dca-a3f7-47d42e4f876b | E23: comm_validation | F23: comm_validation | J23: FALSE | K23: FALSE | W23: Commander Validation
A24: arrest_report | B24: Arrest | C24: Law Enforcement | D24: 5ae25fb3-33b0-4dca-a3f7-47d42e4f876b | E24: comms | F24: comms | J24: FALSE | K24: FALSE | W24: Communication Via
A25: arrest_report | B25: Arrest | C25: Law Enforcement | D25: 5ae25fb3-33b0-4dca-a3f7-47d42e4f876b | E25: suspect_condition | F25: suspect_condition | J25: FALSE | K25: FALSE | W25: condition of suspect
A26: arrest_report | B26: Arrest | C26: Law Enforcement | D26: 5ae25fb3-33b0-4dca-a3f7-47d42e4f876b | E26: comments | F26: comments | G26: Comments | H26: string | J26: FALSE | K26: FALSE

Sheet authority_to_deploy
A1: event_value | B1: event_name | C1: event_category_display | D1: event_category_id | E1: path | F1: json_key | G1: ui_title | H1: type | I1: format | J1: required | K1: is_array | L1: array_item_type | M1: enum_values | N1: enum_names | O1: inactive_enum | P1: enum_images | Q1: minimum | R1: maximum | S1: pattern | T1: default | U1: examples | V1: description | W1: key_ref | X1: notes
A2: authority_to_deploy | B2: Authority to Deploy | C2: Legal | D2: 36879dad-1388-4627-8a00-b6765fafa413 | E2: authorizing_officer | F2: authorizing_officer | G2: Authorizing Officer | H2: string | J2: FALSE | K2: FALSE | M2: county_commander_isiolo_county county_commander_laikipia_county county_commander_meru_county buri_east ocpd_isiolo_central ocpd_laikipia_east ocs_buri_east ocs_buri_west ocs_isiolo_central ocs_laikipia_east s1_borana s1_lewa s2_borana s2_lewa s3_borana s3_lewa | N2: {"buri_east":"OCPD Buri East","county_commander_isiolo_county":"County Commander Isiolo County","county_commander_laikipia_county":"County Commander Laikipia County","county_commander_meru_county":"County Commander Meru County","ocpd_isiolo_central":"OCPD Isiolo Central","ocpd_laikipia_east":"OCPD Laikipia East","ocs_buri_east":"OCS Buri East","ocs_buri_west":"OCS Buri West","ocs_isiolo_central":"OCS Isiolo Central","ocs_laikipia_east":"OCS Laikipia East","s1_borana":"S1 Borana","s1_lewa":"S1 Lewa","s2_borana":"S2 Borana","s2_lewa":"S2 Lewa","s3_borana":"S3 Borana","s3_lewa":"S3 Lewa"}
A3: authority_to_deploy | B3: Authority to Deploy | C3: Legal | D3: 36879dad-1388-4627-8a00-b6765fafa413 | E3: date/time | F3: date/time | G3: Time Authority Given | H3: string | J3: FALSE | K3: FALSE
A4: authority_to_deploy | B4: Authority to Deploy | C4: Legal | D4: 36879dad-1388-4627-8a00-b6765fafa413 | E4: communication_method | F4: communication_method | G4: Method of Communication | H4: string | J4: FALSE | K4: FALSE | M4: garmin_inreach mobile_phone radio sat_phone | N4: {"garmin_inreach":"Garmin InReach","mobile_phone":"Mobile Phone","radio":"Radio","sat_phone":"Sat Phone"}
A5: authority_to_deploy | B5: Authority to Deploy | C5: Legal | D5: 36879dad-1388-4627-8a00-b6765fafa413 | E5: deployed_assets | F5: deployed_assets | J5: FALSE | K5: FALSE | W5: deployed_assets
A6: authority_to_deploy | B6: Authority to Deploy | C6: Legal | D6: 36879dad-1388-4627-8a00-b6765fafa413 | E6: commander_validation | F6: commander_validation | G6: Commander Validation | H6: string | J6: FALSE | K6: FALSE
A7: authority_to_deploy | B7: Authority to Deploy | C7: Legal | D7: 36879dad-1388-4627-8a00-b6765fafa413 | E7: comments | F7: comments | G7: Comments | H7: string | J7: FALSE | K7: FALSE

Sheet baton_rep
A1: event_value | B1: event_name | C1: event_category_display | D1: event_category_id | E1: path | F1: json_key | G1: ui_title | H1: type | I1: format | J1: required | K1: is_array | L1: array_item_type | M1: enum_values | N1: enum_names | O1: inactive_enum | P1: enum_images | Q1: minimum | R1: maximum | S1: pattern | T1: default | U1: examples | V1: description | W1: key_ref | X1: notes
A2: baton_rep | B2: Baton Report | C2: HWC | D2: 97172f47-979e-40ff-ad0a-8e4103b3ea7c | E2: baton_rep | F2: baton_rep | H2: array | J2: FALSE | K2: TRUE | L2: object
A3: baton_rep | B3: Baton Report | C3: HWC | D3: 97172f47-979e-40ff-ad0a-8e4103b3ea7c | E3: baton_rep[]..name | F3: name | G3: Scout | H3: string | J3: FALSE | K3: FALSE
A4: baton_rep | B4: Baton Report | C4: HWC | D4: 97172f47-979e-40ff-ad0a-8e4103b3ea7c | E4: baton_rep[]..type_of_firearm | F4: type_of_firearm | G4: Type of Firearm Used | H4: string | J4: FALSE | K4: FALSE | M4: ak_47 hk_g3 rifle_375 rifle_458 shotgun | N4: {"ak_47":"AK-47","hk_g3":"HK-G3","rifle_375":"Rifle .375","rifle_458":"Rifle .458","shotgun":"Shotgun"}
A5: baton_rep | B5: Baton Report | C5: HWC | D5: 97172f47-979e-40ff-ad0a-8e4103b3ea7c | E5: baton_rep[]..nature_ammo | F5: nature_ammo | G5: Nature of Ammunition Expended | H5: string | J5: FALSE | K5: FALSE | M5: ball ball_ammo blanks shot slug | N5: {"ball":"Ball","ball_ammo":"Ball","blanks":"Blank","shot":"Shot","slug":"Slug"} | O5: ball
A6: baton_rep | B6: Baton Report | C6: HWC | D6: 97172f47-979e-40ff-ad0a-8e4103b3ea7c | E6: baton_rep[]..number_rounds | F6: number_rounds | G6: Number of Rounds Expended | H6: number | J6: FALSE | K6: FALSE | Q6: 0
A7: baton_rep | B7: Baton Report | C7: HWC | D7: 97172f47-979e-40ff-ad0a-8e4103b3ea7c | E7: baton_rep[]..species | F7: species | G7: Wildlife Species | H7: string | J7: FALSE | K7: FALSE | M7: cheetah elephant leopard lion wilddog zebragrevys pangolin aardvark aardwolf africanwildcat baboon batearedfox beisaoryx blackbackedjackal bohorreedbuck buffalo bushbuck bushpig caracal civet jacksonshartebeest commonwaterbuck crocodile defassawaterbuck dikdik eland gazellegrants gazellethompsons gerenuk giantforesthog greyduiker groundhornbill hippo honeybadger hyenaspotted hyenastriped impala klipspringer kudugreater kudulesser oribi ostrich porcupine python reticulatedgiraffe scrubhare serval steenbuck vervetmonkey vulturelappetfaced vultureruppels vulturewhitebacked vulturewhiteheaded warthog whitetailedmongoose wildebeest zebraburchells bird black_rhino chameleon lizard snakes tortoise white_rhino | N7: {"aardvark":"Aardvark / Mhanga","aardwolf":"Aardwolf / Fisi ya Nkole","africanwildcat":"African Wild Cat / Paka Shume","baboon":"Baboon / Nugu","batearedfox":"Bat-eared Fox / Mbweha Masikio","beisaoryx":"Beisa Oryx / Choroa","bird":"Bird / Ndege","black_rhino":"Black Rhino","blackbackedjackal":"Black-backed Jackal / Mbweha Mweusi","bohorreedbuck":"Bohor Reedbuck","buffalo":"Buffalo / Nyathi","bushbuck":"Bushbuck","bushpig":"Bushpig","caracal":"Caracal / Simbamangu","chameleon":"Chameleon","cheetah":"Cheetah / Duma","civet":"Civet","commonwaterbuck":"Common Waterbuck","crocodile":"Crocodile / Mamba","defassawaterbuck":"Defassa Waterbuck / Mende","dikdik":"Dikdik / Elimu","eland":"Eland / Nchi","elephant":"Elephant / Ndovu","gazellegrants":"Grants Gazelle / Swara Granti","gazellethompsons":"Thompsons Gazelle / Swara Tomi","gerenuk":"Gerenuk / Twiga Swara","giantforesthog":"Giant Forest Hog","greyduiker":"Grey Duiker","groundhornbill":"Ground Hornbill","hippo":"Hippo / Kiboko","honeybadger":"Honey Badger / Mbichi ya Asali","hyenaspotted":"Spotted Hyena / Fisi","hyenastriped":"Striped Hyena / Fisi Mwenye Mistari","impala":"Impala / Swara","jacksonshartebeest":"Jacksons Hartebeest","klipspringer":"Klipspringer / Mbuzi Mawe","kudugreater":"Greater Kudu / Tandala Mkubwa","kudulesser":"Lesser Kudu / Tandala Mdogo","leopard":"Leopard / Chui","lion":"Lion / Simba","lizard":"Lizard","oribi":"Oribi","ostrich":"Ostrich / Mbuni","pangolin":"Pangolin","porcupine":"Porcupine / Nungu","python":"Python / Nyoka Mkubwa","reticulatedgiraffe":"Reticulated Giraffe / Twiga","scrubhare":"Scrub Hare","serval":"Serval","snakes":"Snake","steenbuck":"Steenbuck","tortoise":"Tortoise / Mzee Kobe","vervetmonkey":"Vervet Monkey / Tumbiri","vulturelappetfaced":"Lappet Faced Vulture","vultureruppels":"Ruppels Griffon","vulturewhitebacked":"White Backed Vulture","vulturewhiteheaded":"White Headed Vulture","warthog":"Warthog / Ngiri","white_rhino":"White Rhino","whitetailedmongoose":"White-tailed Mongoose / Nguchiro Mkia Mweupe","wilddog":"Wild Dog / Mbwa Mwitu","wildebeest":"Wildebeest / Nyumbu","zebraburchells":"Burchells Zebra / Punda Milia","zebragrevys":"Grevy's Zebra / Punda Milia Mkubwa"} | P7: {"aardvark":"string","aardwolf":"string","africanwildcat":"string","baboon":"string","batearedfox":"string","beisaoryx":"string","blackbackedjackal":"string","bohorreedbuck":"string","buffalo":"string","bushbuck":"string","bushpig":"string","caracal":"string","cheetah":"string","civet":"string","commonwaterbuck":"string","crocodile":"string","defassawaterbuck":"string","dikdik":"string","eland":"string","elephant":"string","gazellegrants":"string","gazellethompsons":"string","gerenuk":"string","giantforesthog":"string","greyduiker":"string","groundhornbill":"string","hippo":"string","honeybadger":"string","hyenaspotted":"string","hyenastriped":"string","impala":"string","jacksonshartebeest":"string","klipspringer":"string","kudugreater":"string","kudulesser":"string","leopard":"string","lion":"string","oribi":"string","ostrich":"string","pangolin":"string","porcupine":"string","python":"string","reticulatedgiraffe":"string","scrubhare":"string","serval":"string","steenbuck":"string","vervetmonkey":"string","vulturelappetfaced":"string","vultureruppels":"string","vulturewhitebacked":"string","vulturewhiteheaded":"string","warthog":"string","whitetailedmongoose":"string","wilddog":"string","wildebeest":"string","zebraburchells":"string","zebragrevys":"string"}
A8: baton_rep | B8: Baton Report | C8: HWC | D8: 97172f47-979e-40ff-ad0a-8e4103b3ea7c | E8: baton_rep[]..justification_use | F8: justification_use | G8: Justification | H8: string | J8: FALSE | K8: FALSE | M8: move_wildlife_HWC move_wildlife_livestock move_wildlife_property move_wildlife_crop removing_game_exclusion return_animals protect_tourists | N8: {"move_wildlife_HWC":"Protecting People from wildlife","move_wildlife_crop":"Protecting Crops from wildlife","move_wildlife_livestock":"Protecting Livestock from wildlife","move_wildlife_property":"Protecting Property from wildlife","protect_tourists":"Self Defense - Protecting tourists from wildlife","removing_game_exclusion":"Removing animals from exclusion zone","return_animals":"Return animals to protected area"}
A9: baton_rep | B9: Baton Report | C9: HWC | D9: 97172f47-979e-40ff-ad0a-8e4103b3ea7c | E9: comm_validation | F9: comm_validation | J9: FALSE | K9: FALSE | W9: Commander Validation
A10: baton_rep | B10: Baton Report | C10: HWC | D10: 97172f47-979e-40ff-ad0a-8e4103b3ea7c | E10: comms | F10: comms | J10: FALSE | K10: FALSE | W10: Communication Via
A11: baton_rep | B11: Baton Report | C11: HWC | D11: 97172f47-979e-40ff-ad0a-8e4103b3ea7c | E11: comments | F11: comments | G11: Comments | H11: string | J11: FALSE | K11: FALSE

Sheet black_rhino_fight_request_2025
A1: event_value | B1: event_name | C1: event_category_display | D1: event_category_id | E1: path | F1: json_key | G1: ui_title | H1: type | I1: format | J1: required | K1: is_array | L1: array_item_type | M1: enum_values | N1: enum_names | O1: inactive_enum | P1: enum_images | Q1: minimum | R1: maximum | S1: pattern | T1: default | U1: examples | V1: description | W1: key_ref | X1: notes
A2: black_rhino_fight_request_2025 | B2: Black Rhino Fight Summary | C2: Rhino Management | D2: 874e243d-16d8-4ac9-89b3-24aaa163eb1f | E2: rhino_two | F2: rhino_two | G2: Second Rhino Name | H2: string | J2: FALSE | K2: FALSE
A3: black_rhino_fight_request_2025 | B3: Black Rhino Fight Summary | C3: Rhino Management | D3: 874e243d-16d8-4ac9-89b3-24aaa163eb1f | E3: rhino_one | F3: rhino_one | G3: First Rhino Name | H3: string | J3: FALSE | K3: FALSE
A4: black_rhino_fight_request_2025 | B4: Black Rhino Fight Summary | C4: Rhino Management | D4: 874e243d-16d8-4ac9-89b3-24aaa163eb1f | E4: cause | F4: cause | G4: Suspected Cause of Fight | H4: string | J4: FALSE | K4: FALSE | M4: territorial courtship unknown | N4: {"courtship":"Courtship","territorial":"Territorial","unknown":"Unknown (only 1 animal present)"}
A5: black_rhino_fight_request_2025 | B5: Black Rhino Fight Summary | C5: Rhino Management | D5: 874e243d-16d8-4ac9-89b3-24aaa163eb1f | E5: blackrhinosighting_watchkeepervalidation | F5: blackrhinosighting_watchkeepervalidation | G5: Watch Keeper Validation | H5: string | J5: FALSE | K5: FALSE
A6: black_rhino_fight_request_2025 | B6: Black Rhino Fight Summary | C6: Rhino Management | D6: 874e243d-16d8-4ac9-89b3-24aaa163eb1f | E6: blackrhinofight_actionschecklist | F6: blackrhinofight_actionschecklist | J6: FALSE | K6: FALSE | W6: blackrhinofight_actionschecklist
A7: black_rhino_fight_request_2025 | B7: Black Rhino Fight Summary | C7: Rhino Management | D7: 874e243d-16d8-4ac9-89b3-24aaa163eb1f | E7: er2er_src_id | F7: er2er_src_id | G7: Event Type Serial Number from Source ER System | H7: string | J7: FALSE | K7: FALSE
A8: black_rhino_fight_request_2025 | B8: Black Rhino Fight Summary | C8: Rhino Management | D8: 874e243d-16d8-4ac9-89b3-24aaa163eb1f | E8: er2er_src_system | F8: er2er_src_system | G8: Name of Source ER System | H8: string | J8: FALSE | K8: FALSE
A9: black_rhino_fight_request_2025 | B9: Black Rhino Fight Summary | C9: Rhino Management | D9: 874e243d-16d8-4ac9-89b3-24aaa163eb1f | E9: er2er_src_serial_number | F9: er2er_src_serial_number | G9: Serial Number of Source Event | H9: string | J9: FALSE | K9: FALSE
A10: black_rhino_fight_request_2025 | B10: Black Rhino Fight Summary | C10: Rhino Management | D10: 874e243d-16d8-4ac9-89b3-24aaa163eb1f | E10: er2er_src_service_root | F10: er2er_src_service_root | G10: Service Root of Source Event | H10: string | J10: FALSE | K10: FALSE

Sheet black_rhino_home_range
A1: event_value | B1: event_name | C1: event_category_display | D1: event_category_id | E1: path | F1: json_key | G1: ui_title | H1: type | I1: format | J1: required | K1: is_array | L1: array_item_type | M1: enum_values | N1: enum_names | O1: inactive_enum | P1: enum_images | Q1: minimum | R1: maximum | S1: pattern | T1: default | U1: examples | V1: description | W1: key_ref | X1: notes
A2: black_rhino_home_range | B2: Black Rhino Home Range | C2: Rhino Management | D2: 874e243d-16d8-4ac9-89b3-24aaa163eb1f | E2: sighting_details_bulls | F2: sighting_details_bulls | G2: Details - Bulls | H2: array | J2: FALSE | K2: TRUE | L2: object
A3: black_rhino_home_range | B3: Black Rhino Home Range | C3: Rhino Management | D3: 874e243d-16d8-4ac9-89b3-24aaa163eb1f | E3: sighting_details_bulls[]..blackrhinosighting_kifid_bull | F3: blackrhinosighting_kifid_bull | G3: Kifaru ID | H3: string | J3: FALSE | K3: FALSE
A4: black_rhino_home_range | B4: Black Rhino Home Range | C4: Rhino Management | D4: 874e243d-16d8-4ac9-89b3-24aaa163eb1f | E4: sighting_details_bulls[]..known_bulls | F4: known_bulls | G4: Bull | H4: string | J4: FALSE | K4: FALSE
A5: black_rhino_home_range | B5: Black Rhino Home Range | C5: Rhino Management | D5: 874e243d-16d8-4ac9-89b3-24aaa163eb1f | E5: sighting_details_bulls[]..known_age_bull | F5: known_age_bull | G5: Age | H5: string | J5: FALSE | K5: FALSE
A6: black_rhino_home_range | B6: Black Rhino Home Range | C6: Rhino Management | D6: 874e243d-16d8-4ac9-89b3-24aaa163eb1f | E6: sighting_details_cows | F6: sighting_details_cows | G6: Details - Cows | H6: array | J6: FALSE | K6: TRUE | L6: object
A7: black_rhino_home_range | B7: Black Rhino Home Range | C7: Rhino Management | D7: 874e243d-16d8-4ac9-89b3-24aaa163eb1f | E7: sighting_details_cows[]..blackrhinosighting_kifid_cow | F7: blackrhinosighting_kifid_cow | G7: Kifaru ID | H7: string | J7: FALSE | K7: FALSE
A8: black_rhino_home_range | B8: Black Rhino Home Range | C8: Rhino Management | D8: 874e243d-16d8-4ac9-89b3-24aaa163eb1f | E8: sighting_details_cows[]..known_cows | F8: known_cows | G8: Known Cows | H8: string | J8: FALSE | K8: FALSE
A9: black_rhino_home_range | B9: Black Rhino Home Range | C9: Rhino Management | D9: 874e243d-16d8-4ac9-89b3-24aaa163eb1f | E9: sighting_details_cows[]..known_age_cow | F9: known_age_cow | G9: Age | H9: string | J9: FALSE | K9: FALSE | M9: a b c d e f | N9: {"a":"A (0-3 months)","b":"B (3 months - 1 year)","c":"C (1 - 2 years)","d":"D (2 - 3.5 years)","e":"E (3.5 - 7 years)","f":"F (adult 7+ years)"}
A10: black_rhino_home_range | B10: Black Rhino Home Range | C10: Rhino Management | D10: 874e243d-16d8-4ac9-89b3-24aaa163eb1f | E10: time_period | F10: time_period | G10: Time Period | H10: string | J10: FALSE | K10: FALSE | M10: q1 q2 q3 q4 | N10: {"q1":"January - March (Q1)","q2":"April - June (Q2)","q3":"July - September (Q3)","q4":"October - December (Q4)"}
A11: black_rhino_home_range | B11: Black Rhino Home Range | C11: Rhino Management | D11: 874e243d-16d8-4ac9-89b3-24aaa163eb1f | E11: time_year | F11: time_year | G11: Year | H11: string | J11: FALSE | K11: FALSE | M11: 2022 2023 2024 2025 | N11: {"2022":"2022","2023":"2023","2024":"2024","2025":"2025"}
A12: black_rhino_home_range | B12: Black Rhino Home Range | C12: Rhino Management | D12: 874e243d-16d8-4ac9-89b3-24aaa163eb1f | E12: blackrhinosighting_watchkeepervalidation | F12: blackrhinosighting_watchkeepervalidation | G12: Watch Keeper Validation | H12: string | J12: FALSE | K12: FALSE
A13: black_rhino_home_range | B13: Black Rhino Home Range | C13: Rhino Management | D13: 874e243d-16d8-4ac9-89b3-24aaa163eb1f | E13: blackrhinosighting_actionschecklist | F13: blackrhinosighting_actionschecklist | J13: FALSE | K13: FALSE | W13: blackrhinosighting_actionschecklist
A14: black_rhino_home_range | B14: Black Rhino Home Range | C14: Rhino Management | D14: 874e243d-16d8-4ac9-89b3-24aaa163eb1f | E14: er2er_src_id | F14: er2er_src_id | G14: Event Type Serial Number from Source ER System | H14: string | J14: FALSE | K14: FALSE
A15: black_rhino_home_range | B15: Black Rhino Home Range | C15: Rhino Management | D15: 874e243d-16d8-4ac9-89b3-24aaa163eb1f | E15: er2er_src_system | F15: er2er_src_system | G15: Name of Source ER System | H15: string | J15: FALSE | K15: FALSE
A16: black_rhino_home_range | B16: Black Rhino Home Range | C16: Rhino Management | D16: 874e243d-16d8-4ac9-89b3-24aaa163eb1f | E16: er2er_src_serial_number | F16: er2er_src_serial_number | G16: Serial Number of Source Event | H16: string | J16: FALSE | K16: FALSE
A17: black_rhino_home_range | B17: Black Rhino Home Range | C17: Rhino Management | D17: 874e243d-16d8-4ac9-89b3-24aaa163eb1f | E17: er2er_src_service_root | F17: er2er_src_service_root | G17: Service Root of Source Event | H17: string | J17: FALSE | K17: FALSE

Sheet black_rhino_mating_2025
A1: event_value | B1: event_name | C1: event_category_display | D1: event_category_id | E1: path | F1: json_key | G1: ui_title | H1: type | I1: format | J1: required | K1: is_array | L1: array_item_type | M1: enum_values | N1: enum_names | O1: inactive_enum | P1: enum_images | Q1: minimum | R1: maximum | S1: pattern | T1: default | U1: examples | V1: description | W1: key_ref | X1: notes
A2: black_rhino_mating_2025 | B2: Black Rhino Mating | C2: Rhino Management | D2: 874e243d-16d8-4ac9-89b3-24aaa163eb1f | E2: rhino_two | F2: rhino_two | G2: Bull Name | H2: string | J2: FALSE | K2: FALSE
A3: black_rhino_mating_2025 | B3: Black Rhino Mating | C3: Rhino Management | D3: 874e243d-16d8-4ac9-89b3-24aaa163eb1f | E3: rhino_one | F3: rhino_one | G3: Cow Name | H3: string | J3: FALSE | K3: FALSE
A4: black_rhino_mating_2025 | B4: Black Rhino Mating | C4: Rhino Management | D4: 874e243d-16d8-4ac9-89b3-24aaa163eb1f | E4: blackrhinosighting_watchkeepervalidation | F4: blackrhinosighting_watchkeepervalidation | G4: Watch Keeper Validation | H4: string | J4: FALSE | K4: FALSE
A5: black_rhino_mating_2025 | B5: Black Rhino Mating | C5: Rhino Management | D5: 874e243d-16d8-4ac9-89b3-24aaa163eb1f | E5: blackrhinofight_actionschecklist | F5: blackrhinofight_actionschecklist | J5: FALSE | K5: FALSE | W5: blackrhinofight_actionschecklist
A6: black_rhino_mating_2025 | B6: Black Rhino Mating | C6: Rhino Management | D6: 874e243d-16d8-4ac9-89b3-24aaa163eb1f | E6: er2er_src_id | F6: er2er_src_id | G6: Event Type Serial Number from Source ER System | H6: string | J6: FALSE | K6: FALSE
A7: black_rhino_mating_2025 | B7: Black Rhino Mating | C7: Rhino Management | D7: 874e243d-16d8-4ac9-89b3-24aaa163eb1f | E7: er2er_src_system | F7: er2er_src_system | G7: Name of Source ER System | H7: string | J7: FALSE | K7: FALSE
A8: black_rhino_mating_2025 | B8: Black Rhino Mating | C8: Rhino Management | D8: 874e243d-16d8-4ac9-89b3-24aaa163eb1f | E8: er2er_src_serial_number | F8: er2er_src_serial_number | G8: Serial Number of Source Event | H8: string | J8: FALSE | K8: FALSE
A9: black_rhino_mating_2025 | B9: Black Rhino Mating | C9: Rhino Management | D9: 874e243d-16d8-4ac9-89b3-24aaa163eb1f | E9: er2er_src_service_root | F9: er2er_src_service_root | G9: Service Root of Source Event | H9: string | J9: FALSE | K9: FALSE

Sheet black_rhino_sighting_rv002
A1: event_value | B1: event_name | C1: event_category_display | D1: event_category_id | E1: path | F1: json_key | G1: ui_title | H1: type | I1: format | J1: required | K1: is_array | L1: array_item_type | M1: enum_values | N1: enum_names | O1: inactive_enum | P1: enum_images | Q1: minimum | R1: maximum | S1: pattern | T1: default | U1: examples | V1: description | W1: key_ref | X1: notes
A2: black_rhino_sighting_rv002 | B2: Black Rhino Sighting | C2: Rhino Management | D2: 874e243d-16d8-4ac9-89b3-24aaa163eb1f | E2: sighting_details_bulls | F2: sighting_details_bulls | G2: Sighting Details - Bulls | H2: array | J2: FALSE | K2: TRUE | L2: object
A3: black_rhino_sighting_rv002 | B3: Black Rhino Sighting | C3: Rhino Management | D3: 874e243d-16d8-4ac9-89b3-24aaa163eb1f | E3: sighting_details_bulls[]..blackrhinosighting_kifid_bull | F3: blackrhinosighting_kifid_bull | G3: Kifaru ID | H3: string | J3: FALSE | K3: FALSE
A4: black_rhino_sighting_rv002 | B4: Black Rhino Sighting | C4: Rhino Management | D4: 874e243d-16d8-4ac9-89b3-24aaa163eb1f | E4: sighting_details_bulls[]..known_bulls | F4: known_bulls | G4: Bull | H4: string | J4: FALSE | K4: FALSE
A5: black_rhino_sighting_rv002 | B5: Black Rhino Sighting | C5: Rhino Management | D5: 874e243d-16d8-4ac9-89b3-24aaa163eb1f | E5: sighting_details_bulls[]..known_age_bull | F5: known_age_bull | G5: Age | H5: string | J5: FALSE | K5: FALSE | M5: a b c d e f | N5: {"a":"A (0-3 months)","b":"B (3 months - 1 year)","c":"C (1 - 2 years)","d":"D (2 - 3.5 years)","e":"E (3.5 - 7 years)","f":"F (adult 7+ years)"}
A6: black_rhino_sighting_rv002 | B6: Black Rhino Sighting | C6: Rhino Management | D6: 874e243d-16d8-4ac9-89b3-24aaa163eb1f | E6: sighting_details_bulls[]..sighting | F6: sighting | G6: Sighting | H6: string | J6: FALSE | K6: FALSE | M6: visual spoor dung telemetry cam_trap | N6: {"cam_trap":"Camera Trap","dung":"Dung","spoor":"Spoor","telemetry":"Telemetry","visual":"Visual"} | P6: {"dung":"string","spoor":"string","telemetry":"string","visual":"string"}
A7: black_rhino_sighting_rv002 | B7: Black Rhino Sighting | C7: Rhino Management | D7: 874e243d-16d8-4ac9-89b3-24aaa163eb1f | E7: sighting_details_bulls[]..condition | F7: condition | G7: Condition | H7: string | J7: FALSE | K7: FALSE | P7: {"five":"string","four":"string","four_half":"string","one":"string","three":"string","three_half":"string","two":"string","two_half":"string"}
A8: black_rhino_sighting_rv002 | B8: Black Rhino Sighting | C8: Rhino Management | D8: 874e243d-16d8-4ac9-89b3-24aaa163eb1f | E8: sighting_details_bulls[]..injuries | F8: injuries | G8: Injuries | H8: string | J8: FALSE | K8: FALSE | P8: {"majorinjury":"string","minorinjury":"string","noinjuries":"string"}
A9: black_rhino_sighting_rv002 | B9: Black Rhino Sighting | C9: Rhino Management | D9: 874e243d-16d8-4ac9-89b3-24aaa163eb1f | E9: sighting_details_cows | F9: sighting_details_cows | G9: Sighting Details - Cows | H9: array | J9: FALSE | K9: TRUE | L9: object
A10: black_rhino_sighting_rv002 | B10: Black Rhino Sighting | C10: Rhino Management | D10: 874e243d-16d8-4ac9-89b3-24aaa163eb1f | E10: sighting_details_cows[]..blackrhinosighting_kifid_cow | F10: blackrhinosighting_kifid_cow | G10: Kifaru ID | H10: string | J10: FALSE | K10: FALSE
A11: black_rhino_sighting_rv002 | B11: Black Rhino Sighting | C11: Rhino Management | D11: 874e243d-16d8-4ac9-89b3-24aaa163eb1f | E11: sighting_details_cows[]..known_cows | F11: known_cows | G11: Known Cows | H11: string | J11: FALSE | K11: FALSE
A12: black_rhino_sighting_rv002 | B12: Black Rhino Sighting | C12: Rhino Management | D12: 874e243d-16d8-4ac9-89b3-24aaa163eb1f | E12: sighting_details_cows[]..known_age_cow | F12: known_age_cow | G12: Age | H12: string | J12: FALSE | K12: FALSE | M12: a b c d e f | N12: {"a":"A (0-3 months)","b":"B (3 months - 1 year)","c":"C (1 - 2 years)","d":"D (2 - 3.5 years)","e":"E (3.5 - 7 years)","f":"F (adult 7+ years)"}
A13: black_rhino_sighting_rv002 | B13: Black Rhino Sighting | C13: Rhino Management | D13: 874e243d-16d8-4ac9-89b3-24aaa163eb1f | E13: sighting_details_cows[]..sighting | F13: sighting | G13: Sighting | H13: string | J13: FALSE | K13: FALSE | M13: visual spoor dung telemetry cam_trap | N13: {"cam_trap":"Camera Trap","dung":"Dung","spoor":"Spoor","telemetry":"Telemetry","visual":"Visual"} | P13: {"dung":"string","spoor":"string","telemetry":"string","visual":"string"}
A14: black_rhino_sighting_rv002 | B14: Black Rhino Sighting | C14: Rhino Management | D14: 874e243d-16d8-4ac9-89b3-24aaa163eb1f | E14: sighting_details_cows[]..condition | F14: condition | G14: Condition | H14: string | J14: FALSE | K14: FALSE | M14: one two two_half three three_half four four_half five | N14: {"five":"5","four":"4","four_half":"4.5","one":"1","three":"3","three_half":"3.5","two":"2","two_half":"2.5"} | P14: {"five":"string","four":"string","four_half":"string","one":"string","three":"string","three_half":"string","two":"string","two_half":"string"}
A15: black_rhino_sighting_rv002 | B15: Black Rhino Sighting | C15: Rhino Management | D15: 874e243d-16d8-4ac9-89b3-24aaa163eb1f | E15: sighting_details_cows[]..injuries | F15: injuries | G15: Injuries | H15: string | J15: FALSE | K15: FALSE | M15: majorinjury minorinjury noinjuries | N15: {"majorinjury":"Major Injury","minorinjury":"Minor Injury","noinjuries":"No Injuries"} | P15: {"majorinjury":"string","minorinjury":"string","noinjuries":"string"}
A16: black_rhino_sighting_rv002 | B16: Black Rhino Sighting | C16: Rhino Management | D16: 874e243d-16d8-4ac9-89b3-24aaa163eb1f | E16: sighting_details_nk | F16: sighting_details_nk | G16: Sighting Details - Unsexed Individuals | H16: array | J16: FALSE | K16: TRUE | L16: object
A17: black_rhino_sighting_rv002 | B17: Black Rhino Sighting | C17: Rhino Management | D17: 874e243d-16d8-4ac9-89b3-24aaa163eb1f | E17: sighting_details_nk[]..blackrhinosighting_unsexed_kifid | F17: blackrhinosighting_unsexed_kifid | G17: Kifaru ID | H17: string | J17: FALSE | K17: FALSE
A18: black_rhino_sighting_rv002 | B18: Black Rhino Sighting | C18: Rhino Management | D18: 874e243d-16d8-4ac9-89b3-24aaa163eb1f | E18: sighting_details_nk[]..unsexed_individuals | F18: unsexed_individuals | G18: Unsexed Individual(s) | H18: string | J18: FALSE | K18: FALSE
A19: black_rhino_sighting_rv002 | B19: Black Rhino Sighting | C19: Rhino Management | D19: 874e243d-16d8-4ac9-89b3-24aaa163eb1f | E19: sighting_details_nk[]..sighting | F19: sighting | G19: Sighting | H19: string | J19: FALSE | K19: FALSE | M19: visual spoor dung telemetry cam_trap | N19: {"cam_trap":"Camera Trap","dung":"Dung","spoor":"Spoor","telemetry":"Telemetry","visual":"Visual"} | P19: {"dung":"string","spoor":"string","telemetry":"string","visual":"string"}
A20: black_rhino_sighting_rv002 | B20: Black Rhino Sighting | C20: Rhino Management | D20: 874e243d-16d8-4ac9-89b3-24aaa163eb1f | E20: sighting_details_nk[]..condition | F20: condition | G20: Condition | H20: string | J20: FALSE | K20: FALSE | M20: one two two_half three three_half four four_half five | N20: {"five":"5","four":"4","four_half":"4.5","one":"1","three":"3","three_half":"3.5","two":"2","two_half":"2.5"} | P20: {"five":"string","four":"string","four_half":"string","one":"string","three":"string","three_half":"string","two":"string","two_half":"string"}
A21: black_rhino_sighting_rv002 | B21: Black Rhino Sighting | C21: Rhino Management | D21: 874e243d-16d8-4ac9-89b3-24aaa163eb1f | E21: sighting_details_nk[]..injuries | F21: injuries | G21: Injuries | H21: string | J21: FALSE | K21: FALSE | M21: majorinjury minorinjury noinjuries | N21: {"majorinjury":"Major Injury","minorinjury":"Minor Injury","noinjuries":"No Injuries"} | P21: {"majorinjury":"string","minorinjury":"string","noinjuries":"string"}
A22: black_rhino_sighting_rv002 | B22: Black Rhino Sighting | C22: Rhino Management | D22: 874e243d-16d8-4ac9-89b3-24aaa163eb1f | E22: blackrhinosighting_groupsize | F22: blackrhinosighting_groupsize | G22: Group Size | H22: number | J22: FALSE | K22: FALSE | Q22: 0
A23: black_rhino_sighting_rv002 | B23: Black Rhino Sighting | C23: Rhino Management | D23: 874e243d-16d8-4ac9-89b3-24aaa163eb1f | E23: blackrhinosighting_exclusion_yesno | F23: blackrhinosighting_exclusion_yesno | G23: Inside Exclusion? | H23: string | J23: FALSE | K23: FALSE | M23: yes no | N23: {"no":"No","yes":"Yes"}
A24: black_rhino_sighting_rv002 | B24: Black Rhino Sighting | C24: Rhino Management | D24: 874e243d-16d8-4ac9-89b3-24aaa163eb1f | E24: blackrhinosighting_exclusion | F24: blackrhinosighting_exclusion | G24: Exclusion Zone | H24: string | J24: FALSE | K24: FALSE | M24: arijuju bor_leng hq waitabit | N24: {"arijuju":"Arijuju","bor_leng":"Borana/Lengishu","hq":"HQ","waitabit":"Waitabit"}
A25: black_rhino_sighting_rv002 | B25: Black Rhino Sighting | C25: Rhino Management | D25: 874e243d-16d8-4ac9-89b3-24aaa163eb1f | E25: blackrhinosighting_watchkeepervalidation | F25: blackrhinosighting_watchkeepervalidation | G25: Watch Keeper Validation | H25: string | J25: FALSE | K25: FALSE
A26: black_rhino_sighting_rv002 | B26: Black Rhino Sighting | C26: Rhino Management | D26: 874e243d-16d8-4ac9-89b3-24aaa163eb1f | E26: blackrhinosighting_actionschecklist | F26: blackrhinosighting_actionschecklist | J26: FALSE | K26: FALSE | W26: blackrhinosighting_actionschecklist
A27: black_rhino_sighting_rv002 | B27: Black Rhino Sighting | C27: Rhino Management | D27: 874e243d-16d8-4ac9-89b3-24aaa163eb1f | E27: er2er_src_id | F27: er2er_src_id | G27: Event Type Serial Number from Source ER System | H27: string | J27: FALSE | K27: FALSE
A28: black_rhino_sighting_rv002 | B28: Black Rhino Sighting | C28: Rhino Management | D28: 874e243d-16d8-4ac9-89b3-24aaa163eb1f | E28: er2er_src_system | F28: er2er_src_system | G28: Name of Source ER System | H28: string | J28: FALSE | K28: FALSE
A29: black_rhino_sighting_rv002 | B29: Black Rhino Sighting | C29: Rhino Management | D29: 874e243d-16d8-4ac9-89b3-24aaa163eb1f | E29: er2er_src_serial_number | F29: er2er_src_serial_number | G29: Serial Number of Source Event | H29: string | J29: FALSE | K29: FALSE
A30: black_rhino_sighting_rv002 | B30: Black Rhino Sighting | C30: Rhino Management | D30: 874e243d-16d8-4ac9-89b3-24aaa163eb1f | E30: er2er_src_service_root | F30: er2er_src_service_root | G30: Service Root of Source Event | H30: string | J30: FALSE | K30: FALSE

Sheet bmc_vehicle_refuel
A1: event_value | B1: event_name | C1: event_category_display | D1: event_category_id | E1: path | F1: json_key | G1: ui_title | H1: type | I1: format | J1: required | K1: is_array | L1: array_item_type | M1: enum_values | N1: enum_names | O1: inactive_enum | P1: enum_images | Q1: minimum | R1: maximum | S1: pattern | T1: default | U1: examples | V1: description | W1: key_ref | X1: notes
A2: bmc_vehicle_refuel | B2: BMC Vehicle Refuel | C2: Borana Mobile Clinic | D2: b4d1066b-22d5-4007-a466-a0282063c2f5 | E2: vehicle_registration | F2: vehicle_registration | G2: Vehicle Registration (all capitals, no spaces) | H2: string | J2: TRUE | K2: FALSE
A3: bmc_vehicle_refuel | B3: BMC Vehicle Refuel | C3: Borana Mobile Clinic | D3: b4d1066b-22d5-4007-a466-a0282063c2f5 | E3: fuel_litres | F3: fuel_litres | G3: Litres Fuel Filled (L) | H3: number | J3: TRUE | K3: FALSE | Q3: 0
A4: bmc_vehicle_refuel | B4: BMC Vehicle Refuel | C4: Borana Mobile Clinic | D4: b4d1066b-22d5-4007-a466-a0282063c2f5 | E4: mileage_km | F4: mileage_km | G4: Mileage Reading (Kms) | H4: number | J4: TRUE | K4: FALSE | Q4: 0
A5: bmc_vehicle_refuel | B5: BMC Vehicle Refuel | C5: Borana Mobile Clinic | D5: b4d1066b-22d5-4007-a466-a0282063c2f5 | E5: reading_date | F5: reading_date | G5: Date Reading Taken | H5: string | I5: date-time | J5: TRUE | K5: FALSE

Sheet bmc_visit_summary
A1: event_value | B1: event_name | C1: event_category_display | D1: event_category_id | E1: path | F1: json_key | G1: ui_title | H1: type | I1: format | J1: required | K1: is_array | L1: array_item_type | M1: enum_values | N1: enum_names | O1: inactive_enum | P1: enum_images | Q1: minimum | R1: maximum | S1: pattern | T1: default | U1: examples | V1: description | W1: key_ref | X1: notes
A2: bmc_visit_summary | B2: BMC Visit Summary | C2: Borana Mobile Clinic | D2: b4d1066b-22d5-4007-a466-a0282063c2f5 | E2: county | F2: county | G2: County | H2: string | J2: TRUE | K2: FALSE | M2: Laikipia County Meru County | N2: Laikipia County Meru County
A3: bmc_visit_summary | B3: BMC Visit Summary | C3: Borana Mobile Clinic | D3: b4d1066b-22d5-4007-a466-a0282063c2f5 | E3: station_visited | F3: station_visited | G3: Station Visited | H3: string | J3: TRUE | K3: FALSE
A4: bmc_visit_summary | B4: BMC Visit Summary | C4: Borana Mobile Clinic | D4: b4d1066b-22d5-4007-a466-a0282063c2f5 | E4: school_name | F4: school_name | G4: If School, enter name | H4: string | J4: FALSE | K4: FALSE
A5: bmc_visit_summary | B5: BMC Visit Summary | C5: Borana Mobile Clinic | D5: b4d1066b-22d5-4007-a466-a0282063c2f5 | E5: other_school_name | F5: other_school_name | G5: If Other, enter name | H5: string | J5: FALSE | K5: FALSE
A6: bmc_visit_summary | B6: BMC Visit Summary | C6: Borana Mobile Clinic | D6: b4d1066b-22d5-4007-a466-a0282063c2f5 | E6: visit_start_date | F6: visit_start_date | G6: Date Visit Started | H6: string | I6: date-time | J6: TRUE | K6: FALSE
A7: bmc_visit_summary | B7: BMC Visit Summary | C7: Borana Mobile Clinic | D7: b4d1066b-22d5-4007-a466-a0282063c2f5 | E7: days_spent | F7: days_spent | G7: How many days spent at the Station | H7: number | J7: TRUE | K7: FALSE | Q7: 0
A8: bmc_visit_summary | B8: BMC Visit Summary | C8: Borana Mobile Clinic | D8: b4d1066b-22d5-4007-a466-a0282063c2f5 | E8: curative_appointments | F8: curative_appointments | G8: Number of curative appointments | H8: number | J8: TRUE | K8: FALSE | Q8: 0
A9: bmc_visit_summary | B9: BMC Visit Summary | C9: Borana Mobile Clinic | D9: b4d1066b-22d5-4007-a466-a0282063c2f5 | E9: family_planning | F9: family_planning | G9: Number of family planning appointments | H9: number | J9: TRUE | K9: FALSE | Q9: 0
A10: bmc_visit_summary | B10: BMC Visit Summary | C10: Borana Mobile Clinic | D10: b4d1066b-22d5-4007-a466-a0282063c2f5 | E10: immunizations_under5 | F10: immunizations_under5 | G10: Number of immunizations under 5 years old | H10: number | J10: TRUE | K10: FALSE | Q10: 0
A11: bmc_visit_summary | B11: BMC Visit Summary | C11: Borana Mobile Clinic | D11: b4d1066b-22d5-4007-a466-a0282063c2f5 | E11: antenatal_care | F11: antenatal_care | G11: Number of Anti Natal Care appointments | H11: number | J11: TRUE | K11: FALSE | Q11: 0
A12: bmc_visit_summary | B12: BMC Visit Summary | C12: Borana Mobile Clinic | D12: b4d1066b-22d5-4007-a466-a0282063c2f5 | E12: measles_campaign | F12: measles_campaign | G12: Measles campaign | H12: number | J12: TRUE | K12: FALSE | Q12: 0
A13: bmc_visit_summary | B13: BMC Visit Summary | C13: Borana Mobile Clinic | D13: b4d1066b-22d5-4007-a466-a0282063c2f5 | E13: total_immunizations | F13: total_immunizations | G13: Number immunizations | H13: number | J13: TRUE | K13: FALSE | Q13: 0
A14: bmc_visit_summary | B14: BMC Visit Summary | C14: Borana Mobile Clinic | D14: b4d1066b-22d5-4007-a466-a0282063c2f5 | E14: deworming_school | F14: deworming_school | G14: Number of dewormings (school children) | H14: number | J14: TRUE | K14: FALSE | Q14: 0
A15: bmc_visit_summary | B15: BMC Visit Summary | C15: Borana Mobile Clinic | D15: b4d1066b-22d5-4007-a466-a0282063c2f5 | E15: malnutrition_screenings | F15: malnutrition_screenings | G15: Number of malnutrition screenings | H15: number | J15: TRUE | K15: FALSE | Q15: 0
A16: bmc_visit_summary | B16: BMC Visit Summary | C16: Borana Mobile Clinic | D16: b4d1066b-22d5-4007-a466-a0282063c2f5 | E16: hiv_counselling | F16: hiv_counselling | G16: Number of HIV counselling appointments | H16: number | J16: TRUE | K16: FALSE | Q16: 0
A17: bmc_visit_summary | B17: BMC Visit Summary | C17: Borana Mobile Clinic | D17: b4d1066b-22d5-4007-a466-a0282063c2f5 | E17: hiv_tests | F17: hiv_tests | G17: Number of HIV tests | H17: number | J17: TRUE | K17: FALSE | Q17: 0
A18: bmc_visit_summary | B18: BMC Visit Summary | C18: Borana Mobile Clinic | D18: b4d1066b-22d5-4007-a466-a0282063c2f5 | E18: hiv_positive | F18: hiv_positive | G18: Number of HIV positive tests performed | H18: number | J18: TRUE | K18: FALSE | Q18: 0
... A20: bmc_visit_summary | B20: BMC Visit Summary | C20: Borana Mobile Clinic | D20: b4d1066b-22d5-4007-a466-a0282063c2f5 | E20: under5_hiv_positive | F20: under5_hiv_positive | G20: Number of children under 5 and HIV positive | H20: number | J20: TRUE | K20: FALSE | Q20: 0
A21: bmc_visit_summary | B21: BMC Visit Summary | C21: Borana Mobile Clinic | D21: b4d1066b-22d5-4007-a466-a0282063c2f5 | E21: drugs_borana_value | F21: drugs_borana_value | G21: Value of drugs supplied by Borana (Ksh) | H21: string | J21: FALSE | K21: FALSE
A22: bmc_visit_summary | B22: BMC Visit Summary | C22: Borana Mobile Clinic | D22: b4d1066b-22d5-4007-a466-a0282063c2f5 | E22: drugs_kemsa_value | F22: drugs_kemsa_value | G22: Value of drugs supplied by KEMSA (Ksh) | H22: string | J22: FALSE | K22: FALSE
A23: bmc_visit_summary | B23: BMC Visit Summary | C23: Borana Mobile Clinic | D23: b4d1066b-22d5-4007-a466-a0282063c2f5 | E23: other_drugs | F23: other_drugs | G23: Provision of other drugs | H23: string | J23: FALSE | K23: FALSE
A24: bmc_visit_summary | B24: BMC Visit Summary | C24: Borana Mobile Clinic | D24: b4d1066b-22d5-4007-a466-a0282063c2f5 | E24: comments | F24: comments | G24: Stories and comments from the day | H24: string | J24: FALSE | K24: FALSE
A25: bmc_visit_summary | B25: BMC Visit Summary | C25: Borana Mobile Clinic | D25: b4d1066b-22d5-4007-a466-a0282063c2f5 | E25: photos | F25: photos | G25: Photo comments (upload below) | H25: string | J25: FALSE | K25: FALSE

Sheet br_birth
A1: event_value | B1: event_name | C1: event_category_display | D1: event_category_id | E1: path | F1: json_key | G1: ui_title | H1: type | I1: format | J1: required | K1: is_array | L1: array_item_type | M1: enum_values | N1: enum_names | O1: inactive_enum | P1: enum_images | Q1: minimum | R1: maximum | S1: pattern | T1: default | U1: examples | V1: description | W1: key_ref | X1: notes
A2: br_birth | B2: Black Rhino Birth | C2: Rhino Management | D2: 874e243d-16d8-4ac9-89b3-24aaa163eb1f | E2: er2er_src_id | F2: er2er_src_id | G2: Event Type Serial Number from Source ER System | H2: string | J2: FALSE | K2: FALSE
A3: br_birth | B3: Black Rhino Birth | C3: Rhino Management | D3: 874e243d-16d8-4ac9-89b3-24aaa163eb1f | E3: er2er_src_system | F3: er2er_src_system | G3: Name of Source ER System | H3: string | J3: FALSE | K3: FALSE
A4: br_birth | B4: Black Rhino Birth | C4: Rhino Management | D4: 874e243d-16d8-4ac9-89b3-24aaa163eb1f | E4: er2er_src_serial_number | F4: er2er_src_serial_number | G4: Serial Number of Source Event | H4: string | J4: FALSE | K4: FALSE
A5: br_birth | B5: Black Rhino Birth | C5: Rhino Management | D5: 874e243d-16d8-4ac9-89b3-24aaa163eb1f | E5: er2er_src_service_root | F5: er2er_src_service_root | G5: Service Root of Source Event | H5: string | J5: FALSE | K5: FALSE
A6: br_birth | B6: Black Rhino Birth | C6: Rhino Management | D6: 874e243d-16d8-4ac9-89b3-24aaa163eb1f | E6: rhino_birthmother_kfid | F6: rhino_birthmother_kfid | G6: KIFARU ID | H6: string | J6: FALSE | K6: FALSE
A7: br_birth | B7: Black Rhino Birth | C7: Rhino Management | D7: 874e243d-16d8-4ac9-89b3-24aaa163eb1f | E7: rhinobirth_mother_name | F7: rhinobirth_mother_name | G7: Black Rhino Mother | H7: string | J7: FALSE | K7: FALSE
A8: br_birth | B8: Black Rhino Birth | C8: Rhino Management | D8: 874e243d-16d8-4ac9-89b3-24aaa163eb1f | E8: rhinobirth_calfhealth | F8: rhinobirth_calfhealth | G8: Calf Health | H8: string | J8: FALSE | K8: FALSE | M8: healthy stable critical | N8: {"critical":"Critical","healthy":"Healthy","stable":"Stable"} | P8: {"critical":"string","healthy":"string","stable":"string"}
A9: br_birth | B9: Black Rhino Birth | C9: Rhino Management | D9: 874e243d-16d8-4ac9-89b3-24aaa163eb1f | E9: rhinobirth_cowbcs | F9: rhinobirth_cowbcs | G9: Cow - BCS | H9: string | J9: FALSE | K9: FALSE | M9: 1 2 25 3 35 4 45 5 | N9: {"1":"1","2":"2","25":"2.5","3":"3","35":"3.5","4":"4","45":"4.5","5":"5"} | P9: {"1":"string","2":"string","25":"string","3":"string","35":"string","4":"string","45":"string","5":"string"}
A10: br_birth | B10: Black Rhino Birth | C10: Rhino Management | D10: 874e243d-16d8-4ac9-89b3-24aaa163eb1f | E10: rhinobirth_calfsex | F10: rhinobirth_calfsex | G10: Calf Sex | H10: string | J10: FALSE | K10: FALSE | M10: 2 1 | N10: {"1":"Male","2":"Female"}
A11: br_birth | B11: Black Rhino Birth | C11: Rhino Management | D11: 874e243d-16d8-4ac9-89b3-24aaa163eb1f | E11: id_name_calf | F11: id_name_calf | G11: Calf KIFARU ID No | H11: string | J11: FALSE | K11: FALSE
A12: br_birth | B12: Black Rhino Birth | C12: Rhino Management | D12: 874e243d-16d8-4ac9-89b3-24aaa163eb1f | E12: calf_number | F12: calf_number | G12: Calf Number | H12: number | J12: FALSE | K12: FALSE
A13: br_birth | B13: Black Rhino Birth | C13: Rhino Management | D13: 874e243d-16d8-4ac9-89b3-24aaa163eb1f | E13: dob | F13: dob | G13: Date of Birth | H13: string | I13: date | J13: FALSE | K13: FALSE
A14: br_birth | B14: Black Rhino Birth | C14: Rhino Management | D14: 874e243d-16d8-4ac9-89b3-24aaa163eb1f | E14: calfname | F14: calfname | G14: Calf Name | H14: string | J14: FALSE | K14: FALSE
A15: br_birth | B15: Black Rhino Birth | C15: Rhino Management | D15: 874e243d-16d8-4ac9-89b3-24aaa163eb1f | E15: rhinobirth_watchkeepervalidation | F15: rhinobirth_watchkeepervalidation | G15: Watchkeeper Validation | H15: string | J15: FALSE | K15: FALSE
A16: br_birth | B16: Black Rhino Birth | C16: Rhino Management | D16: 874e243d-16d8-4ac9-89b3-24aaa163eb1f | E16: rhinobirth_actionschecklist | F16: rhinobirth_actionschecklist | J16: FALSE | K16: FALSE | W16: rhinobirth_actionschecklist

Sheet br_capture_record
A1: event_value | B1: event_name | C1: event_category_display | D1: event_category_id | E1: path | F1: json_key | G1: ui_title | H1: type | I1: format | J1: required | K1: is_array | L1: array_item_type | M1: enum_values | N1: enum_names | O1: inactive_enum | P1: enum_images | Q1: minimum | R1: maximum | S1: pattern | T1: default | U1: examples | V1: description | W1: key_ref | X1: notes
A2: br_capture_record | B2: Black Rhino Capture Record | C2: Rhino Management | D2: 874e243d-16d8-4ac9-89b3-24aaa163eb1f | E2: veterinaryofiicer_name | F2: veterinaryofiicer_name | G2: Veterinary Officer in Charge of Operation | H2: string | J2: FALSE | K2: FALSE
A3: br_capture_record | B3: Black Rhino Capture Record | C3: Rhino Management | D3: 874e243d-16d8-4ac9-89b3-24aaa163eb1f | E3: rhino_kfid | F3: rhino_kfid | G3: Kifaru ID | H3: string | J3: FALSE | K3: FALSE
A4: br_capture_record | B4: Black Rhino Capture Record | C4: Rhino Management | D4: 874e243d-16d8-4ac9-89b3-24aaa163eb1f | E4: rhino_name | F4: rhino_name | G4: Black Rhino Name | H4: string | J4: FALSE | K4: FALSE
A5: br_capture_record | B5: Black Rhino Capture Record | C5: Rhino Management | D5: 874e243d-16d8-4ac9-89b3-24aaa163eb1f | E5: birth_date | F5: birth_date | G5: Rhino Date of Birth | H5: string | I5: date | J5: FALSE | K5: FALSE
A6: br_capture_record | B6: Black Rhino Capture Record | C6: Rhino Management | D6: 874e243d-16d8-4ac9-89b3-24aaa163eb1f | E6: age | F6: age | G6: Age | H6: number | J6: FALSE | K6: FALSE | M6: a b c d e f | N6: {"a":"A (0-3 months)","b":"B (3 months - 1 year)","c":"C (1 - 2 years)","d":"D (2 - 3.5 years)","e":"E (3.5 - 7 years)","f":"F (adult 7+ years)"}
A7: br_capture_record | B7: Black Rhino Capture Record | C7: Rhino Management | D7: 874e243d-16d8-4ac9-89b3-24aaa163eb1f | E7: sex | F7: sex | G7: Sex | H7: string | J7: FALSE | K7: FALSE | M7: 2 1 | N7: {"1":"Male","2":"Female"}
A8: br_capture_record | B8: Black Rhino Capture Record | C8: Rhino Management | D8: 874e243d-16d8-4ac9-89b3-24aaa163eb1f | E8: condition | F8: condition | G8: Body Condition Score | H8: string | J8: FALSE | K8: FALSE | M8: one two two_half three three_half four four_half five | N8: {"five":"5","four":"4","four_half":"4.5","one":"1","three":"3","three_half":"3.5","two":"2","two_half":"2.5"} | P8: {"five":"string","four":"string","four_half":"string","one":"string","three":"string","three_half":"string","two":"string","two_half":"string"}
A9: br_capture_record | B9: Black Rhino Capture Record | C9: Rhino Management | D9: 874e243d-16d8-4ac9-89b3-24aaa163eb1f | E9: capture_date | F9: capture_date | G9: Capture Date | H9: string | I9: date | J9: FALSE | K9: FALSE
A10: br_capture_record | B10: Black Rhino Capture Record | C10: Rhino Management | D10: 874e243d-16d8-4ac9-89b3-24aaa163eb1f | E10: capture_location | F10: capture_location | G10: Capture Location | H10: string | J10: FALSE | K10: FALSE
A11: br_capture_record | B11: Black Rhino Capture Record | C11: Rhino Management | D11: 874e243d-16d8-4ac9-89b3-24aaa163eb1f | E11: weatherconditions | F11: weatherconditions | J11: FALSE | K11: FALSE | W11: weatherconditions
A12: br_capture_record | B12: Black Rhino Capture Record | C12: Rhino Management | D12: 874e243d-16d8-4ac9-89b3-24aaa163eb1f | E12: immobilization_reason | F12: immobilization_reason | J12: FALSE | K12: FALSE | W12: immobilization_reason
A13: br_capture_record | B13: Black Rhino Capture Record | C13: Rhino Management | D13: 874e243d-16d8-4ac9-89b3-24aaa163eb1f | E13: temperature | F13: temperature | G13: Air Temperature (*C) | H13: number | J13: FALSE | K13: FALSE
A14: br_capture_record | B14: Black Rhino Capture Record | C14: Rhino Management | D14: 874e243d-16d8-4ac9-89b3-24aaa163eb1f | E14: dart_in | F14: dart_in | G14: Time of Darting | H14: string | J14: FALSE | K14: FALSE
A15: br_capture_record | B15: Black Rhino Capture Record | C15: Rhino Management | D15: 874e243d-16d8-4ac9-89b3-24aaa163eb1f | E15: immobilization_period | F15: immobilization_period | G15: Total Duration of Immobilization (mins) | H15: number | J15: FALSE | K15: FALSE
A16: br_capture_record | B16: Black Rhino Capture Record | C16: Rhino Management | D16: 874e243d-16d8-4ac9-89b3-24aaa163eb1f | E16: ear_notch_number | F16: ear_notch_number | G16: Ear Notch Number | H16: number | J16: FALSE | K16: FALSE
A17: br_capture_record | B17: Black Rhino Capture Record | C17: Rhino Management | D17: 874e243d-16d8-4ac9-89b3-24aaa163eb1f | E17: microchip | F17: microchip | H17: array | J17: FALSE | K17: TRUE | L17: object
A18: br_capture_record | B18: Black Rhino Capture Record | C18: Rhino Management | D18: 874e243d-16d8-4ac9-89b3-24aaa163eb1f | E18: microchip[]..microchip_placement | F18: microchip_placement | G18: Microchip Placement | H18: string | J18: FALSE | K18: FALSE | N18: {}
A19: br_capture_record | B19: Black Rhino Capture Record | C19: Rhino Management | D19: 874e243d-16d8-4ac9-89b3-24aaa163eb1f | E19: microchip[]..microchip_no | F19: microchip_no | G19: Microchip Number | H19: string | J19: FALSE | K19: FALSE | Q19: 0
A20: br_capture_record | B20: Black Rhino Capture Record | C20: Rhino Management | D20: 874e243d-16d8-4ac9-89b3-24aaa163eb1f | E20: details_dt | F20: details_dt | H20: array | J20: FALSE | K20: TRUE | L20: object
A21: br_capture_record | B21: Black Rhino Capture Record | C21: Rhino Management | D21: 874e243d-16d8-4ac9-89b3-24aaa163eb1f | E21: details_dt[]..type_of_drug | F21: type_of_drug | G21: Type of Drug Administered | H21: string | J21: FALSE | K21: FALSE | N21: {}
A22: br_capture_record | B22: Black Rhino Capture Record | C22: Rhino Management | D22: 874e243d-16d8-4ac9-89b3-24aaa163eb1f | E22: details_dt[]..drug_amount | F22: drug_amount | G22: Amount Administered | H22: number | J22: FALSE | K22: FALSE | Q22: 0
A23: br_capture_record | B23: Black Rhino Capture Record | C23: Rhino Management | D23: 874e243d-16d8-4ac9-89b3-24aaa163eb1f | E23: transmitter | F23: transmitter | H23: array | J23: FALSE | K23: TRUE | L23: object
A24: br_capture_record | B24: Black Rhino Capture Record | C24: Rhino Management | D24: 874e243d-16d8-4ac9-89b3-24aaa163eb1f | E24: transmitter[]..transmitter_deployment | F24: transmitter_deployment | G24: Transmitter Deployment | H24: string | J24: FALSE | K24: FALSE | N24: {}
A25: br_capture_record | B25: Black Rhino Capture Record | C25: Rhino Management | D25: 874e243d-16d8-4ac9-89b3-24aaa163eb1f | E25: transmitter[]..transmitter_type | F25: transmitter_type | G25: Transmitter Type | H25: string | J25: FALSE | K25: FALSE | N25: {}
A26: br_capture_record | B26: Black Rhino Capture Record | C26: Rhino Management | D26: 874e243d-16d8-4ac9-89b3-24aaa163eb1f | E26: transmitter[]..transmitter_id_freq | F26: transmitter_id_freq | G26: Transmitter ID / Frequency | H26: string | J26: FALSE | K26: FALSE
A27: br_capture_record | B27: Black Rhino Capture Record | C27: Rhino Management | D27: 874e243d-16d8-4ac9-89b3-24aaa163eb1f | E27: observation_items | F27: observation_items | G27: Observations | H27: array | J27: FALSE | K27: TRUE | L27: object
A28: br_capture_record | B28: Black Rhino Capture Record | C28: Rhino Management | D28: 874e243d-16d8-4ac9-89b3-24aaa163eb1f | E28: observation_items[]..timestamp_one | F28: timestamp_one | G28: Time | H28: string | J28: FALSE | K28: FALSE
A29: br_capture_record | B29: Black Rhino Capture Record | C29: Rhino Management | D29: 874e243d-16d8-4ac9-89b3-24aaa163eb1f | E29: observation_items[]..observations_notes | F29: observations_notes | G29: OBSERVATIONS/NOTES | H29: string | J29: FALSE | K29: FALSE
A30: br_capture_record | B30: Black Rhino Capture Record | C30: Rhino Management | D30: 874e243d-16d8-4ac9-89b3-24aaa163eb1f | E30: observation_items[]..timestamp_two | F30: timestamp_two | G30: time | H30: string | J30: FALSE | K30: FALSE
A31: br_capture_record | B31: Black Rhino Capture Record | C31: Rhino Management | D31: 874e243d-16d8-4ac9-89b3-24aaa163eb1f | E31: observation_items[]..oxygen_sat | F31: oxygen_sat | G31: O2 Sat | H31: string | J31: FALSE | K31: FALSE
A32: br_capture_record | B32: Black Rhino Capture Record | C32: Rhino Management | D32: 874e243d-16d8-4ac9-89b3-24aaa163eb1f | E32: observation_items[]..respiration | F32: respiration | G32: RESP | H32: string | J32: FALSE | K32: FALSE
A33: br_capture_record | B33: Black Rhino Capture Record | C33: Rhino Management | D33: 874e243d-16d8-4ac9-89b3-24aaa163eb1f | E33: observation_items[]..heart_beat | F33: heart_beat | G33: HR | H33: string | J33: FALSE | K33: FALSE
A34: br_capture_record | B34: Black Rhino Capture Record | C34: Rhino Management | D34: 874e243d-16d8-4ac9-89b3-24aaa163eb1f | E34: observation_items[]..temp | F34: temp | G34: TEMP | H34: string | J34: FALSE | K34: FALSE
A35: br_capture_record | B35: Black Rhino Capture Record | C35: Rhino Management | D35: 874e243d-16d8-4ac9-89b3-24aaa163eb1f | E35: er2er_src_id | F35: er2er_src_id | G35: Event Type Serial Number from Source ER System | H35: string | J35: FALSE | K35: FALSE
A36: br_capture_record | B36: Black Rhino Capture Record | C36: Rhino Management | D36: 874e243d-16d8-4ac9-89b3-24aaa163eb1f | E36: er2er_src_system | F36: er2er_src_system | G36: Name of Source ER System | H36: string | J36: FALSE | K36: FALSE
A37: br_capture_record | B37: Black Rhino Capture Record | C37: Rhino Management | D37: 874e243d-16d8-4ac9-89b3-24aaa163eb1f | E37: er2er_src_serial_number | F37: er2er_src_serial_number | G37: Serial Number of Source Event | H37: string | J37: FALSE | K37: FALSE
